Workbook

Sheet Deals Won (Live update)
C1: WorkDrive Presales - Deals Won (Live Dashboard) - 2026
C3: Auto-calculated from all 12 monthly tabs. Mark any row "Deal Won" anywhere including later-month conversions and every figure & chart updates automatically.
B5: TOTAL DEALS WON | E5: TOTAL DEALS LOST | H5: IN PROGRESS | J5: WIN RATE
B6: =COUNTIF('January'!$P$2:$P$2000,"Deal Won")+COUNTIF('February'!$P$2:$P$2000,"Deal Won")+COUNTIF('March'!$P$2:$P$2000,"Deal Won")+COUNTIF('April'!$P$2:$P$2000,"Deal Won")+COUNTIF('May'!$P$2:$P$2000,"Deal Won")+COUNTIF('June'!$P$2:$P$2002,"Deal Won")+COUNTIF('July'!$P$2:$P$2000,"Deal Won")+COUNTIF('August'!$P$2:$P$2000,"Deal Won")+COUNTIF('September'!$P$2:$P$2000,"Deal Won")+COUNTIF('October'!$P$2:$P$2000,"Deal Won")+COUNTIF('November'!$P$2:$P$2000,"Deal Won")+COUNTIF('December'!$P$2:$P$2000,"Deal Won") -> 129 | E6: =COUNTIF('January'!$P$2:$P$2000,"Deal Lost")+COUNTIF('February'!$P$2:$P$2000,"Deal Lost")+COUNTIF('March'!$P$2:$P$2000,"Deal Lost")+COUNTIF('April'!$P$2:$P$2000,"Deal Lost")+COUNTIF('May'!$P$2:$P$2000,"Deal Lost")+COUNTIF('June'!$P$2:$P$2002,"Deal Lost")+COUNTIF('July'!$P$2:$P$2000,"Deal Lost")+COUNTIF('August'!$P$2:$P$2000,"Deal Lost")+COUNTIF('September'!$P$2:$P$2000,"Deal Lost")+COUNTIF('October'!$P$2:$P$2000,"Deal Lost")+COUNTIF('November'!$P$2:$P$2000,"Deal Lost")+COUNTIF('December'!$P$2:$P$2000,"Deal Lost") -> 238 | H6: =COUNTIF('January'!$P$2:$P$2000,"In Progress")+COUNTIF('February'!$P$2:$P$2000,"In Progress")+COUNTIF('March'!$P$2:$P$2000,"In Progress")+COUNTIF('April'!$P$2:$P$2000,"In Progress")+COUNTIF('May'!$P$2:$P$2000,"In Progress")+COUNTIF('June'!$P$2:$P$2002,"In Progress")+COUNTIF('July'!$P$2:$P$2000,"In Progress")+COUNTIF('August'!$P$2:$P$2000,"In Progress")+COUNTIF('September'!$P$2:$P$2000,"In Progress")+COUNTIF('October'!$P$2:$P$2000,"In Progress")+COUNTIF('November'!$P$2:$P$2000,"In Progress")+COUNTIF('December'!$P$2:$P$2000,"In Progress") -> 87 | J6: =IF(B6+E6=0,0,B6/(B6+E6)) -> 0.35149864
A9: DEALS WON BY MONTH (live count per tab)
A10: Month | B10: Demos Logged | C10: Deal Won | D10: Deal Lost | E10: In Progress | F10: Win %
A11: January | B11: =COUNTIF('January'!$P$2:$P$2000,"Deal Won")+COUNTIF('January'!$P$2:$P$2000,"Deal Lost")+COUNTIF('January'!$P$2:$P$2000,"In Progress")+COUNTIF('January'!$P$2:$P$2000,"Existing customer")+COUNTIF('January'!$P$2:$P$2000,"No Scope for WD")+COUNTIF('January'!$P$2:$P$2000,"Free user")+COUNTIF('January'!$P$2:$P$2000,"Partner") -> 99 | C11: =COUNTIF('January'!$P$2:$P$2000,"Deal Won") -> 31 | D11: =COUNTIF('January'!$P$2:$P$2000,"Deal Lost") -> 53 | E11: =COUNTIF('January'!$P$2:$P$2000,"In Progress") -> 0 | F11: =IF(C11+D11=0,0,C11/(C11+D11)) -> 0.36904762 | Z11: Demos Logged | AA11: Month | AB11: New-Prospect Demos | AC11: Non-prospects
A12: February | B12: =COUNTIF('February'!$P$2:$P$2000,"Deal Won")+COUNTIF('February'!$P$2:$P$2000,"Deal Lost")+COUNTIF('February'!$P$2:$P$2000,"In Progress")+COUNTIF('February'!$P$2:$P$2000,"Existing customer")+COUNTIF('February'!$P$2:$P$2000,"No Scope for WD")+COUNTIF('February'!$P$2:$P$2000,"Free user")+COUNTIF('February'!$P$2:$P$2000,"Partner") -> 98 | C12: =COUNTIF('February'!$P$2:$P$2000,"Deal Won") -> 25 | D12: =COUNTIF('February'!$P$2:$P$2000,"Deal Lost") -> 57 | E12: =COUNTIF('February'!$P$2:$P$2000,"In Progress") -> 3 | F12: =IF(C12+D12=0,0,C12/(C12+D12)) -> 0.30487805 | Z12: =COUNTIF('January'!$P$2:$P$2000,"Deal Won")+COUNTIF('January'!$P$2:$P$2000,"Deal Lost")+COUNTIF('January'!$P$2:$P$2000,"In Progress")+COUNTIF('January'!$P$2:$P$2000,"Existing customer")+COUNTIF('January'!$P$2:$P$2000,"No Scope for WD")+COUNTIF('January'!$P$2:$P$2000,"Free user")+COUNTIF('January'!$P$2:$P$2000,"Partner") -> 99 | AA12: January | AB12: =COUNTIFS('January'!$P$2:$P$2000,"Deal Won",'January'!$N$2:$N$2000,"New Prospect")+COUNTIFS('January'!$P$2:$P$2000,"Deal Lost",'January'!$N$2:$N$2000,"New Prospect")+COUNTIFS('January'!$P$2:$P$2000,"In Progress",'January'!$N$2:$N$2000,"New Prospect") -> 79 | AC12: =Z12-AB12 -> 20
A13: March | B13: =COUNTIF('March'!$P$2:$P$2000,"Deal Won")+COUNTIF('March'!$P$2:$P$2000,"Deal Lost")+COUNTIF('March'!$P$2:$P$2000,"In Progress")+COUNTIF('March'!$P$2:$P$2000,"Existing customer")+COUNTIF('March'!$P$2:$P$2000,"No Scope for WD")+COUNTIF('March'!$P$2:$P$2000,"Free user")+COUNTIF('March'!$P$2:$P$2000,"Partner") -> 117 | C13: =COUNTIF('March'!$P$2:$P$2000,"Deal Won") -> 28 | D13: =COUNTIF('March'!$P$2:$P$2000,"Deal Lost") -> 48 | E13: =COUNTIF('March'!$P$2:$P$2000,"In Progress") -> 10 | F13: =IF(C13+D13=0,0,C13/(C13+D13)) -> 0.36842105 | Z13: =COUNTIF('February'!$P$2:$P$2000,"Deal Won")+COUNTIF('February'!$P$2:$P$2000,"Deal Lost")+COUNTIF('February'!$P$2:$P$2000,"In Progress")+COUNTIF('February'!$P$2:$P$2000,"Existing customer")+COUNTIF('February'!$P$2:$P$2000,"No Scope for WD")+COUNTIF('February'!$P$2:$P$2000,"Free user")+COUNTIF('February'!$P$2:$P$2000,"Partner") -> 98 | AA13: February | AB13: =COUNTIFS('February'!$P$2:$P$2000,"Deal Won",'February'!$N$2:$N$2000,"New Prospect")+COUNTIFS('February'!$P$2:$P$2000,"Deal Lost",'February'!$N$2:$N$2000,"New Prospect")+COUNTIFS('February'!$P$2:$P$2000,"In Progress",'February'!$N$2:$N$2000,"New Prospect") -> 71 | AC13: =Z13-AB13 -> 27
A14: April | B14: =COUNTIF('April'!$P$2:$P$2000,"Deal Won")+COUNTIF('April'!$P$2:$P$2000,"Deal Lost")+COUNTIF('April'!$P$2:$P$2000,"In Progress")+COUNTIF('April'!$P$2:$P$2000,"Existing customer")+COUNTIF('April'!$P$2:$P$2000,"No Scope for WD")+COUNTIF('April'!$P$2:$P$2000,"Free user")+COUNTIF('April'!$P$2:$P$2000,"Partner") -> 105 | C14: =COUNTIF('April'!$P$2:$P$2000,"Deal Won") -> 28 | D14: =COUNTIF('April'!$P$2:$P$2000,"Deal Lost") -> 38 | E14: =COUNTIF('April'!$P$2:$P$2000,"In Progress") -> 13 | F14: =IF(C14+D14=0,0,C14/(C14+D14)) -> 0.42424242 | Z14: =COUNTIF('March'!$P$2:$P$2000,"Deal Won")+COUNTIF('March'!$P$2:$P$2000,"Deal Lost")+COUNTIF('March'!$P$2:$P$2000,"In Progress")+COUNTIF('March'!$P$2:$P$2000,"Existing customer")+COUNTIF('March'!$P$2:$P$2000,"No Scope for WD")+COUNTIF('March'!$P$2:$P$2000,"Free user")+COUNTIF('March'!$P$2:$P$2000,"Partner") -> 117 | AA14: March | AB14: =COUNTIFS('March'!$P$2:$P$2000,"Deal Won",'March'!$N$2:$N$2000,"New Prospect")+COUNTIFS('March'!$P$2:$P$2000,"Deal Lost",'March'!$N$2:$N$2000,"New Prospect")+COUNTIFS('March'!$P$2:$P$2000,"In Progress",'March'!$N$2:$N$2000,"New Prospect") -> 74 | AC14: =Z14-AB14 -> 43
A15: May | B15: =COUNTIF('May'!$P$2:$P$2000,"Deal Won")+COUNTIF('May'!$P$2:$P$2000,"Deal Lost")+COUNTIF('May'!$P$2:$P$2000,"In Progress")+COUNTIF('May'!$P$2:$P$2000,"Existing customer")+COUNTIF('May'!$P$2:$P$2000,"No Scope for WD")+COUNTIF('May'!$P$2:$P$2000,"Free user")+COUNTIF('May'!$P$2:$P$2000,"Partner") -> 97 | C15: =COUNTIF('May'!$P$2:$P$2000,"Deal Won") -> 15 | D15: =COUNTIF('May'!$P$2:$P$2000,"Deal Lost") -> 41 | E15: =COUNTIF('May'!$P$2:$P$2000,"In Progress") -> 19 | F15: =IF(C15+D15=0,0,C15/(C15+D15)) -> 0.26785714 | Z15: =COUNTIF('April'!$P$2:$P$2000,"Deal Won")+COUNTIF('April'!$P$2:$P$2000,"Deal Lost")+COUNTIF('April'!$P$2:$P$2000,"In Progress")+COUNTIF('April'!$P$2:$P$2000,"Existing customer")+COUNTIF('April'!$P$2:$P$2000,"No Scope for WD")+COUNTIF('April'!$P$2:$P$2000,"Free user")+COUNTIF('April'!$P$2:$P$2000,"Partner") -> 105 | AA15: April | AB15: =COUNTIFS('April'!$P$2:$P$2000,"Deal Won",'April'!$N$2:$N$2000,"New Prospect")+COUNTIFS('April'!$P$2:$P$2000,"Deal Lost",'April'!$N$2:$N$2000,"New Prospect")+COUNTIFS('April'!$P$2:$P$2000,"In Progress",'April'!$N$2:$N$2000,"New Prospect") -> 61 | AC15: =Z15-AB15 -> 44
A16: June | B16: =COUNTIF('June'!$P$2:$P$2002,"Deal Won")+COUNTIF('June'!$P$2:$P$2002,"Deal Lost")+COUNTIF('June'!$P$2:$P$2002,"In Progress")+COUNTIF('June'!$P$2:$P$2002,"Existing customer")+COUNTIF('June'!$P$2:$P$2002,"No Scope for WD")+COUNTIF('June'!$P$2:$P$2002,"Free user")+COUNTIF('June'!$P$2:$P$2002,"Partner") -> 54 | C16: =COUNTIF('June'!$P$2:$P$2002,"Deal Won") -> 2 | D16: =COUNTIF('June'!$P$2:$P$2002,"Deal Lost") -> 1 | E16: =COUNTIF('June'!$P$2:$P$2002,"In Progress") -> 42 | F16: =IF(C16+D16=0,0,C16/(C16+D16)) -> 0.66666667 | Z16: =COUNTIF('May'!$P$2:$P$2000,"Deal Won")+COUNTIF('May'!$P$2:$P$2000,"Deal Lost")+COUNTIF('May'!$P$2:$P$2000,"In Progress")+COUNTIF('May'!$P$2:$P$2000,"Existing customer")+COUNTIF('May'!$P$2:$P$2000,"No Scope for WD")+COUNTIF('May'!$P$2:$P$2000,"Free user")+COUNTIF('May'!$P$2:$P$2000,"Partner") -> 97 | AA16: May | AB16: =COUNTIFS('May'!$P$2:$P$2000,"Deal Won",'May'!$N$2:$N$2000,"New Prospect")+COUNTIFS('May'!$P$2:$P$2000,"Deal Lost",'May'!$N$2:$N$2000,"New Prospect")+COUNTIFS('May'!$P$2:$P$2000,"In Progress",'May'!$N$2:$N$2000,"New Prospect") -> 63 | AC16: =Z16-AB16 -> 34
A17: July | B17: =COUNTIF('July'!$P$2:$P$2000,"Deal Won")+COUNTIF('July'!$P$2:$P$2000,"Deal Lost")+COUNTIF('July'!$P$2:$P$2000,"In Progress")+COUNTIF('July'!$P$2:$P$2000,"Existing customer")+COUNTIF('July'!$P$2:$P$2000,"No Scope for WD")+COUNTIF('July'!$P$2:$P$2000,"Free user")+COUNTIF('July'!$P$2:$P$2000,"Partner") -> 0 | C17: =COUNTIF('July'!$P$2:$P$2000,"Deal Won") -> 0 | D17: =COUNTIF('July'!$P$2:$P$2000,"Deal Lost") -> 0 | E17: =COUNTIF('July'!$P$2:$P$2000,"In Progress") -> 0 | F17: =IF(C17+D17=0,0,C17/(C17+D17)) -> 0 | Z17: =COUNTIF('June'!$P$2:$P$2002,"Deal Won")+COUNTIF('June'!$P$2:$P$2002,"Deal Lost")+COUNTIF('June'!$P$2:$P$2002,"In Progress")+COUNTIF('June'!$P$2:$P$2002,"Existing customer")+COUNTIF('June'!$P$2:$P$2002,"No Scope for WD")+COUNTIF('June'!$P$2:$P$2002,"Free user")+COUNTIF('June'!$P$2:$P$2002,"Partner") -> 54 | AA17: June | AB17: =COUNTIFS('June'!$P$2:$P$2002,"Deal Won",'June'!$N$2:$N$2002,"New Prospect")+COUNTIFS('June'!$P$2:$P$2002,"Deal Lost",'June'!$N$2:$N$2002,"New Prospect")+COUNTIFS('June'!$P$2:$P$2002,"In Progress",'June'!$N$2:$N$2002,"New Prospect") -> 38 | AC17: =Z17-AB17 -> 16
A18: August | B18: =COUNTIF('August'!$P$2:$P$2000,"Deal Won")+COUNTIF('August'!$P$2:$P$2000,"Deal Lost")+COUNTIF('August'!$P$2:$P$2000,"In Progress")+COUNTIF('August'!$P$2:$P$2000,"Existing customer")+COUNTIF('August'!$P$2:$P$2000,"No Scope for WD")+COUNTIF('August'!$P$2:$P$2000,"Free user")+COUNTIF('August'!$P$2:$P$2000,"Partner") -> 0 | C18: =COUNTIF('August'!$P$2:$P$2000,"Deal Won") -> 0 | D18: =COUNTIF('August'!$P$2:$P$2000,"Deal Lost") -> 0 | E18: =COUNTIF('August'!$P$2:$P$2000,"In Progress") -> 0 | F18: =IF(C18+D18=0,0,C18/(C18+D18)) -> 0 | Z18: =COUNTIF('July'!$P$2:$P$2000,"Deal Won")+COUNTIF('July'!$P$2:$P$2000,"Deal Lost")+COUNTIF('July'!$P$2:$P$2000,"In Progress")+COUNTIF('July'!$P$2:$P$2000,"Existing customer")+COUNTIF('July'!$P$2:$P$2000,"No Scope for WD")+COUNTIF('July'!$P$2:$P$2000,"Free user")+COUNTIF('July'!$P$2:$P$2000,"Partner") -> 0 | AA18: July | AB18: =COUNTIFS('July'!$P$2:$P$2000,"Deal Won",'July'!$N$2:$N$2000,"New Prospect")+COUNTIFS('July'!$P$2:$P$2000,"Deal Lost",'July'!$N$2:$N$2000,"New Prospect")+COUNTIFS('July'!$P$2:$P$2000,"In Progress",'July'!$N$2:$N$2000,"New Prospect") -> 0 | AC18: =Z18-AB18 -> 0
A19: September | B19: =COUNTIF('September'!$P$2:$P$2000,"Deal Won")+COUNTIF('September'!$P$2:$P$2000,"Deal Lost")+COUNTIF('September'!$P$2:$P$2000,"In Progress")+COUNTIF('September'!$P$2:$P$2000,"Existing customer")+COUNTIF('September'!$P$2:$P$2000,"No Scope for WD")+COUNTIF('September'!$P$2:$P$2000,"Free user")+COUNTIF('September'!$P$2:$P$2000,"Partner") -> 0 | C19: =COUNTIF('September'!$P$2:$P$2000,"Deal Won") -> 0 | D19: =COUNTIF('September'!$P$2:$P$2000,"Deal Lost") -> 0 | E19: =COUNTIF('September'!$P$2:$P$2000,"In Progress") -> 0 | F19: =IF(C19+D19=0,0,C19/(C19+D19)) -> 0 | Z19: =COUNTIF('August'!$P$2:$P$2000,"Deal Won")+COUNTIF('August'!$P$2:$P$2000,"Deal Lost")+COUNTIF('August'!$P$2:$P$2000,"In Progress")+COUNTIF('August'!$P$2:$P$2000,"Existing customer")+COUNTIF('August'!$P$2:$P$2000,"No Scope for WD")+COUNTIF('August'!$P$2:$P$2000,"Free user")+COUNTIF('August'!$P$2:$P$2000,"Partner") -> 0 | AA19: August | AB19: =COUNTIFS('August'!$P$2:$P$2000,"Deal Won",'August'!$N$2:$N$2000,"New Prospect")+COUNTIFS('August'!$P$2:$P$2000,"Deal Lost",'August'!$N$2:$N$2000,"New Prospect")+COUNTIFS('August'!$P$2:$P$2000,"In Progress",'August'!$N$2:$N$2000,"New Prospect") -> 0 | AC19: =Z19-AB19 -> 0
A20: October | B20: =COUNTIF('October'!$P$2:$P$2000,"Deal Won")+COUNTIF('October'!$P$2:$P$2000,"Deal Lost")+COUNTIF('October'!$P$2:$P$2000,"In Progress")+COUNTIF('October'!$P$2:$P$2000,"Existing customer")+COUNTIF('October'!$P$2:$P$2000,"No Scope for WD")+COUNTIF('October'!$P$2:$P$2000,"Free user")+COUNTIF('October'!$P$2:$P$2000,"Partner") -> 0 | C20: =COUNTIF('October'!$P$2:$P$2000,"Deal Won") -> 0 | D20: =COUNTIF('October'!$P$2:$P$2000,"Deal Lost") -> 0 | E20: =COUNTIF('October'!$P$2:$P$2000,"In Progress") -> 0 | F20: =IF(C20+D20=0,0,C20/(C20+D20)) -> 0 | Z20: =COUNTIF('September'!$P$2:$P$2000,"Deal Won")+COUNTIF('September'!$P$2:$P$2000,"Deal Lost")+COUNTIF('September'!$P$2:$P$2000,"In Progress")+COUNTIF('September'!$P$2:$P$2000,"Existing customer")+COUNTIF('September'!$P$2:$P$2000,"No Scope for WD")+COUNTIF('September'!$P$2:$P$2000,"Free user")+COUNTIF('September'!$P$2:$P$2000,"Partner") -> 0 | AA20: September | AB20: =COUNTIFS('September'!$P$2:$P$2000,"Deal Won",'September'!$N$2:$N$2000,"New Prospect")+COUNTIFS('September'!$P$2:$P$2000,"Deal Lost",'September'!$N$2:$N$2000,"New Prospect")+COUNTIFS('September'!$P$2:$P$2000,"In Progress",'September'!$N$2:$N$2000,"New Prospect") -> 0 | AC20: =Z20-AB20 -> 0
A21: November | B21: =COUNTIF('November'!$P$2:$P$2000,"Deal Won")+COUNTIF('November'!$P$2:$P$2000,"Deal Lost")+COUNTIF('November'!$P$2:$P$2000,"In Progress")+COUNTIF('November'!$P$2:$P$2000,"Existing customer")+COUNTIF('November'!$P$2:$P$2000,"No Scope for WD")+COUNTIF('November'!$P$2:$P$2000,"Free user")+COUNTIF('November'!$P$2:$P$2000,"Partner") -> 0 | C21: =COUNTIF('November'!$P$2:$P$2000,"Deal Won") -> 0 | D21: =COUNTIF('November'!$P$2:$P$2000,"Deal Lost") -> 0 | E21: =COUNTIF('November'!$P$2:$P$2000,"In Progress") -> 0 | F21: =IF(C21+D21=0,0,C21/(C21+D21)) -> 0 | Z21: =COUNTIF('October'!$P$2:$P$2000,"Deal Won")+COUNTIF('October'!$P$2:$P$2000,"Deal Lost")+COUNTIF('October'!$P$2:$P$2000,"In Progress")+COUNTIF('October'!$P$2:$P$2000,"Existing customer")+COUNTIF('October'!$P$2:$P$2000,"No Scope for WD")+COUNTIF('October'!$P$2:$P$2000,"Free user")+COUNTIF('October'!$P$2:$P$2000,"Partner") -> 0 | AA21: October | AB21: =COUNTIFS('October'!$P$2:$P$2000,"Deal Won",'October'!$N$2:$N$2000,"New Prospect")+COUNTIFS('October'!$P$2:$P$2000,"Deal Lost",'October'!$N$2:$N$2000,"New Prospect")+COUNTIFS('October'!$P$2:$P$2000,"In Progress",'October'!$N$2:$N$2000,"New Prospect") -> 0 | AC21: =Z21-AB21 -> 0
A22: December | B22: =COUNTIF('December'!$P$2:$P$2000,"Deal Won")+COUNTIF('December'!$P$2:$P$2000,"Deal Lost")+COUNTIF('December'!$P$2:$P$2000,"In Progress")+COUNTIF('December'!$P$2:$P$2000,"Existing customer")+COUNTIF('December'!$P$2:$P$2000,"No Scope for WD")+COUNTIF('December'!$P$2:$P$2000,"Free user")+COUNTIF('December'!$P$2:$P$2000,"Partner") -> 0 | C22: =COUNTIF('December'!$P$2:$P$2000,"Deal Won") -> 0 | D22: =COUNTIF('December'!$P$2:$P$2000,"Deal Lost") -> 0 | E22: =COUNTIF('December'!$P$2:$P$2000,"In Progress") -> 0 | F22: =IF(C22+D22=0,0,C22/(C22+D22)) -> 0 | Z22: =COUNTIF('November'!$P$2:$P$2000,"Deal Won")+COUNTIF('November'!$P$2:$P$2000,"Deal Lost")+COUNTIF('November'!$P$2:$P$2000,"In Progress")+COUNTIF('November'!$P$2:$P$2000,"Existing customer")+COUNTIF('November'!$P$2:$P$2000,"No Scope for WD")+COUNTIF('November'!$P$2:$P$2000,"Free user")+COUNTIF('November'!$P$2:$P$2000,"Partner") -> 0 | AA22: November | AB22: =COUNTIFS('November'!$P$2:$P$2000,"Deal Won",'November'!$N$2:$N$2000,"New Prospect")+COUNTIFS('November'!$P$2:$P$2000,"Deal Lost",'November'!$N$2:$N$2000,"New Prospect")+COUNTIFS('November'!$P$2:$P$2000,"In Progress",'November'!$N$2:$N$2000,"New Prospect") -> 0 | AC22: =Z22-AB22 -> 0
A23: TOTAL | B23: =SUM(B11:B22) -> 570 | C23: =SUM(C11:C22) -> 129 | D23: =SUM(D11:D22) -> 238 | E23: =SUM(E11:E22) -> 87 | F23: =IF(C23+D23=0,0,C23/(C23+D23)) -> 0.35149864 | Z23: =COUNTIF('December'!$P$2:$P$2000,"Deal Won")+COUNTIF('December'!$P$2:$P$2000,"Deal Lost")+COUNTIF('December'!$P$2:$P$2000,"In Progress")+COUNTIF('December'!$P$2:$P$2000,"Existing customer")+COUNTIF('December'!$P$2:$P$2000,"No Scope for WD")+COUNTIF('December'!$P$2:$P$2000,"Free user")+COUNTIF('December'!$P$2:$P$2000,"Partner") -> 0 | AA23: December | AB23: =COUNTIFS('December'!$P$2:$P$2000,"Deal Won",'December'!$N$2:$N$2000,"New Prospect")+COUNTIFS('December'!$P$2:$P$2000,"Deal Lost",'December'!$N$2:$N$2000,"New Prospect")+COUNTIFS('December'!$P$2:$P$2000,"In Progress",'December'!$N$2:$N$2000,"New Prospect") -> 0 | AC23: =Z23-AB23 -> 0
A26: NEW-PROSPECT CONVERSION
A27: Month | B27: New-Prospect Demos | C27: Deal Won | D27: Deal Lost | E27: In Progress | F27: Conversion %
A28: January | B28: =COUNTIFS('January'!$P$2:$P$2000,"Deal Won",'January'!$N$2:$N$2000,"New Prospect")+COUNTIFS('January'!$P$2:$P$2000,"Deal Lost",'January'!$N$2:$N$2000,"New Prospect")+COUNTIFS('January'!$P$2:$P$2000,"In Progress",'January'!$N$2:$N$2000,"New Prospect") -> 79 | C28: =COUNTIFS('January'!$P$2:$P$2000,"Deal Won",'January'!$N$2:$N$2000,"New Prospect") -> 28 | D28: =COUNTIFS('January'!$P$2:$P$2000,"Deal Lost",'January'!$N$2:$N$2000,"New Prospect") -> 51 | E28: =COUNTIFS('January'!$P$2:$P$2000,"In Progress",'January'!$N$2:$N$2000,"New Prospect") -> 0 | F28: =IF(B28=0,0,C28/B28) -> 0.35443038
A29: February | B29: =COUNTIFS('February'!$P$2:$P$2000,"Deal Won",'February'!$N$2:$N$2000,"New Prospect")+COUNTIFS('February'!$P$2:$P$2000,"Deal Lost",'February'!$N$2:$N$2000,"New Prospect")+COUNTIFS('February'!$P$2:$P$2000,"In Progress",'February'!$N$2:$N$2000,"New Prospect") -> 71 | C29: =COUNTIFS('February'!$P$2:$P$2000,"Deal Won",'February'!$N$2:$N$2000,"New Prospect") -> 21 | D29: =COUNTIFS('February'!$P$2:$P$2000,"Deal Lost",'February'!$N$2:$N$2000,"New Prospect") -> 48 | E29: =COUNTIFS('February'!$P$2:$P$2000,"In Progress",'February'!$N$2:$N$2000,"New Prospect") -> 2 | F29: =IF(B29=0,0,C29/B29) -> 0.29577465
A30: March | B30: =COUNTIFS('March'!$P$2:$P$2000,"Deal Won",'March'!$N$2:$N$2000,"New Prospect")+COUNTIFS('March'!$P$2:$P$2000,"Deal Lost",'March'!$N$2:$N$2000,"New Prospect")+COUNTIFS('March'!$P$2:$P$2000,"In Progress",'March'!$N$2:$N$2000,"New Prospect") -> 74 | C30: =COUNTIFS('March'!$P$2:$P$2000,"Deal Won",'March'!$N$2:$N$2000,"New Prospect") -> 25 | D30: =COUNTIFS('March'!$P$2:$P$2000,"Deal Lost",'March'!$N$2:$N$2000,"New Prospect") -> 43 | E30: =COUNTIFS('March'!$P$2:$P$2000,"In Progress",'March'!$N$2:$N$2000,"New Prospect") -> 6 | F30: =IF(B30=0,0,C30/B30) -> 0.33783784
A31: April | B31: =COUNTIFS('April'!$P$2:$P$2000,"Deal Won",'April'!$N$2:$N$2000,"New Prospect")+COUNTIFS('April'!$P$2:$P$2000,"Deal Lost",'April'!$N$2:$N$2000,"New Prospect")+COUNTIFS('April'!$P$2:$P$2000,"In Progress",'April'!$N$2:$N$2000,"New Prospect") -> 61 | C31: =COUNTIFS('April'!$P$2:$P$2000,"Deal Won",'April'!$N$2:$N$2000,"New Prospect") -> 21 | D31: =COUNTIFS('April'!$P$2:$P$2000,"Deal Lost",'April'!$N$2:$N$2000,"New Prospect") -> 32 | E31: =COUNTIFS('April'!$P$2:$P$2000,"In Progress",'April'!$N$2:$N$2000,"New Prospect") -> 8 | F31: =IF(B31=0,0,C31/B31) -> 0.3442623
A32: May | B32: =COUNTIFS('May'!$P$2:$P$2000,"Deal Won",'May'!$N$2:$N$2000,"New Prospect")+COUNTIFS('May'!$P$2:$P$2000,"Deal Lost",'May'!$N$2:$N$2000,"New Prospect")+COUNTIFS('May'!$P$2:$P$2000,"In Progress",'May'!$N$2:$N$2000,"New Prospect") -> 63 | C32: =COUNTIFS('May'!$P$2:$P$2000,"Deal Won",'May'!$N$2:$N$2000,"New Prospect") -> 10 | D32: =COUNTIFS('May'!$P$2:$P$2000,"Deal Lost",'May'!$N$2:$N$2000,"New Prospect") -> 37 | E32: =COUNTIFS('May'!$P$2:$P$2000,"In Progress",'May'!$N$2:$N$2000,"New Prospect") -> 16 | F32: =IF(B32=0,0,C32/B32) -> 0.15873016
A33: June | B33: =COUNTIFS('June'!$P$2:$P$2002,"Deal Won",'June'!$N$2:$N$2002,"New Prospect")+COUNTIFS('June'!$P$2:$P$2002,"Deal Lost",'June'!$N$2:$N$2002,"New Prospect")+COUNTIFS('June'!$P$2:$P$2002,"In Progress",'June'!$N$2:$N$2002,"New Prospect") -> 38 | C33: =COUNTIFS('June'!$P$2:$P$2002,"Deal Won",'June'!$N$2:$N$2002,"New Prospect") -> 2 | D33: =COUNTIFS('June'!$P$2:$P$2002,"Deal Lost",'June'!$N$2:$N$2002,"New Prospect") -> 0 | E33: =COUNTIFS('June'!$P$2:$P$2002,"In Progress",'June'!$N$2:$N$2002,"New Prospect") -> 36 | F33: =IF(B33=0,0,C33/B33) -> 0.052631579
A34: July | B34: =COUNTIFS('July'!$P$2:$P$2000,"Deal Won",'July'!$N$2:$N$2000,"New Prospect")+COUNTIFS('July'!$P$2:$P$2000,"Deal Lost",'July'!$N$2:$N$2000,"New Prospect")+COUNTIFS('July'!$P$2:$P$2000,"In Progress",'July'!$N$2:$N$2000,"New Prospect") -> 0 | C34: =COUNTIFS('July'!$P$2:$P$2000,"Deal Won",'July'!$N$2:$N$2000,"New Prospect") -> 0 | D34: =COUNTIFS('July'!$P$2:$P$2000,"Deal Lost",'July'!$N$2:$N$2000,"New Prospect") -> 0 | E34: =COUNTIFS('July'!$P$2:$P$2000,"In Progress",'July'!$N$2:$N$2000,"New Prospect") -> 0 | F34: =IF(B34=0,0,C34/B34) -> 0
A35: August | B35: =COUNTIFS('August'!$P$2:$P$2000,"Deal Won",'August'!$N$2:$N$2000,"New Prospect")+COUNTIFS('August'!$P$2:$P$2000,"Deal Lost",'August'!$N$2:$N$2000,"New Prospect")+COUNTIFS('August'!$P$2:$P$2000,"In Progress",'August'!$N$2:$N$2000,"New Prospect") -> 0 | C35: =COUNTIFS('August'!$P$2:$P$2000,"Deal Won",'August'!$N$2:$N$2000,"New Prospect") -> 0 | D35: =COUNTIFS('August'!$P$2:$P$2000,"Deal Lost",'August'!$N$2:$N$2000,"New Prospect") -> 0 | E35: =COUNTIFS('August'!$P$2:$P$2000,"In Progress",'August'!$N$2:$N$2000,"New Prospect") -> 0 | F35: =IF(B35=0,0,C35/B35) -> 0
A36: September | B36: =COUNTIFS('September'!$P$2:$P$2000,"Deal Won",'September'!$N$2:$N$2000,"New Prospect")+COUNTIFS('September'!$P$2:$P$2000,"Deal Lost",'September'!$N$2:$N$2000,"New Prospect")+COUNTIFS('September'!$P$2:$P$2000,"In Progress",'September'!$N$2:$N$2000,"New Prospect") -> 0 | C36: =COUNTIFS('September'!$P$2:$P$2000,"Deal Won",'January'!$N$2:$N$2000,"New Prospect") -> 0 | D36: =COUNTIFS('September'!$P$2:$P$2000,"Deal Lost",'September'!$N$2:$N$2000,"New Prospect") -> 0 | E36: =COUNTIFS('September'!$P$2:$P$2000,"In Progress",'September'!$N$2:$N$2000,"New Prospect") -> 0 | F36: =IF(B36=0,0,C36/B36) -> 0
A37: October | B37: =COUNTIFS('October'!$P$2:$P$2000,"Deal Won",'October'!$N$2:$N$2000,"New Prospect")+COUNTIFS('October'!$P$2:$P$2000,"Deal Lost",'October'!$N$2:$N$2000,"New Prospect")+COUNTIFS('October'!$P$2:$P$2000,"In Progress",'October'!$N$2:$N$2000,"New Prospect") -> 0 | C37: =COUNTIFS('October'!$P$2:$P$2000,"Deal Won",'October'!$N$2:$N$2000,"New Prospect") -> 0 | D37: =COUNTIFS('October'!$P$2:$P$2000,"Deal Lost",'October'!$N$2:$N$2000,"New Prospect") -> 0 | E37: =COUNTIFS('October'!$P$2:$P$2000,"In Progress",'October'!$N$2:$N$2000,"New Prospect") -> 0 | F37: =IF(B37=0,0,C37/B37) -> 0
A38: November | B38: =COUNTIFS('November'!$P$2:$P$2000,"Deal Won",'November'!$N$2:$N$2000,"New Prospect")+COUNTIFS('November'!$P$2:$P$2000,"Deal Lost",'November'!$N$2:$N$2000,"New Prospect")+COUNTIFS('November'!$P$2:$P$2000,"In Progress",'November'!$N$2:$N$2000,"New Prospect") -> 0 | C38: =COUNTIFS('November'!$P$2:$P$2000,"Deal Won",'November'!$N$2:$N$2000,"New Prospect") -> 0 | D38: =COUNTIFS('November'!$P$2:$P$2000,"Deal Lost",'November'!$N$2:$N$2000,"New Prospect") -> 0 | E38: =COUNTIFS('November'!$P$2:$P$2000,"In Progress",'November'!$N$2:$N$2000,"New Prospect") -> 0 | F38: =IF(B38=0,0,C38/B38) -> 0
A39: December | B39: =COUNTIFS('December'!$P$2:$P$2000,"Deal Won",'December'!$N$2:$N$2000,"New Prospect")+COUNTIFS('December'!$P$2:$P$2000,"Deal Lost",'December'!$N$2:$N$2000,"New Prospect")+COUNTIFS('December'!$P$2:$P$2000,"In Progress",'December'!$N$2:$N$2000,"New Prospect") -> 0 | C39: =COUNTIFS('December'!$P$2:$P$2000,"Deal Won",'December'!$N$2:$N$2000,"New Prospect") -> 0 | D39: =COUNTIFS('December'!$P$2:$P$2000,"Deal Lost",'December'!$N$2:$N$2000,"New Prospect") -> 0 | E39: =COUNTIFS('December'!$P$2:$P$2000,"In Progress",'December'!$N$2:$N$2000,"New Prospect") -> 0 | F39: =IF(B39=0,0,C39/B39) -> 0
A40: TOTAL | B40: =SUM(B28:B39) -> 386 | C40: =SUM(C28:C39) -> 107 | D40: =SUM(D28:D39) -> 211 | E40: =SUM(E28:E39) -> 68 | F40: =IF(B40=0,0,C40/B40) -> 0.27720207
B44: DEALS WON BY REGION
B45: Region | C45: Deals Won | D45: % of Won
B46: IN | C46: =COUNTIFS('January'!$P$2:$P$2000,"Deal Won",'January'!$B$2:$B$2000,$B46)+COUNTIFS('February'!$P$2:$P$2000,"Deal Won",'February'!$B$2:$B$2000,$B46)+COUNTIFS('March'!$P$2:$P$2000,"Deal Won",'March'!$B$2:$B$2000,$B46)+COUNTIFS('April'!$P$2:$P$2000,"Deal Won",'April'!$B$2:$B$2000,$B46)+COUNTIFS('May'!$P$2:$P$2000,"Deal Won",'May'!$B$2:$B$2000,$B46)+COUNTIFS('June'!$P$2:$P$2002,"Deal Won",'June'!$B$2:$B$2002,$B46)+COUNTIFS('July'!$P$2:$P$2000,"Deal Won",'July'!$B$2:$B$2000,$B46)+COUNTIFS('August'!$P$2:$P$2000,"Deal Won",'August'!$B$2:$B$2000,$B46)+COUNTIFS('September'!$P$2:$P$2000,"Deal Won",'September'!$B$2:$B$2000,$B46)+COUNTIFS('October'!$P$2:$P$2000,"Deal Won",'October'!$B$2:$B$2000,$B46)+COUNTIFS('November'!$P$2:$P$2000,"Deal Won",'November'!$B$2:$B$2000,$B46)+COUNTIFS('December'!$P$2:$P$2000,"Deal Won",'December'!$B$2:$B$2000,$B46) -> 91 | D46: =IF($F$5=0,0,C46/$F$5) -> 0
B47: US | C47: =COUNTIFS('January'!$P$2:$P$2000,"Deal Won",'January'!$B$2:$B$2000,$B47)+COUNTIFS('February'!$P$2:$P$2000,"Deal Won",'February'!$B$2:$B$2000,$B47)+COUNTIFS('March'!$P$2:$P$2000,"Deal Won",'March'!$B$2:$B$2000,$B47)+COUNTIFS('April'!$P$2:$P$2000,"Deal Won",'April'!$B$2:$B$2000,$B47)+COUNTIFS('May'!$P$2:$P$2000,"Deal Won",'May'!$B$2:$B$2000,$B47)+COUNTIFS('June'!$P$2:$P$2002,"Deal Won",'June'!$B$2:$B$2002,$B47)+COUNTIFS('July'!$P$2:$P$2000,"Deal Won",'July'!$B$2:$B$2000,$B47)+COUNTIFS('August'!$P$2:$P$2000,"Deal Won",'August'!$B$2:$B$2000,$B47)+COUNTIFS('September'!$P$2:$P$2000,"Deal Won",'September'!$B$2:$B$2000,$B47)+COUNTIFS('October'!$P$2:$P$2000,"Deal Won",'October'!$B$2:$B$2000,$B47)+COUNTIFS('November'!$P$2:$P$2000,"Deal Won",'November'!$B$2:$B$2000,$B47)+COUNTIFS('December'!$P$2:$P$2000,"Deal Won",'December'!$B$2:$B$2000,$B47) -> 16 | D47: =IF($F$5=0,0,C47/$F$5) -> 0
B48: EMEA | C48: =COUNTIFS('January'!$P$2:$P$2000,"Deal Won",'January'!$B$2:$B$2000,$B48)+COUNTIFS('February'!$P$2:$P$2000,"Deal Won",'February'!$B$2:$B$2000,$B48)+COUNTIFS('March'!$P$2:$P$2000,"Deal Won",'March'!$B$2:$B$2000,$B48)+COUNTIFS('April'!$P$2:$P$2000,"Deal Won",'April'!$B$2:$B$2000,$B48)+COUNTIFS('May'!$P$2:$P$2000,"Deal Won",'May'!$B$2:$B$2000,$B48)+COUNTIFS('June'!$P$2:$P$2002,"Deal Won",'June'!$B$2:$B$2002,$B48)+COUNTIFS('July'!$P$2:$P$2000,"Deal Won",'July'!$B$2:$B$2000,$B48)+COUNTIFS('August'!$P$2:$P$2000,"Deal Won",'August'!$B$2:$B$2000,$B48)+COUNTIFS('September'!$P$2:$P$2000,"Deal Won",'September'!$B$2:$B$2000,$B48)+COUNTIFS('October'!$P$2:$P$2000,"Deal Won",'October'!$B$2:$B$2000,$B48)+COUNTIFS('November'!$P$2:$P$2000,"Deal Won",'November'!$B$2:$B$2000,$B48)+COUNTIFS('December'!$P$2:$P$2000,"Deal Won",'December'!$B$2:$B$2000,$B48) -> 14 | D48: =IF($F$5=0,0,C48/$F$5) -> 0
B49: EU | C49: =COUNTIFS('January'!$P$2:$P$2000,"Deal Won",'January'!$B$2:$B$2000,$B49)+COUNTIFS('February'!$P$2:$P$2000,"Deal Won",'February'!$B$2:$B$2000,$B49)+COUNTIFS('March'!$P$2:$P$2000,"Deal Won",'March'!$B$2:$B$2000,$B49)+COUNTIFS('April'!$P$2:$P$2000,"Deal Won",'April'!$B$2:$B$2000,$B49)+COUNTIFS('May'!$P$2:$P$2000,"Deal Won",'May'!$B$2:$B$2000,$B49)+COUNTIFS('June'!$P$2:$P$2002,"Deal Won",'June'!$B$2:$B$2002,$B49)+COUNTIFS('July'!$P$2:$P$2000,"Deal Won",'July'!$B$2:$B$2000,$B49)+COUNTIFS('August'!$P$2:$P$2000,"Deal Won",'August'!$B$2:$B$2000,$B49)+COUNTIFS('September'!$P$2:$P$2000,"Deal Won",'September'!$B$2:$B$2000,$B49)+COUNTIFS('October'!$P$2:$P$2000,"Deal Won",'October'!$B$2:$B$2000,$B49)+COUNTIFS('November'!$P$2:$P$2000,"Deal Won",'November'!$B$2:$B$2000,$B49)+COUNTIFS('December'!$P$2:$P$2000,"Deal Won",'December'!$B$2:$B$2000,$B49) -> 7 | D49: =IF($F$5=0,0,C49/$F$5) -> 0
B50: ANZ | C50: =COUNTIFS('January'!$P$2:$P$2000,"Deal Won",'January'!$B$2:$B$2000,$B50)+COUNTIFS('February'!$P$2:$P$2000,"Deal Won",'February'!$B$2:$B$2000,$B50)+COUNTIFS('March'!$P$2:$P$2000,"Deal Won",'March'!$B$2:$B$2000,$B50)+COUNTIFS('April'!$P$2:$P$2000,"Deal Won",'April'!$B$2:$B$2000,$B50)+COUNTIFS('May'!$P$2:$P$2000,"Deal Won",'May'!$B$2:$B$2000,$B50)+COUNTIFS('June'!$P$2:$P$2002,"Deal Won",'June'!$B$2:$B$2002,$B50)+COUNTIFS('July'!$P$2:$P$2000,"Deal Won",'July'!$B$2:$B$2000,$B50)+COUNTIFS('August'!$P$2:$P$2000,"Deal Won",'August'!$B$2:$B$2000,$B50)+COUNTIFS('September'!$P$2:$P$2000,"Deal Won",'September'!$B$2:$B$2000,$B50)+COUNTIFS('October'!$P$2:$P$2000,"Deal Won",'October'!$B$2:$B$2000,$B50)+COUNTIFS('November'!$P$2:$P$2000,"Deal Won",'November'!$B$2:$B$2000,$B50)+COUNTIFS('December'!$P$2:$P$2000,"Deal Won",'December'!$B$2:$B$2000,$B50) -> 0 | D50: =IF($F$5=0,0,C50/$F$5) -> 0
B51: APAC | C51: =COUNTIFS('January'!$P$2:$P$2000,"Deal Won",'January'!$B$2:$B$2000,$B51)+COUNTIFS('February'!$P$2:$P$2000,"Deal Won",'February'!$B$2:$B$2000,$B51)+COUNTIFS('March'!$P$2:$P$2000,"Deal Won",'March'!$B$2:$B$2000,$B51)+COUNTIFS('April'!$P$2:$P$2000,"Deal Won",'April'!$B$2:$B$2000,$B51)+COUNTIFS('May'!$P$2:$P$2000,"Deal Won",'May'!$B$2:$B$2000,$B51)+COUNTIFS('June'!$P$2:$P$2002,"Deal Won",'June'!$B$2:$B$2002,$B51)+COUNTIFS('July'!$P$2:$P$2000,"Deal Won",'July'!$B$2:$B$2000,$B51)+COUNTIFS('August'!$P$2:$P$2000,"Deal Won",'August'!$B$2:$B$2000,$B51)+COUNTIFS('September'!$P$2:$P$2000,"Deal Won",'September'!$B$2:$B$2000,$B51)+COUNTIFS('October'!$P$2:$P$2000,"Deal Won",'October'!$B$2:$B$2000,$B51)+COUNTIFS('November'!$P$2:$P$2000,"Deal Won",'November'!$B$2:$B$2000,$B51)+COUNTIFS('December'!$P$2:$P$2000,"Deal Won",'December'!$B$2:$B$2000,$B51) -> 1 | D51: =IF($F$5=0,0,C51/$F$5) -> 0
B52: LATAM | C52: =COUNTIFS('January'!$P$2:$P$2000,"Deal Won",'January'!$B$2:$B$2000,$B52)+COUNTIFS('February'!$P$2:$P$2000,"Deal Won",'February'!$B$2:$B$2000,$B52)+COUNTIFS('March'!$P$2:$P$2000,"Deal Won",'March'!$B$2:$B$2000,$B52)+COUNTIFS('April'!$P$2:$P$2000,"Deal Won",'April'!$B$2:$B$2000,$B52)+COUNTIFS('May'!$P$2:$P$2000,"Deal Won",'May'!$B$2:$B$2000,$B52)+COUNTIFS('June'!$P$2:$P$2002,"Deal Won",'June'!$B$2:$B$2002,$B52)+COUNTIFS('July'!$P$2:$P$2000,"Deal Won",'July'!$B$2:$B$2000,$B52)+COUNTIFS('August'!$P$2:$P$2000,"Deal Won",'August'!$B$2:$B$2000,$B52)+COUNTIFS('September'!$P$2:$P$2000,"Deal Won",'September'!$B$2:$B$2000,$B52)+COUNTIFS('October'!$P$2:$P$2000,"Deal Won",'October'!$B$2:$B$2000,$B52)+COUNTIFS('November'!$P$2:$P$2000,"Deal Won",'November'!$B$2:$B$2000,$B52)+COUNTIFS('December'!$P$2:$P$2000,"Deal Won",'December'!$B$2:$B$2000,$B52) -> 0 | D52: =IF($F$5=0,0,C52/$F$5) -> 0
B53: TOTAL | C53: =SUM(C46:C52) -> 129 | D53: =IF($F$5=0,0,C53/$F$5) -> 0

Sheet January
A1: Date | B1: Region | C1: Handled by | D1: Email address | E1: Industry | F1: Ticket ID | G1: Purpose | H1: New requirements | I1: Current Platform | J1: Existing data size | K1: Follow up stages | L1: PSE Creation | M1: Source | N1: Engagement Type | O1: Trial sign up | P1: Status | Q1: Deal Size | R1: Revenue | S1: Suggested/purchased edition | T1: Notes | U1: Demo Recording | V1: Sales Notes from CRM | W1: Sprint link
A2: 46024 | B2: IN | C2: Sakthi | D2: umesh.shringi@allen.in | E2: Education | F2: #152989037 | G2: Workplace prospect looking for Trial migration of Google Workspace to WorkDrive and had a few queries on WorkDrive. Helped them complete the test migration. | I2: Google WorkSpace | K2: Do not follow | M2: Internally Looped | N2: New Prospect | O2: POC | P2: Deal Won | Q2: 8000 | R2: 72809.97 | S2: WP flexi | T2: Customer Plan Mail Flexible Plan - 7000 Flexi - Workplace Standard 10gb, 1000 Flexi - Workplace Professional 10gb | V2: No notes
A3: 46024 | B3: IN | C3: Janani | D3: itsupport@kurumgroup.com | E3: Consulting | F3: #149943032 | G3: Prospect is looking for Sign up for Zoho One He already had a session regarding integrating between CRM and WorkDrive and automating features for contacts and creating folders in WorkDrive | H3: Document reminder | I3: System Server | K3: Do not follow | M3: WD support - Chat/Call/Mail | N3: New Prospect | O3: Yes | P3: Deal Won | Q3: 15 | S3: Zoho One | U3: https://workdrive.zoho.in/file/p7iy5e93d0127862f421ebd7bacb82bd32f95 | W3: Document Reminder https://sprints.zoho.in/workspace/zdocs#P15/itemdetails/I7129
A4: 46028 | B4: US | C4: Jennifer | D4: ryan.collins@lsa.inc | E4: Language Service Associates | F4: #153244173 | G4: Currently using Egnyte; facing upload/download action limits with additional costs. Looking for a DMS with no action-based limits, secure file sharing and collection from clients, and smooth collaboration for team members. | I4: Egnyte | J4: < 3 TB | K4: Sales follow up 3 | L4: PSE541721 | M4: WorkDrive - Book a Demo (direct) | N4: New Prospect | O4: No | P4: Deal Lost | Q4: 30 | S4: Team | T4: Price quote is sent in the last mail from the sales team | U4: No recording | V4: Thank you for following up. We do appreciate your time demonstrating your platform and answering any questions we had. Ultimately, we have decided to pursue other vendors that are based in the United States for compliance reasons.
A5: 46028 | B5: IN | C5: Sakthi | D5: mayank.kumar@psb.bank.i | E5: Banking | F5: #153227159 | G5: 1. They were looking for replacement for MS Teams, Outlook, OneDrive and they are currently using WhatsApp for internal communication. >> Suggested Workplace. Gave a quick overview of Workplace. | I5: MS Office 365 | K5: Do not follow | M5: WorkDrive - Book a Demo (direct) | N5: New Prospect | O5: No | P5: Deal Lost | Q5: 1000 | S5: WP flexi
A6: 46028 | B6: IN | C6: Rohith | D6: studio.nkpr@gmail.com | E6: Media | F6: #106824933 | G6: The user had already evaluated WorkDrive in May 2025 and confirmed their decision to proceed. They wanted clarity on the differences between WorkDrive standalone plans and the Workplace bundle. | H6: 1. Custom roles & permission 2. AutoCAD file integration features. | I6: Google personal Drive | K6: Follow up 1 | L6: PSE542077 | M6: From Sales End | N6: New Prospect | O6: Yes | P6: Deal Won | Q6: 7 | S6: WP (Professional) | U6: Connected via direct call | W6: 1. Custom Roles & Permissionshttps://sprints.zoho.in/workspace/zdocs#P15/itemdetails/I7130 2. Auto CAD integration. https://sprints.zoho.in/workspace/zdocs#P15/itemdetails/I7451
A7: 46028 | B7: IN | C7: Rohith | D7: amith@tbkmetalksa.com | E7: Architectural | F7: #152590768 | G7: Demo on Workflows | K7: Sales follow up 2 | L7: PSE542080 | M7: WorkDrive - Book a Demo (direct) | N7: New Prospect | O7: Yes | P7: Deal Won | Q7: 15 | S7: Business | U7: Connected via assist
A8: 46028 | B8: IN | C8: Janani | D8: hareshkapadiya@torrentgas.com | E8: Manufacturing | F8: #153216701 | G8: Prospect is looking for an overview on how to use WorkDrive He have signed up for Trial edition, and wanted to share his screen and know the features on | K8: Sales follow up 3 | M8: From Sales End | N8: New Prospect | O8: Suspended | P8: Deal Lost | Q8: 10 | S8: Starter | U8: https://workdrive.zoho.in/file/wqwyd1273f93c995e4f08a3d4a3143c4e84bd | V8: Ringed and no response over mails/calls
A9: 46028 | B9: IN | C9: Janani | D9: himadri.roy@havrokconsulting.com | E9: Consulting | F9: #153236632 | G9: Prospect is looking for an alternate to Sharepoint in Zoho To store and have a collaboration space | I9: OneDrive | K9: Follow up 1 | M9: WorkDrive - Book a Demo (direct) | N9: New Prospect | O9: Yes | P9: Deal Won | Q9: 1 | S9: Starter | U9: https://workdrive.zoho.in/file/wqwyd0024438bdc594cfe902be9d1abffd67e
A10: 46029 | B10: IN | C10: Sakthi | D10: abhijeet.dey@sedemac.com | E10: Manufacturing | F10: #153282485 | G10: They are currently using PLM application to manager their files internally. | H10: In their existing PLM, they extensively use Major and Minor Version control. >> It is highly crucial for them to have numeric patter link 1.0, 1.1, 1.2,1.3 ….so on and then 2.0, 2.1, 2.2. instead of directly providing 1.0, 2.0, 3.0. >> An option to create minor versions is very critical for their organization. They want an option to manually add minor versions when and where required while checking in a file. Please advise on this feature requirement. | I10: PLM | K10: Sales follow up 3 | M10: WorkDrive - Book a Demo (direct) | N10: New Prospect | O10: No | P10: Deal Lost | Q10: 500 | S10: Business | T10: As we are unable to provide major and minor versioing, we lost this deal. We have also followed up mentioning that we have started working on supporting major and minor versioning. The prospect is yet to get back. | U10: https://workdrive.zoho.in/file/zhubf035eb27aad4042309c8465d67c4437e2 | V10: Sorry for reaching out to you late. After my discussion with the team, we have decided not to go ahead at this time. There are some basic features we require that are currently not present in Zoho WorkDrive. Thank you for your time and for sharing the proposal. | W10: Minor & Major versioning:https://sprints.zoho.in/workspace/zdocs#P15/itemdetails/I7166
A11: 46029 | B11: US | C11: Rohith | D11: cyuhasz@povprint.com | E11: Arts | F11: #153293231 | G11: They need a centralized space to store large files, with the ability to link those files to the corresponding contacts in Zoho CRM. | K11: Do not follow | L11: NO PSE | M11: WorkDrive - Book a Demo (direct) | N11: Existing Paid Cx | O11: Existing user | P11: Existing customer | Q11: 7 | S11: Zoho One | U11: No recording
A12: 46029 | B12: EMEA | C12: Rohith | D12: ry1071220@gmail.com | E12: Education institution | F12: #153303861 | G12: They have a team of fewer than 100 members and need a centralized system to collect individual user information along with related documents. The data includes form-based details and multiple file formats such as Word documents, PDFs, images, and PPTs. Each user should have their own account to upload documents, which must go through a review process. Administrators with appropriate permissions should be able to access, review, and download all submitted files. | H12: None | I12: - | K12: Sales follow up 3 | L12: PSE543061 | M12: From Sales End | N12: New Prospect | O12: Yes | P12: Deal Lost | Q12: 10 to 40 | S12: Business | U12: https://workdrive.zoho.in/file/6ejm19e307182791b490eb753d9252950f3a1 | V12: no response closing mail sent.
A13: 46029 | B13: US | C13: Rohith | D13: dreamloan@centum.ca | E13: Finance | F13: #153320978 | G13: Cloud space to store documents | H13: None | I13: None | K13: Follow up 3 | L13: NO PSE | M13: WorkDrive - Book a Demo (direct) | N13: New Prospect | O13: Yes | P13: Deal Lost | Q13: 4 | T13: No Response from cx | U13: https://workdrive.zoho.in/file/6ejm161f9a100fe264c1895dcfdbd51fb907b
A14: 46029 | B14: IN | C14: Rohith | D14: sukkunmst@gmail.com | E14: Tax | F14: #153338612 | G14: They handle sensitive client tax data and are looking for a secure cloud-based document storage solution. Employees should be able to work on and edit assigned documents, but should not be allowed to download, copy, or externally share those files. | H14: None | I14: Custom roles | K14: Sales follow up 3 | L14: NO PSE | M14: WorkDrive - Book a Demo (direct) | N14: New Prospect | O14: Yes | P14: Deal Lost | Q14: 5 | S14: Starter | U14: No recording | V14: No Response from cx
A15: 46030 | B15: IN | C15: Janani | D15: opagarwalandco@gmail.com | E15: Consulting | F15: #153228475 | G15: Prospect is looking to backup data from system to cloud | H15: None | K15: Sales follow up 1 | M15: From Sales End | N15: New Prospect | O15: Suspended | P15: Deal Lost | Q15: 3 | S15: Starter | U15: https://workdrive.zoho.in/file/ws66nb104dded9b5a4e2dacfa3b077d0a9bd0 | V15: No response
A16: 46030 | B16: IN | C16: Janani | D16: lakshmi@scas.co.in | E16: Consulting | F16: #153274008 | G16: Prospect was looking for cloud storage platform, that helps their clients to login and get access to the files and folders | H16: None | K16: Sales follow up 3 | M16: From Sales End | N16: New Prospect | O16: No | P16: Deal Lost | Q16: 10 | S16: Team | U16: https://workdrive.zoho.in/file/ws66n691a44bcfced4099b76b8ee87659dbf0 | V16: waiting for their management approvals
A17: 46030 | B17: IN | C17: Janani | D17: pankajramol@almamet.com | E17: Logistics | F17: #148152614 | G17: Prospect had demo previously last year wanted to know about the product once again | H17: None | K17: Sales follow up 2 | M17: WD support - Chat/Call/Mail | N17: New Prospect | O17: Yes | P17: Deal Won | Q17: 30 | S17: Team | T17: Deal won in May month | U17: https://workdrive.zoho.in/file/ws66nc4bb16b99a164d7bba22684a0d48aebc
A18: 46030 | B18: IN | C18: Sakthi | D18: finance@tuljaihr.com | E18: Accounting | F18: #153329888 | G18: They are a startup business. They are using LAN to connect their laptops. 2. They want to know if Truesync can be used to sync contents in one laptop to another, where both the laptop belongs to the same user. | K18: Follow up 1 | M18: WorkDrive - Book a Demo (direct) | N18: New Prospect | O18: No | P18: Deal Lost | Q18: 3 | S18: Starter
A19: 46030 | B19: IN | C19: Rohith | D19: dineshk@foodbuddies.in | E19: Food production | F19: #153288747 | G19: They are currently using the Microsoft platform and facing challenges with storage allocation. As a result, they are exploring an alternative solution with better storage flexibility and collaboration capabilities. | H19: None | I19: OneDrive | J19: 1TB | K19: Sales follow up 3 | L19: NO PSE | M19: WorkDrive - Book a Demo (direct) | N19: New Prospect | O19: Free User | P19: Deal Lost | Q19: 4 | S19: Business | U19: Connected via direct call | V19: No Response from cx
A20: 46030 | B20: IN | C20: Rohith | D20: manimaran.g@eduvanta.ai | E20: Education institution | F20: #153090179 | G20: Query in Zoho WorkDrive | H20: None | K20: Do not follow | M20: From Sales End | N20: New Prospect | O20: Yes | P20: Deal Won | Q20: 4 | S20: Starter | U20: https://workdrive.zoho.in/file/f48vvd7cb0f09c40e4251818ceb1060b793ac
A21: 46030 | B21: IN | C21: Rohith | D21: karthik@deducetech.com | E21: Location Content and Maps Industry | F21: #153267281 | G21: They are looking for a cloud storage solution to support daily data transfers from Mexico to India. The expected upload volume is around 600–800 GB per day. The data will be downloaded to their NAS at the Bangalore location and then deleted from the cloud, so the requirement is primarily for high-volume, short-term data transfer with reliability and performance. | H21: None | I21: OneDrive | J21: 2TB | K21: Sales follow up 3 | L21: NO PSE | M21: WD support - Chat/Call/Mail | N21: New Prospect | O21: Suspended | P21: Deal Lost | S21: Business | U21: https://workdrive.zoho.in/file/f48vv5fb9145b6e0a46eba97dfa74f321bb1b | V21: No Response from cx
A22: 46030 | B22: US | C22: Rohith | D22: info@tangoshieldsecurity.com | E22: IT security | F22: #153360663 | G22: They are an MSP supporting a global distribution client, they are looking for a WorkDrive-focused demo covering strong admin-level control and security policies for BYOD users, integration with Zoho One and third-party systems such as ERP and WMS, encrypted file sharing with detailed audit trails for compliance, geo-restricted access and DLP use cases, and scalable storage with reliable multi-region performance. They also requested examples aligned with high-volume document management and regulated environments such as FedRAMP, HIPAA, and GDPR. | H22: None | K22: Sales follow up 3 | L22: NO PSE | M22: WorkDrive - Book a Demo (direct) | N22: New Prospect | O22: Suspended | P22: Deal Lost | Q22: 10 | S22: Business | U22: https://workdrive.zoho.in/file/6ejm18c85937609b349a0bd9fa53826adc669 | V22: No Response from cx
A23: 46031 | B23: IN | C23: Sakthi | D23: systemengineer@niperhajipur.ac.in | E23: Government sector | F23: #153348227 | G23: 1. Their primary requirement is to have a Workflow set up for the below mentioned use-case: >> They want to trigger a workflow of approval for their purchase orders and other kinds of documents from: Administrative Officer-> Registrar-> Dean-> Sometimes to HOD for inputs-> Director | K23: Follow up 1 | M23: WorkDrive - Book a Demo (direct) | N23: New Prospect | O23: No | P23: Deal Lost | Q23: 50 | S23: Business | U23: https://workdrive.zoho.in/file/x4582ce625fce28734c4d9388e7f5e3e02e4b
A24: 46031 | B24: IN | C24: Sakthi | D24: milin.patel@kokuyocamlin.com | E24: Manufacturing | F24: #153385675 | G24: Looking for features like DLP, Access control and team folder based collaboration | H24: Logs for Print actions in org-level activity report. | K24: Sales follow up 2 | M24: WD support - Chat/Call/Mail | N24: New Prospect | O24: Suspended | P24: Deal Lost | Q24: 12 | S24: Business | U24: https://workdrive.zoho.in/file/l4d7771c8b8a0ee8b4c07b59c6700fbe0ccbc | W24: Print logs in activity report: https://sprints.zoho.in/workspace/zdocs#P15/itemdetails/I7459
A25: 46031 | B25: IN | C25: Janani | D25: katearf@hotmail.com | E25: Consulting | F25: #153382549 | G25: Prospect is looking for an alternate to DropBox And primary requirement is to share and collaborate with external users | K25: Sales follow up 3 | M25: WorkDrive - Book a Demo (direct) | N25: New Prospect | O25: No | P25: Deal Lost | Q25: 46298 | S25: Starter | U25: https://workdrive.zoho.in/file/l4d77cdc4bc7e500b42bba65e3e67c24e05ea
A26: 46031 | B26: IN | C26: Janani | D26: mrunalini.hr@mecpl.in | E26: construction | F26: #153385925 | G26: Primary requirement is to replace Google Sheet in Zoho Since sales team suggested it is not possible to collaborate only with Zoho Sheet sign up, | K26: Sales follow up 2 | M26: From Sales End | N26: New Prospect | O26: Yes | P26: Deal Won | Q26: 380 | R26: 4965.84 | S26: Starter | U26: https://workdrive.zoho.in/file/l4d77f7b0389ece7a4be3a0c7a3a462c09d3c
A27: 46031 | B27: IN | C27: Janani | D27: md.arif@imoneypay.in | E27: financial services | F27: #153322758 | G27: Prospect is looking for Zoho apps in common as they are Indian made and mainly a DLP solution | H27: - DLP feature, whether it is available as standalone in Zoho same an microsfot purvie | K27: Follow up 3 | M27: WD support - Chat/Call/Mail | N27: New Prospect | O27: No | P27: Deal Lost | Q27: Not confirmed | S27: Starter | U27: https://workdrive.zoho.in/file/ws66n64d3e72d3dd14e6bbeba404ea19e48d1
A28: 46031 | B28: IN | C28: Janani | D28: hemstoneomondi5@gmail.com | E28: Consulting | F28: #153349646 | G28: Prospect has already signed up for Trial edition and wanted to explore all the features in Zoho WorkDrive | K28: Sales follow up 3 | M28: WorkDrive - Book a Demo (direct) | N28: New Prospect | O28: Yes | P28: Deal Lost | Q28: 46176 | S28: Zoho One | T28: Zoho One lead | U28: https://workdrive.zoho.in/file/ws66n48004e8458ff438696f2365cc533f55b
A29: 46031 | B29: IN | C29: Janani | D29: prashant.kumar@omnioffshore.com | E29: marine & offshore oil services | F29: #102351238 | G29: Prospect is looking for an We are looking for an online document management system for our project team. Almost all project documents are in pdf format. The solution should be able to handle commenting and review of pdf documents. | H29: - He wanted to see if we can have comment export feature - Export the document workflow status on track workflow page So that they can have reports of all the file that has been gone through reviewal and approval process OR On every approval and reviewal process, is it possible to add a stamp once the review or approval gets completed | K29: Sales follow up 3 | M29: From Sales End | N29: New Prospect | O29: Suspended | P29: Deal Lost | Q29: 15 | S29: Business | U29: https://workdrive.zoho.in/file/ws66ned19fb2bc802423c8fcbd6d1a77af93b | V29: The team is actively testing the system now using a trial account. We should have an outcome in a few days., I am sorry to inform that the final decision was not in your favour. I really wanted to move to Zoho WorkDrive but could not convince the engineering team.
A30: 46031 | B30: IN | C30: Rohith | D30: nidhi@gepathways.com.au | E30: Overseas education | F30: #151471225 | G30: They have a distributed team working from multiple locations and need a centralized document repository. Currently, files are stored on individual machines, which has resulted in duplication, version confusion, and difficulty collaborating across teams. | H30: None | I30: Local Drive | K30: Follow up 2 | L30: PSE543164 | M30: From Sales End | N30: New Prospect | O30: Yes | P30: Deal Won | Q30: 13 | S30: Business | U30: https://workdrive.zoho.in/file/l4d7742e2fd04bdaf4e4793aa54788af17d08
A31: 46031 | B31: IN | C31: Sakthi | D31: trs@zengroupindia.com | E31: Manufacturing | F31: #153385675 | G31: 1. They were currently using hard-disk to manage their files. Accessibility was their primary concern. 2. They have requested for Workflow feature where they want to send document to multiple approvers. | K31: Follow up 1 | M31: WD support - Chat/Call/Mail | N31: New Prospect | O31: Yes | P31: Deal Won | Q31: 11 | R31: 402.93 | S31: Team | U31: https://workdrive.zoho.in/file/l4d77229e30639a8c4f628b69b68db7826a5d
A32: 46031 | B32: IN | C32: Rohith | D32: advbhagat@zohomail.in | E32: Personal use | F32: #153404681 | G32: Queries on Zoho Writer and WorkDrive | I32: Google Drive | K32: Sales follow up 3 | L32: NO PSE | M32: WD support - Chat/Call/Mail | N32: New Prospect | O32: No | P32: Deal Lost | U32: No recording | V32: No Response from cx
A33: 46031 | B33: IN | C33: Rohith | D33: premchand4892@gmail.com | E33: Consultant | F33: #153030903 | G33: They are looking for a spreadsheet tool to manage client details such as name, email, and other information. | H33: While locking the cell, copy action should be restricted | I33: None | K33: Follow up 3 | L33: NO PSE | M33: WorkDrive - Book a Demo (direct) | N33: New Prospect | O33: No | P33: Deal Lost | Q33: 2 | S33: Starter | T33: No Response from cx | U33: No recording
A34: 46031 | B34: IN | C34: Jennifer | D34: manickavalli@gmail.com | E34: Unknown | F34: #153385007 | G34: They are using Google Drive and OneDrive to manage their documents from desktop version, however they have challenges with simultaneous syncing process. Plus they are looking to maintain their private files separately and have desktop app that does not take up the system storage. | I34: Google Drive and OneDrive | J34: ~200 GB | K34: Sales follow up 1 | L34: PSE543282 | M34: WD support - Chat/Call/Mail | N34: New Prospect | O34: Yes | P34: Deal Won | Q34: 3 | S34: Starter | U34: https://workdrive.zoho.in/file/kdqtxe1f50aa9bb484e7e945d487af9fa6616
A35: 46034 | B35: IN | C35: Janani | D35: contact@theanant.in | E35: Consulting | F35: #153333592 | G35: Work Drive, WorkSpace, Biomatric & Attendance, Work Space - App | K35: Sales follow up 1 | M35: From Sales End | N35: New Prospect | O35: No | P35: Deal Lost | Q35: 15 | S35: WP (Standard) | U35: https://workdrive.zoho.in/file/x3dyzcd408f3ba3cb4bca9e33b7185d830bf4
A36: 46034 | B36: IN | C36: Janani | D36: kesar240391@gmail.com | E36: Personal | F36: #153445929 | G36: Prospect is looking for an overview on WorkDrive and the features | K36: Sales follow up 2 | M36: WorkDrive - Book a Demo (direct) | N36: New Prospect | O36: No | P36: Deal Lost | Q36: 10 | S36: Starter | U36: https://workdrive.zoho.in/file/x3dyz7ce9c57c565942d6be20aabbf0fb4f54
A37: 46034 | B37: IN | C37: Rohith | D37: wlfoundation@outlook.com | E37: NGO | F37: #153394548 | G37: They are looking for a centralized cloud storage solution to manage data across all project locations, with real-time access for the Hyderabad head office as files are uploaded. They also require controlled folder access per project/location, detailed activity tracking (uploads, edits, moves, and sharing), and an affordable pricing model, preferably with NGO-specific discounts | H37: None | I37: DY box | K37: Sales follow up 2 | L37: NO PSE | M37: WorkDrive - Book a Demo (direct) | N37: New Prospect | O37: Yes | P37: Deal Won | Q37: 4 | S37: Starter | U37: https://workdrive.zoho.in/file/k5iz65300f78e357e4ed2af76077fab7957a4
A38: 46034 | B38: IN | C38: Rohith | D38: amith@tbkmetalksa.com | E38: Architectural | F38: #152590768 | G38: Queries in Zoho WorkDrive | K38: Sales follow up 2 | L38: PSE543884 | M38: WorkDrive - Book a Demo (direct) | N38: Already Engaged Px | O38: Yes | P38: Deal Won | Q38: 15 | R38: 1034.5 | S38: Business | U38: Connected via assist
A39: 46034 | B39: EMEA | C39: Rohith | D39: mohammed.wedaa@alqasabi.sa | E39: Constructions | F39: #152978135 | G39: The customer is looking for a centralized document management system to manage all project-related files with controlled access at both folder and subfolder levels. They need clearly defined review and approval workflows involving contractors, consultants, and clients, along with strong version control and complete audit trails. Approved documents should be locked to prevent further edits, and they require document logs (such as drawing registers) to track approvals and document history. Additionally, they need powerful search capabilities to manage large volumes of files and scalable storage that can be expanded as the project grows. | H39: None | I39: None | K39: Sales follow up 2 | L39: PSE543890 | M39: WorkDrive - Book a Demo (direct) | N39: New Prospect | O39: Suspended | P39: Deal Lost | Q39: 30 | S39: Business | U39: https://workdrive.zoho.in/file/k5iz639d8b63eb02e4db7beefe4945ab0b613 | V39: Sales followed up in mail
A40: 46034 | B40: IN | C40: Rohith | D40: nagesh.dhumma@dhummaconsulting.com | E40: Consulting Services | F40: #152928511 | G40: They are looking for a combined project and document management solution. Their key needs include centralized document storage with controlled access to files, clear visibility into team progress, and the ability to collaborate seamlessly with team members in Germany. They also require easy access to files and updates from both desktop and mobile devices. | H40: None | I40: Trello | J40: 1.5TB | K40: Follow up 2 | L40: PSE543898 | M40: WorkDrive - Book a Demo (direct) | N40: New Prospect | O40: Yes | P40: Deal Won | Q40: 5 | S40: Team | U40: https://workdrive.zoho.in/file/k5iz6d47bfeadc843479cb9f6a6ef4c7b9688
A41: 46034 | B41: IN | C41: Rohith | D41: info@yunikaainternational.com | E41: Metal trade & export | F41: #152829390 | G41: The customer is currently on the Zoho Mail Premium plan with 8 users and wanted to check if it’s possible to upgrade to the Zoho Workplace plan for only a few users. | H41: None | K41: Do not follow | M41: WD support - Chat/Call/Mail | N41: New Prospect | O41: Yes | P41: Deal Won | Q41: 8 | S41: WP (Standard) | T41: Upgrade team is already in touch with cx | U41: No recording
A42: 46035 | B42: IN | C42: Janani | D42: jsrit.sapfico@gmail.com | E42: Personal | F42: #153531599 | G42: One user need To store files and folder in cloud and share | K42: Sales follow up 1 | M42: WorkDrive - Book a Demo (direct) | N42: New Prospect | O42: No | P42: Deal Lost | Q42: 1 | S42: Starter | U42: https://workdrive.zoho.in/file/x3dyzc65ad2317f134ce9afa771c10ace1a61
A43: 46035 | B43: EMEA | C43: Rohith | D43: anil_baheti@yahoo.com | E43: financial services | F43: #153481993 | G43: They are looking for a one-stop solution to manage the IT needs of a team of 20+ employees. This includes access-controlled cloud storage, structured folder and file management, a backup solution, email management, an office suite with collaboration capabilities, and document workflows. They are also open to exploring finance and HR modules as part of a unified ecosystem. | H43: None | I43: NAS Drive | K43: Sales follow up 2 | L43: PSE544205 | M43: WorkDrive - Book a Demo (direct) | N43: New Prospect | O43: Yes | P43: Deal Won | Q43: 10 | R43: 47880 | S43: WP (Professional) | T43: Zoho Workplace team is following up with the cx | U43: https://workdrive.zoho.in/file/sxt59a78d85db2972446aa16f714560addb8e | V43: cx evaluating other bundle solutions as well , spoke with him got me informed that he will be conclude whether he will move with workdrive , or bundle solution
A44: 46035 | B44: IN | C44: Jennifer | D44: akrofficehyd2@gmail.com | E44: financial services | F44: #150834398 | G44: They are using physical servers to host their files which is difficult as it comes only to access from office, so they are looking for a cloud based DMS, with activity tracking, versions. | H44: None | I44: Physical Drive | K44: Sales follow up 2 | L44: NO PSE | M44: From Sales End | N44: New Prospect | O44: Yes | P44: Deal Won | Q44: 10 | R44: 33000 | S44: Team | U44: https://workdrive.zoho.in/file/0ylba501b825d1c2348dcb87216692a38e04a
A45: 46035 | B45: EMEA | C45: Rohith | D45: harsh@digisidekick.com | E45: Digital marketing | F45: #153530877 | G45: They are currently using Dropbox and are facing challenges with storage allocation. As a result, they are exploring alternative solutions that offer better storage management and flexibility. | H45: None | I45: Dropbox | K45: Follow up 1 | L45: NO PSE | M45: WorkDrive - Book a Demo (direct) | N45: New Prospect | O45: Yes | P45: Deal Won | Q45: 3 | S45: Starter | U45: https://workdrive.zoho.in/file/sxt59ece227945feb408b9914dce7aae25bf4
A46: 46035 | B46: EMEA | C46: Rohith | D46: tom@melsqatar.com | E46: lighting design and supply | F46: #153325409 | G46: They work on lighting design and supply projects and are currently facing challenges due to manual approval processes involving printed documents and physical signatures. They are looking for a centralized document repository with structured workflows to streamline approvals and improve efficiency. | H46: Sign integration in Workflows | I46: None | K46: Sales follow up 1 | L46: PSE544299 | M46: WorkDrive - Book a Demo (direct) | N46: New Prospect | O46: Yes | P46: Deal Won | Q46: 6 | S46: Starter | U46: https://workdrive.zoho.in/file/sxt59a0c82d3793244ee2bef81beb04596304 | W46: Already provided via custom function
A47: 46036 | B47: EMEA | C47: Jennifer | D47: wajeeh070@hotmail.com | E47: Manufacturing | F47: #153593444 | G47: They have been hosting their files in local storage and looking for a centralised space to save their data. They have been using Zoho Books for few years, which made them to check workdrive as well. | I47: Local Drive | K47: Sales follow up 2 | L47: NO PSE | M47: WorkDrive - Book a Demo (direct) | N47: New Prospect | O47: Yes | P47: Deal Won | Q47: 3 | R47: 86.41 | S47: Starter | U47: https://workdrive.zoho.in/file/nybji77e8d9d6ff2f4b2ba5e37046790a083e
A48: 46037 | B48: IN | C48: Janani | D48: satish@forecoreprofessionals.com | E48: Manufacturing | F48: #153655491 | G48: Need cloud based storage to work on files with real time sync, archival, retrival, on-the-go access like Dropbox for storage of ~1TB. Total team size ~15 persons | K48: Follow up 1 | M48: WorkDrive - Book a Demo (direct) | N48: New Prospect | O48: Yes | P48: Deal Won | Q48: 15 | S48: Starter | U48: https://workdrive.zoho.in/file/x3dyz1978a7d81b9546838170dbe2d85a26f2
A49: 46037 | B49: IN | C49: Jennifer | D49: utkarshsarkar2207@gmail.com | E49: Interior Design | F49: #153510062 | G49: They have been using Zoho Mail, and are looking for data management, where they would like to keep an eye on not all members having the option to delete a file, admins should have overall control. | H49: None | I49: Local Servers | K49: Sales follow up 2 | L49: NO PSE | M49: WorkDrive - Book a Demo (direct) | N49: New Prospect | O49: Yes | P49: Deal Won | Q49: 8 | R49: 13440 | S49: Starter | T49: activated in the email addres - info@bywordhr.com | U49: No recording - missed to record
A50: 46038 | B50: IN | C50: Janani | D50: vikas@civilarch.in | E50: Construction | F50: #153715387 | G50: Prospect was looking for cloud storage to store data, provide access to files and folders for their internal team members to edit and collaborate | K50: Sales follow up 1 | M50: WorkDrive - Book a Demo (direct) | N50: New Prospect | O50: Yes | P50: Deal Won | Q50: 5 | S50: Starter | U50: https://workdrive.zoho.in/file/x3dyz5924d8eed1684f8087c6e5ea3a082c39
A51: 46038 | B51: IN | C51: Sakthi | D51: utkarsh.chhiber@stayvista.com | E51: Tourism | F51: #153018670 | G51: 1. They were extensive users of Google AppScript. They wanted to link the data generated from Redash in Zoho Sheet for every 2 hours. | I51: Google WorkSpace | K51: Follow up 1 | M51: Internally Looped | N51: New Prospect | O51: No | P51: Deal Lost | S51: WP (Standard) | U51: https://workdrive.zoho.in/file/pu62r8fcd7c11c1964687b5fe551b7580a65d
A52: 46038 | B52: IN | C52: Sakthi | D52: stacey.dias@safeprofire.com | E52: Public Safety | F52: #153456241 | G52: 1. They are fire extinguisher manufacturer, looking to digitise their hardcopies to soft copies. 2. They have departments for Sales, invoices and purchases. They want to have repository for each of their departments along with role based access control. | H52: The prospect wants to make use of Data templates in Starter edition. As we have plans to enable Data Templates for all plans, when are we going to implement this? | K52: Follow up 1 | M52: WD support - Chat/Call/Mail | N52: New Prospect | O52: Free User | P52: Deal Lost | Q52: 35 | S52: Starter | U52: https://workdrive.zoho.in/file/pu62r16b26ea9fde3485abadd9352ec500b65
A53: 46041 | B53: ANZ | C53: Janani | D53: anthony@archerinstitute.edu.au | E53: Education | F53: #153850562 | G53: Would like to know 1. do you have an all in one solution ( drive, CRM etc) 2. Zhoho accounting do you have an api intergration We have an existing software program and we would like to integrate the accounting feature. We would like to see if it would be possible to intergreate with our subscription clients | K53: Do not follow | M53: WorkDrive - Book a Demo (direct) | N53: New Prospect | O53: No | P53: No Scope for WD | S53: Zoho One
A54: 46041 | B54: IN | C54: Janani | D54: swapnil@cadsaga.com | E54: Consulting | F54: #153850649 | G54: Need to take Workdrive subscription for a team of 5 | K54: Do not follow | M54: WorkDrive - Book a Demo (direct) | N54: New Prospect | O54: No | P54: Existing customer | S54: Zoho One
A55: 46041 | B55: IN | C55: Rohith | D55: salesinfoelecom@gmail.com | E55: IT | F55: #150301978 | G55: They are currently storing documents on individual users’ machines and want to move everything to the cloud. They had already explored Zoho WorkDrive and, before proceeding with the purchase, wanted a complete walkthrough of the product. | H55: None | I55: Local Drive | K55: Sales follow up 2 | L55: NO PSE | M55: WD support - Chat/Call/Mail | N55: New Prospect | O55: Free User | P55: Deal Lost | Q55: 46209 | S55: Starter | U55: No recording | V55: Tried calling the cx - call forwarded and not answered - dropping mail for update
A56: 46041 | B56: IN | C56: Rohith | D56: jalaj.patil@cleantechsynergy.co.in | E56: Renewable energy | F56: #122128744 | G56: We want to understand all the features of workdrive | H56: None | K56: Do not follow | M56: WorkDrive - Book a Demo (direct) | N56: New Prospect | O56: Existing user | P56: Existing customer | Q56: 7 | S56: WP (Professional)
A57: 46041 | B57: IN | C57: Sakthi | D57: abhishek.sawant@wysetek.com | E57: Information Technology | F57: #150535108 | G57: 1. They have requested for an ETA of Offline Desktop app for Windows. Kirubbha 2. They wanted to know what would be the maximum rows and columns supported in Zoho Sheet Offline app once the offline feature is rolled out. Kumar Vinay Tikeshwar Sahu sahu 3. They also wanted to get early access for a stable Zoho Sheet Windows app, so that they can test importing their existing large sized spreadsheets in Zoho Sheet. When are we providing early access? | I57: MS Office 365 | K57: Follow up 3 | M57: From Sales End | N57: New Prospect | O57: POC | P57: Deal Lost | Q57: 1000+ | S57: WP flexi | U57: WP demo, they haven't recorded it. | V57: No response to the call and email.
A58: 46042 | B58: EU | C58: Jennifer | D58: niranjan@droneworx.ai | E58: Drone Services | F58: #2216101 | G58: Concerning drive, they have been using google drive and looking for no unauthorised downloads to handle their sensitive files, activity stats, better storage to manage their 20-30 GBs of data. | I58: Google WorkSpace | J58: 20-30 GB | K58: WP follow up | L58: NO PSE | M58: WorkDrive - Book a Demo (direct) | N58: New Prospect | O58: Suspended | P58: Deal Lost | Q58: 5 | S58: WP (Standard) | T58: Workplace team is following up with the prospect | U58: https://workdrive.zoho.in/file/x3dyz715f4b84497f46edaecc870b77e48280
A59: 46042 | B59: IN | C59: Rohith | D59: atharva.garad@digisecureinsurance.com | E59: Insurance | F59: #153840792 | G59: Queries in Zoho WorkDrive | K59: Do not follow | L59: NO PSE | M59: From Sales End | N59: New Prospect | O59: Existing user | P59: Existing customer | Q59: 33 | S59: WP (Professional)
A60: 46042 | B60: US | C60: Jennifer | D60: montana@xydrobe.com | E60: Media | F60: #153862456 | G60: They are a startup, mainly working with slack, pitch and notion. They are looking for a centralised DMS with their team working together on files with the option to access data from different devices. They are also looking to create share links and share with their global clients securely. | K60: Follow up 3 | L60: PSE546472 | M60: WorkDrive - Book a Demo (direct) | N60: New Prospect | O60: No | P60: Deal Lost | Q60: 46298 | S60: Business | T60: Reason was not mentioned - followed up asking reason for choosing different app | U60: https://workdrive.zoho.in/file/rj2346c5c82de6e4449689f4de44ab439087d
A61: 46043 | B61: IN | C61: Janani | D61: amittatrey@sysfuturetech.com | E61: IT services and technology | F61: #153800705 | G61: i am looking a backup solution for my client who has 20 user who has company laptop , and they need to take his machine backup on client , per user data around 100 gb . | K61: Follow up 2 | M61: WorkDrive - Book a Demo (direct) | N61: New Prospect | O61: No | P61: Deal Lost | Q61: 20 | S61: Team | U61: https://workdrive.zoho.in/file/gbhc36319dcda83aa4b31bc7a7efd380c26cb
A62: 46043 | B62: US | C62: Jennifer | D62: tallulah@harmonicspeech.com | E62: Healthcare | F62: #153771634 | G62: They have been using Google Workspace and looking for alternatives with HIPAA compliance. They had challenges with with AI popups and the increased pricing in google drive because of AI, along with their team members complaining with privacy issues with AI (not shared clearly, as she is not completely aware of it) | I62: Google WorkSpace | K62: WP follow up | L62: PSE546522 | M62: WorkDrive - Book a Demo (direct) | N62: New Prospect | O62: No | P62: Deal Lost | Q62: 10 | S62: WP (Standard) | U62: https://workdrive.zoho.in/file/rj23467750ac2c0b146519c04e17154d0bfd1
A63: 46043 | B63: IN | C63: Rohith | D63: kamran@aisharao.com | E63: Clothing | F63: #153840082 | G63: They are currently using Google Drive, but are facing storage limitations and high costs. They are looking for a more cost-effective storage solution specifically for their design and marketing teams. | H63: None | I63: Google Drive | J63: 1TB | K63: Sales follow up 2 | L63: NO PSE | M63: WorkDrive - Book a Demo (direct) | N63: New Prospect | O63: No | P63: Deal Lost | Q63: 10 | S63: Team
A64: 46043 | B64: ANZ | C64: Rohith | D64: esdevco.frans@gmail.com | E64: Construction | F64: #153737714 | G64: They are a construction company that currently relies heavily on physical paper documents and manual document handling. They are looking to move to a cloud-based solution to automate document storage, reviews, and approval processes. | H64: None | I64: Local Drive | K64: Sales follow up 3 | L64: PSE546869 | M64: From Sales End | N64: New Prospect | O64: No | P64: Deal Lost | S64: Business | V64: no response over call.
A65: 46043 | B65: IN | C65: Rohith | D65: ravi.patil@tq3travel.com | E65: Travels | F65: #153905364 | G65: Best practices on WorkDrive | H65: None | K65: Do not follow | L65: NO PSE | M65: WorkDrive - Book a Demo (direct) | N65: Existing Paid Cx | O65: Existing user | P65: Existing customer | Q65: 20 | S65: WP (Professional) | U65: No recording
A66: 46043 | B66: IN | C66: Jennifer | D66: saurabh_patel1212@yahoo.com | E66: Individual | F66: #153942401 | G66: Looking WorkDrive for himself at the moment to manage his client files securely in one centralised space. Currently the documents are fragmented and not saved securely, plus since he is planning to scaleup later with 5 user licenses. | H66: None | I66: Local Drive | K66: Sales follow up 2 | L66: PSE546910 | M66: WorkDrive - Book a Demo (direct) | N66: New Prospect | O66: Suspended | P66: Deal Lost | Q66: 1 | S66: Team | U66: https://workdrive.zoho.in/file/py0o8e3da2744ced44aa4ab8bd831caf3761f
A67: 46043 | B67: IN | C67: Sakthi | D67: chetan.lotlikar@axismf.com | E67: Investment Banking | F67: #153452804 | G67: As MS Office 2016 is at EOL and there is an immediate renewal coming up for MS Office, they are right now looking for a replacement for MS Office and evaluating Zoho Office Suite. | H67: Awaiting early access for Zoho Sheet Offline Windows app. | I67: MS Office 365 | K67: Sales follow up 3 | M67: From Sales End | N67: New Prospect | O67: Free User | P67: Deal Lost | Q67: 800 | S67: Zoho Office Suite Desktop apps | U67: Conducted on MS Teams meeting by prospect | V67: Hello Manoj, Since we had very short time to evaluate the OEMs, we had to go ahead with Microsoft. We will get in touch with you if there is any further requirement.
A68: 46043 | B68: IN | C68: Sakthi | D68: rajvishwakarma@railtelindia.com | E68: Government sector | F68: #154030990 | G68: Gave a demo on TrueSync and assisted them with migration from OneDrive to WorkDrive | I68: MS Office 365 | K68: Follow up 1 | M68: Direct Mail to Presales | N68: Already Engaged Px | O68: POC | P68: Deal Won | Q68: 500 | S68: WP (Professional)
A69: 46043 | B69: IN | C69: Jennifer | D69: saurabh_patel1212@yahoo.com | E69: Individual | F69: #153942401 | G69: Looking WorkDrive for himself at the moment to manage his client files securely in one centralised space. Currently the documents are fragmented and not saved securely, plus since he is planning to scaleup later with 5 user licenses. | H69: None | I69: Local Drive | K69: Sales follow up 2 | L69: PSE546910 | M69: WorkDrive - Book a Demo (direct) | N69: Already Engaged Px | O69: Suspended | P69: Deal Lost | Q69: 1 | S69: Team | U69: https://workdrive.zoho.in/file/py0o8e3da2744ced44aa4ab8bd831caf3761f
A70: 46044 | B70: ANZ | C70: Janani | D70: christin.casperson@moddule.com | E70: supply chain and logistics | F70: #153986127 | G70: Prospect was looking to switch from google to Zoho WorkDrive | K70: Sales follow up 1 | M70: From Sales End | N70: New Prospect | O70: Free User | P70: Deal Lost | Q70: 11-50 | S70: Starter | U70: https://workdrive.zoho.in/file/gbhc353e937872afb49cca738bcc3785f9ace | V70: Thank you for the follow up. We have decided to stay with our current solution. Thank you again for the demo and information.
A71: 46044 | B71: EU | C71: Rohith | D71: mark@dunelmpharma.com | E71: Pharmacuteical | F71: #152022345 | G71: WorkDrive + CRM integration | K71: Do not follow | L71: NO PSE | M71: Direct Mail to Presales | N71: Existing Paid Cx | O71: Existing user | P71: Existing customer | S71: Zoho One
A72: 46044 | B72: US | C72: Rohith | D72: montya@macmai.com | E72: Accounts | F72: #153973931 | G72: Demo on true sync app | H72: None | I72: Local drive | K72: Sales follow up 2 | L72: PSE547330 | M72: WorkDrive - Book a Demo (direct) | N72: New Prospect | O72: Yes | P72: Deal Won | Q72: 2 | R72: 60 | S72: Starter | U72: https://workdrive.zoho.in/file/e5ovz4e83f742619d4b3ebf9dd605c9425404 | V72: Tried reaching the prospect through phone not able to connect hence sent an email to the prospect.
A73: 46044 | B73: US | C73: Jennifer | D73: lgonzalez@tworld.com | E73: Brokerage | F73: #153974109 | G73: They are looking for organized team folders, role-based access control, secure file sharing, and the ability for agents to upload client documents. They also need simple user management options and the ability to immediately remove, access and transfer files when an agent is offboarded. | H73: None | I73: OneDrive | K73: Sales follow up 3 | L73: NO PSE | M73: WorkDrive - Book a Demo (direct) | N73: New Prospect | O73: No | P73: Deal Lost | Q73: 50 | U73: https://workdrive.zoho.in/file/e5ovz844b9dfefec4442c919590fc44906fae
A74: 46044 | B74: IN | C74: Sakthi | D74: deepak.kashyap@go-mmt.com | E74: Travel | F74: #152283842 | G74: 1. Existing File Ago user, with existing storage of 200GB. >> They are primarily using it for External sharing. >> They are looking for an alternative as there were so many limitations and not scalab | I74: FileAgo | K74: Sales follow up 3 | M74: From Sales End | N74: New Prospect | O74: Yes | P74: Deal Won | Q74: 100 | R74: 194040 | S74: Business | U74: Onboarding
A75: 46045 | B75: IN | C75: Janani | D75: sumit.gupta@remittanceshub.com | E75: financial | F75: #153893952 | G75: Paid Team edition user needed more clarifications on - Collect file feature | K75: Do not follow | M75: WorkDrive - Book a Demo (direct) | N75: Existing Paid Cx | O75: Existing user | P75: Existing customer | U75: https://workdrive.zoho.in/file/gbhc351cb7f4c5a30442f9aa9f6fc724a9fe8
A76: 46045 | B76: IN | C76: Janani | D76: akthakore@divanballubhai.edu.in | E76: educational institution | F76: #153840059 | G76: Needs a single centralized cloud repository accessible from multiple campuses. | K76: Sales follow up 2 | M76: From Sales End | N76: New Prospect | O76: No | P76: Deal Lost | Q76: 200+ | S76: Business | U76: https://workdrive.zoho.in/file/ws66n0af037759de94ebeace7309fc69fa429
A77: 46045 | B77: US | C77: Rohith | D77: jamie@globalregulatoryservices.com | E77: IT | F77: #153948518 | G77: Session booked by mistake | I77: OneDrive | K77: Do not follow | L77: NO PSE | M77: WorkDrive - Book a Demo (direct) | N77: New Prospect | O77: No | P77: No Scope for WD | T77: User booked the session by mistake They are currently using OneDrive and are not looking to switch services at this time | U77: No recording
A78: 46048 | B78: EMEA | C78: Rohith | D78: itadmin@choueri-uae.com | E78: Real estate | F78: #154150764 | G78: They are looking to set up a cloud-based storage solution for their business. The requirement is to have a shared folder/drive that can be accessed by all four users, with the admin having full control over access and permissions. They are currently using a NextGen cloud solution but lack proper control and permission management. | H78: None | I78: NextGen | K78: Sales follow up 2 | L78: PSE548129 | M78: From Sales End | N78: New Prospect | O78: Suspended | P78: Deal Lost | Q78: 4 | S78: Business | U78: https://workdrive.zohoexternal.in/external/67b5d4169ce32201c9ae5ff9f67504ad3e5c2304780962c7b7146032bca0e9c3 | V78: px didnt get an chance to speak with her management and she is flying to india this week for vacation so asked to follow in mail after a week
A79: 46048 | B79: IN | C79: Rohith | D79: sharmavin97@gmail.com | E79: Marketing | F79: #154310795 | G79: He was using Zoho Flow and needed Zoho Sheet for data storage. While testing Zoho Sheet, he was redirected to Zoho WorkDrive and wanted to understand its capabilities. | H79: None | I79: None | K79: Do not follow | L79: PSE550624 | M79: From Sales End | N79: Free Users | O79: Free User | P79: Free user | T79: No scope for Zoho WorkDrive | U79: https://workdrive.zoho.in/file/f19a6f16c177678b44fd084aca45252ca4e7c
A80: 46049 | B80: US | C80: Jennifer | D80: admin@serenetax.com | E80: Financial Services | F80: #112457618 | G80: They have been using OneDrive, however was facing sync issues and file duplications, since they would not like to maintain any file duplicates and now is their peak season for managing their client's tax files they are looking for alternatives and enroll soon. Apart from sync issues and file duplications, they are also looking for access levels where admin to only delete files, and collaboratively work on files. | H80: None | I80: OneDrive | K80: Follow up 2 | L80: NO PSE | M80: WD support - Chat/Call/Mail | N80: New Prospect | O80: No | P80: Deal Lost | Q80: Not confirmed | S80: Starter | T80: Deal Lost reason - Since the US tax season has started, we got too busy and this might not be the right time to switch our workflow. Can we connect after 04/20/2026 to work on this. | U80: https://workdrive.zoho.in/file/5zgbmbdb8f789576a478eaa34bed6074ae1f9
A81: 46049 | B81: IN | C81: Janani | D81: administrator@junooncapital.in | E81: financial services | F81: #154105006 | G81: Paid WP user , he have challenges to access Google Sheets when it is being shared to Zoho | K81: Do not follow | M81: WorkDrive - Book a Demo (direct) | N81: Existing Paid Cx | O81: Existing user | P81: Existing customer | S81: Team
A82: 46049 | B82: IN | C82: Janani | D82: ashishjain@pksurfacesystems.com | E82: manufacturing | F82: #153358690 | G82: Prospect is a startup and have already explore Zoho office suite application along with Wd | K82: Sales follow up 3 | M82: From Sales End | N82: New Prospect | O82: Yes | P82: Free user | Q82: 46298 | S82: Starter | U82: https://workdrive.zoho.in/file/gbhc30cfa5d7ff35f4fc486b8131f79c02715
A83: 46049 | B83: IN | C83: Rohith | D83: mohit@tekshapers.com | E83: Healthcare | F83: #154027986 | G83: Queries on Zoho WorkDrive | H83: None | K83: Sales follow up 2 | L83: PSE549454 | M83: Internally Looped | N83: Already Engaged Px | O83: No | P83: Deal Lost | S83: WP (Professional) | U83: No recording | V83: If you wish to bypass the IP restriction, kindly share the detailed reason for this request along with your business use case, as allowing access only via mobile, while restricting web access, may not serve the intended purpose.
A84: 46050 | B84: US | C84: Jennifer | D84: dkhan@careconnectionservices.com | E84: Hospital and Health Care | F84: #154218517 | G84: They were relying on Google Drive for a long time, and now they find it hard in managing their files to be organised, with not much options to filter the required files, so they are looking for better file organisation and search capabilities. | H84: None | I84: Google Drive | J84: <50 GB | K84: Sales follow up 3 | L84: PSE548698 | M84: From Sales End | N84: New Prospect | O84: No | P84: Deal Lost | Q84: 46300 | S84: Starter | U84: Px did not want to be recorded | V84: Happy with free
A85: 46050 | B85: IN | C85: Janani | D85: : nikhilvekariya33@gmail.com | E85: Consulting | F85: #154188562 | G85: Prospect was looking to switch from google to Zoho, and they are considering to migrate both Mail and Drive | K85: Sales follow up 1 | M85: WD support - Chat/Call/Mail | N85: New Prospect | O85: Yes | P85: Deal Won | Q85: 1 | S85: Free Individual | U85: https://workdrive.zoho.in/file/ws66n95137331b82d4dd79be7d1b878d9d350
A86: 46050 | B86: ANZ | C86: Janani | D86: exec@killin.com.au | E86: Investments | F86: #153502620 | G86: Prospect was looking for about WorkDrive and its features overview | K86: Sales follow up 1 | M86: WorkDrive - Book a Demo (direct) | N86: New Prospect | O86: No | P86: Deal Lost | Q86: 15 | S86: WP (Standard) | U86: https://workdrive.zoho.in/file/gbhc3e9cb03128f494ddaac2336209ed3c549
A87: 46050 | B87: IN | C87: Sakthi | D87: vishnus@softcell.com | E87: Global System Integrator | F87: #154017676 | G87: There are 100 computers provided to 100 employees. The data are available in their computers and hard-disk. Recovering the data when it gets corrupted from computer or hard-disk becomes tedious for them. | H87: 1. As of now, Desktop Folder sync via TrueSync is only limited to sync upto 5 Desktop folders and not the entire computer with their drives like C; E; D;. 2. They want their employees to work as they want and not force them to keep their content only in those 5 desktop folders, which they might not do, even if enforced. They are looking to use WorkDrive as a backup solution for their entire computers. >> They want the entire computer to be backed up in the cloud. Do we have this in our roadmap? @Kingsley Reuben Joseph @Kalidoss Rajendran @Manikandan N | I87: Local Drive | K87: Follow up 1 | M87: WorkDrive - Book a Demo (direct) | N87: New Prospect | O87: No | P87: Deal Lost | Q87: 100 | S87: Business
A88: 46050 | B88: IN | C88: Rohith | D88: automation.integration@myoperator.co | E88: Automation | F88: #154246132 | G88: Knowledge management solution | I88: GetGuru | K88: Do not follow | L88: NO PSE | M88: WorkDrive - Book a Demo (direct) | N88: New Prospect | O88: Yes | P88: No Scope for WD | U88: https://workdrive.zoho.in/file/v340a2b2cb5d262144407ba690cd28d76e4c1
A89: 46050 | B89: IN | C89: Jennifer | D89: customdesign970@gmail.com | E89: Architecture and Design | F89: #154224762 | G89: Concerning storage, they are looking to track file activity, to be able to edit their designer files, apply tasks and have admin control for their project executives. | I89: Google Drive and Dzylo | J89: < 5 TB | K89: Sales follow up 2 | L89: PSE549093 | M89: WorkDrive - Book a Demo (direct) | N89: New Prospect | O89: No | P89: Deal Lost | Q89: 10 | S89: Business | U89: Px did not want to be recorded
A90: 46051 | B90: IN | C90: Jennifer | D90: info@staffinitysolutions.co.uk | E90: Human Resources | F90: #154135131 | G90: They are looking for desktop version, the option to share files with their global clients who are in UK, Pakistan. Currently they dont have formal system in place to manage files. | K90: WP follow up | L90: NO PSE | M90: WorkDrive - Book a Demo (direct) | N90: New Prospect | O90: No | P90: Deal Lost | Q90: 5 | S90: WP (Standard) | U90: https://workdrive.zoho.in/file/rvdm5c3fd26af30844dfaad0bf37e34c3bd11
A91: 46051 | B91: IN | C91: Rohith | D91: nk@nkpr.in | E91: Media | F91: #153840386 | G91: Onboarding session | H91: Custom roles & permission and Integration with CAD | K91: Do not follow | M91: WorkDrive - Book a Demo (direct) | N91: Existing Paid Cx | O91: Existing user | P91: Existing customer | W91: 1. Custom Roles & Permissionshttps://sprints.zoho.in/workspace/zdocs#P15/itemdetails/I7130 2. Auto CAD integration. https://sprints.zoho.in/workspace/zdocs#P15/itemdetails/I7451
A92: 46051 | B92: IN | C92: Jennifer | D92: arunrajchettiyar@gmail.com | E92: Training | F92: #154271961 | G92: Startup, who have just started preparing KT sessions and related documents for their clients. They have individually maintained files in their local drive, which was difficult to access beyond their work environment. Plus collaborating with their clients was a challenge hence looking to move into Zoho Ecosystem and planning to explore mail, CRM, sites, forms, drive and more. | H92: Search by Video Chapter Name, Search by Timestamp Comment Content, Search Within Video Content, Multilingual Transcription generation for videos (specially Tamil). | I92: Local Drive | J92: < 1 TB | K92: Sales follow up 2 | L92: PSE549664 | M92: From Sales End | N92: New Prospect | O92: Extended | P92: Deal Won | Q92: 3 | R92: 55.44 | S92: Starter | U92: https://workdrive.zoho.in/file/13zc92fe794d354db402b996bc446ecbf0307 | V92: spoke with the cx, explained him on the plan nd pricing and help him book demo with our team demo went well , and evaluation is progressing well within his org as well , and shraed the price quote , he will be moving forward with the paid version once if the trial period got expired | W92: https://sprints.zoho.in/workspace/zdocs#P15/itemdetails/I2111
A93: 46052 | B93: US | C93: Jennifer | D93: pdalal@curruxvision.com | E93: Transportation Infrastructure | F93: #154173397 | G93: They have large amount of documents expected to be around 3 TB in their Google Drive, where they have challenges with file duplication, shared file access for their clients. Looking for the option to maintain files with track changes, set up permissions, maintain versions, work together on files, receive notifications. | I93: Google Drive | J93: 3 TB | K93: Sales follow up 1 | L93: PSE549665 | M93: From Sales End | N93: New Prospect | O93: Yes | P93: Deal Won | Q93: 4 | R93: 216 | S93: Team | U93: https://workdrive.zoho.in/file/13zc99de2f2829d704bd1b12d79423ab99308
A94: 46052 | B94: IN | C94: Sakthi | D94: jashir.alimathil@dailydelight.com | E94: Food manufacturing | F94: #154309576 | G94: The requirement was to have documents sent to Workflow for an approval from a manager and the end of the workflow they want to add e-sign. | H94: They wanted to sent up file contract and expiry for the files. They wanted to collect E-sign at the end of the workflow. >> Showcased “Execute custom function” where sign can be added. | I94: Local Servers | K94: Sales follow up 3 | M94: WorkDrive - Book a Demo (direct) | N94: New Prospect | O94: No | P94: Deal Lost | Q94: 100+ | S94: Business | U94: https://workdrive.zoho.in/file/0vc1317ca5d797f3047cfb0f6218b3add78c1 | V94: No response for several call attempts and follow up email | W94: File Expiry:https://sprints.zoho.in/workspace/zdocs#P15/itemdetails/I7169
A95: 46052 | B95: IN | C95: Rohith | D95: preetam.shetty@navsanindia.com | E95: IT | F95: #153060512 | G95: They are currently using Zoho People and ManageEngine products and are looking for a centralized cloud storage solution for unstructured data with around 1 TB of storage. They have evaluated Box and Dropbox but prefer to continue within the Zoho ecosystem for document management. | H95: Reminders for documents | I95: Local Drive | J95: 1TB | K95: Sales follow up 2 | L95: PSE549963 | M95: From Sales End | N95: New Prospect | O95: Yes | P95: Deal Won | Q95: 20 | R95: 1306.8 | S95: Business | U95: https://workdrive.zoho.in/file/0vc13f0e971a6621c45f2b2cf93bfffcb934c | W95: Document reminders https://sprints.zoho.in/workspace/zdocs#P15/itemdetails/I7129
A96: 46052 | B96: IN | C96: Janani | D96: itsupport@thevatconsultant.com | E96: Consulting | F96: #154320536 | G96: Prospect is already using Zoho WorkDrive Free individual edition and now wanted to switch to Team edition and wanted to explore features that will be benefit them as a team to store, and manage documents in cloud | K96: Follow up 1 | M96: From Sales End | N96: Free Users | O96: Yes | P96: Deal Won | Q96: 7 | S96: WP flexi | U96: https://workdrive.zoho.in/file/mnji985c271caecf6431a80364004fef296ec
A97: 46052 | B97: IN | C97: Janani | D97: sohail@cloudmojo.tech | E97: IT | F97: #154261241 | G97: I am using a Zoho One account and need a Demo on the work drive to show me how it works. | K97: Do not follow | M97: Direct Mail to Presales | N97: Existing Paid Cx | O97: Existing user | P97: Existing customer | S97: Zoho One | U97: https://workdrive.zoho.in/file/mnji98d468b7a58414cf9b9d2954b3244220b
A98: 46052 | B98: IN | C98: Janani | D98: nithin@purplerock.com | E98: FInance | F98: #154251472 | G98: But the team needs to setup an application that has DC in Saudi , since they are already using Zoho and aware of SA DC | I98: MS Office platform | K98: Sales follow up 3 | M98: WorkDrive - Book a Demo (direct) | N98: New Prospect | O98: No | P98: Deal Lost | Q98: 15 | S98: Team | U98: https://workdrive.zoho.in/file/mnji9baf42da68fbc4f56b72f89de92eef5ba
A99: 46052 | B99: IN | C99: Rohith | D99: accounts@dvmgopalandassociates.in | E99: Legal | F99: #154359737 | G99: They operate three different firms and currently use Zoho products across all of them, including Zoho Books and Payroll. They are looking to implement Zoho WorkDrive as a centralized document management system across all firms. Their use case includes storing employee appointment letters, agreements, vendor POs, client NDAs, and contracts. | H99: None | I99: OneDrive | K99: Sales follow up 2 | L99: NO PSE | M99: From Sales End | N99: New Prospect | O99: Free User | P99: Deal Lost | Q99: 10 | S99: Starter | U99: https://workdrive.zoho.in/file/0vc137f5da8f31ae54caa950b13d008620820
A100: 46052 | B100: IN | C100: Rohith | D100: sentme@zohomail.in | E100: Personal | F100: #154324374 | G100: They are currently using Google Drive, with storage usage nearing 1TB. Due to higher costs, they are exploring alternative solutions and prefer an Indian company. The user wanted a comparison between Google Drive and Zoho WorkDrive, details on storage options, and information on migrating existing data. | H100: None | I100: Google Drive | J100: 1TB | K100: Sales follow up 3 | L100: PSE550455 | M100: From Sales End | N100: New Prospect | O100: Free User | P100: Deal Lost | Q100: 3 | U100: https://workdrive.zoho.in/file/mnji9b321c95e8ed5430ba4fb9fc1619264d9 | V100: spoke with him he is evaluating the Zoho Workplace and planning to migrate from Google one so no requirements for now and had a query from the technical team, got them informed to address this promptlyc

Sheet February
A1: Date | B1: Region | C1: Handled by | D1: Email address | E1: Industry | F1: Ticket ID | G1: Purpose | H1: New requirements | I1: Current Platform | J1: Existing data size | K1: Follow up stages | L1: PSE Creation | M1: Source | N1: Engagement Type | O1: Trial sign up | P1: Status | Q1: Deal Size | R1: Revenue | S1: Suggested/purchased edition | T1: Notes | U1: Demo Recording | V1: Sales Notes from CRM | W1: Sprint link
A2: 46055 | B2: IN | C2: Sakthi | D2: shinoy.thachapully@ae.mcd.com | E2: Food | F2: #154488423 | G2: They are currently using Legacy NTFS Windows server and they want to migrate over to Zoho WorkDrive. | H2: They have requested for UAE sensitive information types like Emirates passport, Emirates ID. >> We have requested for the list of predefined sensitive information types that need to be added by default. They want exemptions for files applied with DLP. Like a time based exemption. >> As of now, marking “Remove classification label”, once marked it is not time based exemptions. >> Once the time is set up the want the removed classification label to be reapplied with the classification label. They have requested for integration with Teams, Office 365, Sharepoint. >> Do we have any integration with Teams in our roadmap. For O365 we can suggest MS office extension. For Sharepoint, we have requested for more information. | I2: Legacy NTFS Windows server | K2: Sales follow up 3 | M2: WorkDrive - Book a Demo (direct) | N2: New Prospect | O2: No | P2: Deal Lost | Q2: 550 | S2: Business | U2: MS Teams | V2: Update from Shinoy - Mc D "I am in talk with our global cyber team to whitelist Zoho workdrive for POC" | W2: 1. UAE Sensitive information type:https://sprints.zoho.in/workspace/zdocs#P15/itemdetails/I7229 2. ZScalar integration: https://sprints.zoho.in/workspace/zdocs#P15/itemdetails/I7231
A3: 46055 | B3: IN | C3: Janani | D3: info@prcas.com | E3: Financial | F3: #154380360 | G3: Zoho Mail user, need more information on Individual edition as of now they are looking to store data to Zoho WorkDrive cloud | J3: GDrive | K3: Follow up 1 | M3: WorkDrive - Book a Demo (direct) | N3: New Prospect | O3: Yes | P3: Deal Won | Q3: 1 | S3: WP (Standard) | U3: https://workdrive.zoho.in/file/1obh949b6c61eb6a84224837ee046365ba7f4
A4: 46055 | B4: US | C4: Rohith | D4: adam.teitelbaum@wartsila.com | E4: Sales | F4: #154399628 | G4: They are looking to build a centralized sales content library where all documents are stored in one place and can be easily searched and filtered based on content types. The setup should allow a single admin to create, edit, and manage all sales content, while the sales team should have view-only access to ensure content consistency. Additionally, they are looking for a cost-effective licensing model to support this structure. | H4: None | I4: Local Drive | K4: Sales follow up 3 | L4: No PSE | M4: WorkDrive - Book a Demo (direct) | N4: New Prospect | O4: Yes | P4: Deal Lost | Q4: 3 + 20CL | S4: Business | U4: https://workdrive.zoho.in/file/ddt54977a91741ab644a7a34ed16fdd888522 | V4: No response from cx
A5: 46055 | B5: US | C5: Jennifer | D5: atkconsult3@gmail.com | E5: Financial Services | F5: #154433327 | G5: They are exploring broader Zoho apps and planning to move to the zoho ecosystem and have signed up for Zoho One already. Concerning WD, they are looking for multiple user access, with permissions applied for now. | H5: 7-year data retention feasibility | K5: Z1 follow up | L5: No PSE | M5: WorkDrive - Book a Demo (direct) | N5: New Prospect | O5: Yes | P5: Deal Lost | Q5: 1 | S5: Zoho One | T5: Still in trial evaluating - Zoho one | U5: https://workdrive.zoho.in/file/f19a64b5d1cc9053747c28108e2dac2ef2202 | W5: https://sprints.zoho.in/workspace/zdocs#P15/itemdetails/I6334/details
A6: 46056 | B6: US | C6: Jennifer | D6: jasonb@ricelandcabinet.com | E6: Manufacturing | F6: #153778548 | G6: They currently need their team members to be able to capture pictures from their different branches to WorkDrive, where their staff members are not tech savvy. They are also looking for document sharing with their clients, which they have been doing with zoho mail now. they also used dropbox, but not extensively, so no comments on it. | H6: None | K6: Sales follow up 3 | L6: PSE550740 | M6: From Sales End | N6: New Prospect | O6: Suspended | P6: Deal Lost | Q6: 20 | S6: Starter | U6: https://workdrive.zoho.in/file/f19a68b15f4e7792d4555abacf49e9747e5fa | V6: second follow up mail sent
A7: 46056 | B7: IN | C7: Jennifer | D7: jay19shah@gmail.com | E7: Financial Services | F7: #154475521 | G7: They have been using local server, NAS backup for all these years, however they have been having challenges with accessing and planning to move to a cloud based to maintain their files with MS office, PDF, Image extensions. They currently own 100 GB of data and expecting to expand a little more, with the options to access from mobile and set access levels for their members. | H7: None | I7: Local Server | J7: 100 GB | K7: Sales follow up 3 | L7: PSE551193 | M7: From Sales End | N7: New Prospect | O7: Suspended | P7: Deal Lost | Q7: 10 | S7: Starter | U7: https://workdrive.zoho.in/file/ddt54b473e77fb44945c293458b101e058863 | V7: no response from the prospect
A8: 46056 | B8: IN | C8: Janani | D8: atchula@zohomail.in | E8: Personal | F8: #154485655 | G8: Prospect needs cloud storage to store family photos | J8: Google photos | K8: Sales follow up 3 | M8: WD support - Chat/Call/Mail | N8: New Prospect | O8: Yes | P8: Deal Lost | Q8: 1 | S8: Free Individual | U8: https://workdrive.zoho.in/file/1obh926832b4cfd46447da8bc10c8696c80f3
A9: 46056 | B9: IN | C9: Janani | D9: edp@krishcarbon.com | E9: Manufacturing | F9: #154465180 | G9: Prospect is looking for our primary requirement is that we want to share the document within our organisation. | J9: System server | K9: Sales follow up 3 | M9: From Sales End | N9: New Prospect | O9: Yes | P9: Deal Lost | Q9: 10-15 | S9: Team | U9: https://workdrive.zoho.in/file/1obh994e2751b212f4d9aadb75e58ef3b08b3 | V9: Spoke with cx and they are not looking for this application currently.
A10: 46056 | B10: IN | C10: Janani | D10: anas@goldenfinty.com | E10: Electrical & Mechanical Contracting | F10: #154413902 | G10: Prospect is looking for an cloud storage platform where they collect data and store in cloud for other team members to access it | J10: OneDrive | K10: Sales follow up 3 | M10: WorkDrive - Book a Demo (direct) | N10: New Prospect | O10: No | P10: Deal Lost | Q10: 10 | S10: Starter | U10: https://workdrive.zoho.in/file/1obh945e5f09f915347f8b718ae51057b3684
A11: 46056 | B11: IN | C11: Janani | D11: sumit@nagpal.law | E11: Law | F11: #150564803 | G11: Prospect is using OneDrive and wanted to switch to zoho due to some challenges in OneDrive | J11: OneDrive | K11: Sales follow up 2 | M11: WorkDrive - Book a Demo (direct) | N11: New Prospect | O11: No | P11: Deal Lost | Q11: 13 | S11: Starter | U11: https://workdrive.zoho.in/file/1obh9b436450577644980959b6c12196cae41 | V11: Looking for Zoho Workplace
A12: 46056 | B12: IN | C12: Rohith | D12: raghav.banflexcables@gmail.com | E12: B2B | F12: #154464648 | G12: They are a B2B cable company based in Delhi currently using a local network drive, which lacks proper access control, leads to version conflicts, and makes it difficult to access data outside the office. | H12: None | I12: Network Drive | J12: 5GB | K12: Sales follow up 3 | L12: PSE551368 | M12: From Sales End | N12: New Prospect | O12: Yes | P12: Deal Lost | Q12: 46366 | S12: Team | U12: https://workdrive.zoho.in/file/r9vht2a9685e2dd3b425e8b317fd51a72891c | V12: Px declined the call after introduction
A13: 46056 | B13: IN | C13: Rohith | D13: nistha@caankur.com | E13: IT | F13: #154475061 | G13: They are looking for a document storage solution to manage client data, where users can edit files but are restricted from deleting them unless the admin explicitly allows it. At present, all documents are stored on a local drive. They have evaluated other tools but felt those solutions did not adequately address their access control and permission requirements. | H13: None | I13: Local Drive | K13: Sales follow up 3 | L13: PSE551387 | M13: WorkDrive - Book a Demo (direct) | N13: New Prospect | O13: Yes | P13: Deal Lost | U13: https://workdrive.zoho.in/file/ddt54852a6401347e4589aa9fca6f858d7e35 | V13: spoke with px she stated that they will continue with their existing subscription
A14: 46057 | B14: US | C14: Jennifer | D14: fabian@oakleewellness.com/ fabian.newman@oakleewellnessbilling.com | E14: Hospital and Health Care | F14: #154500314 | G14: Concerning Drive, they are looking for option to create folder for each of their employee to access exclusively, with different access levels, and desktop access. | H14: None | I14: Box | J14: 20-30 GB | K14: Sales follow up 2 | L14: No PSE | M14: WD support - Chat/Call/Mail | N14: New Prospect | O14: Yes | P14: Deal Won | Q14: 8 | R14: 104.54 | S14: WP (Standard) | T14: purchased from fabian.newman@oakleewellnessbilling.com | U14: https://workdrive.zoho.in/file/1obh9726447234096497e869ae92c4e54a8dd
A15: 46057 | B15: IN | C15: Rohith | D15: caakashag9@gmail.com | E15: Marketing | F15: #154205905 | G15: They are looking for a cloud storage solution for three members, where each user has a private space, along with a shared common space for collaboration. | H15: None | I15: Local Drive | K15: Sales follow up 3 | L15: PSE552267 | M15: WD support - Chat/Call/Mail | N15: New Prospect | O15: Yes | P15: Deal Lost | Q15: 3 | U15: No recording | V15: Busy line - no response over mail/calls
A16: 46057 | B16: IN | C16: Rohith | D16: ali@emeraldenc.com | E16: Metals & minerals | F16: #153549439 | G16: They are an electrical contracting company handling a high volume of project documents and are looking for a centralized cloud storage solution with better control, visibility, and access restrictions. They want to prevent unauthorized copying, downloading, or sharing of sensitive documents, and the solution should be easy for non-IT staff to adopt. | H16: Custom roles & permission | I16: Local Drive | K16: Sales follow up 3 | L16: PSE552314 | M16: From Sales End | N16: New Prospect | O16: Yes | P16: Deal Lost | Q16: 10-20 | S16: Business | U16: https://workdrive.zoho.in/file/nkkih6525f41b96f04f6c90174e81ad70956a | V16: Not responding to calls or emails. | W16: https://sprints.zoho.in/workspace/zdocs#P15/itemdetails/I7452/details
A17: 46057 | B17: IN | C17: Janani | D17: kunal.parikh@ralsonics.com | E17: IT | F17: #154482268 | G17: Prospect is from manufacturing company and there are over 80-100 employees in the organisation. but he needs a centralized respository to store all the image, files and folders in common folder so that each department can get easy | K17: Sales follow up 3 | M17: From Sales End | N17: New Prospect | O17: Yes | P17: Free user
A18: 46057 | B18: IN | C18: Janani | D18: itkaraulibhojubeer@gmail.com | E18: Medical | F18: #154472095 | G18: Prospect is from clinical and diagnostic labs. And needed an software equivalent to LIS in Zoho | J18: LIS | K18: Do not follow | M18: WD support - Chat/Call/Mail | N18: New Prospect | O18: No | P18: No Scope for WD
A19: 46057 | B19: US | C19: Jennifer | D19: imartinez@jasperenterprisesinc.com | E19: Construction | F19: #154507399 | G19: They are looking to manage their files better and to have it organised, with accessible to their members or external users. They currently have no system in place to manage their files. | H19: None | K19: Z1 follow up | L19: No PSE | M19: WorkDrive - Book a Demo (direct) | N19: New Prospect | O19: Free User | P19: Deal Lost | Q19: 46174 | S19: Zoho One | T19: Stil in Zoho One trial - testing | U19: No recording - px requested | V19: No response from cx
A20: 46058 | B20: IN | C20: Janani | D20: knconsultantsind@gmail.com | E20: Consulting | F20: #154524230 | G20: Prospect is currently using system server, Tally, Excel and multiple other applications to create, edit and collaborate | K20: Sales follow up 2 | M20: From Sales End | N20: New Prospect | O20: Yes | P20: Deal Won | Q20: 10 | S20: Team
A21: 46058 | B21: IN | C21: Rohith | D21: mohamed.aareef@kiongroup.com | E21: Machinery manufacturer | F21: #154592783 | G21: The customer is evaluating Zoho WorkDrive to understand its features, capabilities, and suitability for enterprise-wide document management. They are looking for a centralized document management system for ~50 users across Europe, the Middle East, Asia-Pacific, and China. Key areas of interest include document storage and version control, team collaboration and access controls, security and compliance, integrations with Zoho and third-party applications, and enterprise-friendly pricing and licensing models. They have prior experience with Zoho CRM Analytics but this was their first exposure to Zoho WorkDrive | H21: Expiry for documents | K21: Sales follow up 3 | L21: PSE552420 | M21: From Sales End | N21: New Prospect | O21: No | P21: Deal Lost | Q21: 50 | S21: Business | T21: Connect post | U21: https://workdrive.zoho.in/file/nkkih8d3e828a2009425db49f3b564a0275f6 | V21: No response from cx | W21: https://sprints.zoho.in/workspace/zdocs#P15/itemdetails/I7323
A22: 46058 | B22: EU | C22: Rohith | D22: jennifer.gonzalez@graphite-technology.com | E22: IT | F22: #154189469 | G22: Zoho CRM integration with OneDrive | I22: OneDrive | K22: Do not follow | L22: PSE552427 | M22: From Sales End | N22: Free Users | O22: No | P22: No Scope for WD
A23: 46059 | B23: IN | C23: Rohith | D23: livingston.d@tsts.in | E23: IT | F23: #152346855 | G23: They want a clear folder structure based on departments and years. Their objective is to maintain a single source of truth for documents, supported by strong versioning, audit logs, and granular access controls at both folder and file levels. They also require multi-stage approval workflows for documents, secure access across web, desktop, and mobile platforms with admin-level controls, and robust security and compliance features to meet ISO/QMS audit requirements. Additionally, they want smooth collaboration capabilities for both internal teams and external users. | H23: Watermarks for all documents | I23: NAS Drive | K23: Sales follow up 2 | L23: PSE553469 | M23: WD support - Chat/Call/Mail | N23: Already Engaged Px | O23: No | P23: Deal Lost | Q23: 100 | S23: Business | T23: Connect post | U23: https://workdrive.zoho.in/file/ws66n9a4da5e250824d7b800882b457718ec6 | V23: Spoke with the cx, they haen;t started with the trial will get back to us post to the evlaution on next week follow up email sent | W23: https://sprints.zoho.in/workspace/zdocs#P15/itemdetails/I7453
A24: 46059 | B24: IN | C24: Rohith | D24: kunal@spap.in | E24: Information service | F24: #153136027 | G24: The customer has already purchased Zoho WorkDrive and wants to ensure that all data remains accessible strictly within the WorkDrive environment. Users, including those working remotely or from outstation locations, should be able to access and work on files without downloading them to local machines. Any upload or download activity should remain controlled within the Drive ecosystem. | H24: None | K24: Do not follow | L24: PSE553768 | M24: From Sales End | N24: New Prospect | O24: Yes | P24: Deal Won | Q24: 8 | S24: Starter
A25: 46059 | B25: IN | C25: Rohith | D25: parthiv.panchal@devx.work | E25: Software | F25: #154632266 | G25: The customer wants to build a library-style document structure similar to what they currently use in Microsoft OneDrive. They need a main index page (for example, “Audited Financials”) that, when clicked, allows users to select a specific year such as 2025 or 2024. Once a year is selected, all documents within that respective folder should be displayed. | H25: None | I25: OneDrive | K25: Sales follow up 3 | L25: No PSE | M25: WorkDrive - Book a Demo (direct) | N25: New Prospect | O25: Yes | P25: Deal Lost | Q25: 3 | S25: Starter | U25: https://workdrive.zoho.in/file/l9oi3ec56b991bdab4ede89cafb10dcfff39f | V25: No response from cx
A26: 46059 | B26: IN | C26: Jennifer | D26: abhay.nawale@gmail.com | E26: IT | F26: #154113603 | G26: hey are currently using Google Suite and looking for certain suite like service in Zoho for managing files, mails, and meetings. | I26: Google Suite | K26: WP follow up | L26: No PSE | M26: Internally Looped | N26: New Prospect | O26: No | P26: Deal Lost | Q26: 1 | T26: WP team following up
A27: 46058 | B27: IN | C27: Sakthi | D27: sachin.baluja@shivnadarfoundation.org | E27: IT | F27: #152016104 | G27: Business unit head and procurement head for Shiv Nadar foundation attended the session along with other key stakeholders. | H27: 1. Upon overdue of the approval during a workflow, actions like auto-approved or auto-reject has to be done. 2. Slab based pricing 3. In-house support assistance. 4. Preview support for DWG files 5. Zia hubs early access 6. E-sign integration with custom functions. | I27: OneDrive | K27: Sales follow up 3 | M27: From Sales End | N27: Already Engaged Px | O27: No | P27: Deal Lost | Q27: 50 +500 client licenses | S27: Business | T27: Connect post | U27: On campus demo | V27: Spoke with their procurement head and clarified all their commercial queries. Cx may need another 10-15 days to get this cleared from the procurement end. | W27: Auto CAD preview support: https://sprints.zoho.in/workspace/zdocs#P15/itemdetails/I7462
A28: 46062 | B28: IN | C28: Janani | D28: siddhartha.sarkar@meldx.in | E28: IT | F28: #154656070 | G28: Prospect is already part of Zoho using Payroll and CRM and wanted to know how to store their files in Zoho WorkDrive in an organised way | K28: Follow up 1 | M28: WorkDrive - Book a Demo (direct) | N28: New Prospect | O28: Yes | P28: Deal Won | Q28: 1 | S28: Business | U28: https://workdrive.zoho.in/file/ws66n2068f095eb244e17bcfda294fab89640
A29: 46062 | B29: IN | C29: Rohith | D29: ranjith@rantronicstechnology.com | E29: Electronics | F29: #154211791 | G29: The customer is looking for an online cloud storage solution to store all their project-related documents. No additional requirements were raised during the discussion. | H29: None | K29: Follow up 3 | L29: No PSE | M29: WD support - Chat/Call/Mail | N29: New Prospect | O29: Yes | P29: Deal Lost | Q29: 3 | S29: Starter | T29: No response from cx
A30: 46062 | B30: IN | C30: Jennifer | D30: tawarventures@gmail.com | E30: Construction | F30: #154771687 | G30: they are using their server to maintain their files, however have challenges when need to access files from their sites via other systems or mobile. | H30: none | I30: on-premise | J30: <1 TB | K30: Sales follow up 2 | L30: PSE553074 | M30: From Sales End | N30: New Prospect | O30: Yes | P30: Deal Won | Q30: 3 | R30: 55.44 | S30: Starter | U30: https://workdrive.zoho.in/file/qn8e235d74a6d117a483bbdefa9c727b0fa21
A31: 46062 | B31: EU | C31: Jennifer | D31: waqas@global-security.co.uk | E31: Security | F31: #2275029 | G31: They are looking for cloud based storage solution to manage their files with no duplications and to have their members from London and Pakistan to access as well. | H31: none | I31: DropBox | J31: 50 GB | K31: Sales follow up 3 | L31: No PSE | M31: WorkDrive - Book a Demo (direct) | N31: New Prospect | O31: Suspended | P31: Deal Lost | Q31: 1 | S31: Starter | U31: https://workdrive.zoho.in/file/qn8e2b7b59b3a3bff4390a56c43b1f39f0467 | V31: Email sent - 3 followups
A32: 46063 | B32: IN | C32: Janani | D32: sskpas@gmail.com | E32: Consulting | F32: #154803355 | G32: Prospect is from consulting services looking for a cloud storage platform for 21 users who is part of the org | I32: System | K32: Sales follow up 1 | M32: WorkDrive - Book a Demo (direct) | N32: New Prospect | O32: No | P32: Deal Lost | Q32: 21 | S32: Team | U32: https://workdrive.zoho.in/file/gxtko8201ea5bcc934808bfaf4bb276c1a46d | V32: Ringed and no response - and no response over mail
A33: 46063 | B33: IN | C33: Sakthi | D33: nupur.madaan@fwdefence.com | E33: Defence | F33: #154635017 | G33: 1. The prospect is an existing Zoho Mail and Zoho People user. | I33: Google Workspace | K33: Sales follow up 3 | L33: PSE560110 | M33: WorkDrive - Book a Demo (direct) | N33: New Prospect | O33: Yes | P33: Deal Won | Q33: 40 | R33: 67200 | S33: Starter | U33: https://workdrive.zoho.in/file/ltgcl01fc2fc3fc464fff99738df1a7a8d0ae
A34: 46063 | B34: IN | C34: Jennifer | D34: sumeet.sodhani@gmail.com | E34: CA | F34: #154821218 | G34: They are using an on-premise file server, but faced difficulties accessing files while traveling. This often led to manual file transfers, resulting in file duplication and challenges in maintaining a single, consistent version of the same file. | H34: None | I34: on-premise | K34: Sales follow up 3 | L34: PSE553553 | M34: From Sales End | N34: New Prospect | O34: No | P34: Deal Lost | Q34: 7 | U34: https://workdrive.zoho.in/file/l9oi3432634188af347c5a8551f628bfcc383 | V34: spoke with px he stated that he is occupied with some other work and will get back after 10days
A35: 46064 | B35: IN | C35: Janani | D35: akash.gupta@veeline.com | E35: Manufacturing | F35: #154815828 | G35: Prospect is looking for cloud storage space to store and collaborate with documents within the team and provide them proper access level and permissions | H35: None | I35: System Drive | J35: 3TB | K35: Sales follow up 2 | M35: From Sales End | N35: New Prospect | O35: No | P35: Deal Lost | Q35: 10 | S35: Team | U35: https://workdrive.zoho.in/file/gxtko8201ea5bcc934808bfaf4bb276c1a46d
A36: 46064 | B36: IN | C36: Janani | D36: csgsbhat@gmail.com | E36: CA | F36: #153909151 | G36: Prospect is looking for cloud storage to store their tally documents and provide access to their users who are working remotely right now | H36: None | I36: System Drive | J36: 3TB | K36: Sales follow up 3 | M36: WorkDrive - Book a Demo (direct) | N36: New Prospect | O36: Yes | P36: Deal Won | Q36: 5 | S36: Team | U36: https://workdrive.zoho.in/file/f05xz2c1964cc8d5a4fb4895756925558c6f5
A37: 46064 | B37: US | C37: Rohith | D37: sam@goodluckusa.com | E37: Information service | F37: #154834363 | G37: Requirement is related to Zoho CRM | H37: None | K37: Do not follow | L37: No PSE | M37: WorkDrive - Book a Demo (direct) | N37: Partners | O37: Free User | P37: No Scope for WD | U37: https://workdrive.zoho.in/file/xgtrm7aa2c9b2129043edad6536e201bbe431
A38: 46064 | B38: IN | C38: Jennifer | D38: jagachchandarr.ljconsulting@gmail.com | E38: Consultancy | F38: #154914117 | G38: Px is using dropbox, however they find difficult with accessing the files few times, so manually they are sending the files back and forth, they also tried using Gdrive and finally have reached here. | H38: None | I38: DropBox | K38: Follow up 2 | L38: No PSE | M38: WorkDrive - Book a Demo (direct) | N38: New Prospect | O38: Yes | P38: Deal Won | Q38: 3 | R38: 5040 | S38: Starter | U38: No recording - connected via Zoho voice and shared screen through meeting
A39: 46065 | B39: IN | C39: Rohith | D39: jyoti@kelevosoftware.co.in | E39: Zoho Partner | F39: #154921590 | G39: As a Zoho Partner, they requested a detailed process walkthrough/demo to better understand the current workflow and system usage. The objective is to align the Zoho solution accurately with their customer’s business requirements. They wanted a complete end-to-end explanation that would help them design the integration and implementation properly. | H39: None | K39: Do not follow | L39: No PSE | M39: WorkDrive - Book a Demo (direct) | N39: Partners | O39: Partner | P39: Partner | U39: https://workdrive.zoho.in/file/l8q3i4edfebc500ce4333a3e73e053bf945ba
A40: 46065 | B40: EMEA | C40: Rohith | D40: it.admin@petiolehub.com | E40: Food | F40: #154948296 | G40: They are currently using Zoho Mail, Cliq, and Zoho People. For document management, they are using Box and are now exploring a move to Zoho WorkDrive. | H40: Automation using AI | I40: Box | K40: Sales follow up 2 | L40: PSE554233 | M40: WorkDrive - Book a Demo (direct) | N40: New Prospect | O40: Extended | P40: Deal Won | Q40: 20 | R40: $ 2,160 (USD) | S40: Business | U40: https://workdrive.zoho.in/file/l8q3i6e9182268b4642878f50f036b4a10694 | V40: trial extended till 25th march 2026 | W40: Option available via API
A41: 46064 | B41: IN | C41: Sakthi | D41: jigna.vr@gmail.com | E41: Radiology | F41: #154800911 | G41: They will be receiving DICOM files which are scanned files sent via email from 25 different radiology centres. | H41: Preview support for DICOM files (XRAY, MRI, scan-file) | I41: V transfer | K41: Do not follow | M41: WorkDrive - Book a Demo (direct) | N41: New Prospect | O41: No | P41: Deal Lost | Q41: 8 | S41: WP (Professional) | U41: https://workdrive.zoho.in/file/bs2ila6b142c1f95145d0b999f87d14b9df00 | V41: Looking for Workplace Professional 8 user licenses
A42: 46064 | B42: IN | C42: Sakthi | D42: matt.birtwhistle@jbagroup.co.uk | E42: Industrial Automation | F42: #121050445 | G42: They will be signing up for a new domain and email address in EU DC for the same set of users in US DC. | H42: The prospect wanted to sync his SSO from US DC to EU DC as he wanted to create an org in EU DC. | K42: Do not follow | M42: WorkDrive - Book a Demo (direct) | N42: Already Engaged Px | O42: Existing user | P42: Existing customer | Q42: 60 | S42: Business | T42: Accounts team has mentioned that syncing SSO from US DC to EU DC for the same set of users with different domain and email address would not be supported. | U42: MS Teams
A43: 46064 | B43: IN | C43: Sakthi | D43: mohamed.aareef@kiongroup.com | E43: Supply Chain | F43: #154592783 | G43: They will be starting the POC and have requested for early access for Zia Hubs once they start POC. | K43: Sales follow up 3 | M43: From Sales End | N43: Already Engaged Px | O43: No | P43: Deal Lost | Q43: 100 | S43: Business | U43: MS Teams | V43: Followup email sent | W43: Document Expiry: https://sprints.zoho.in/workspace/zdocs#P15/itemdetails/I7323
A44: 46064 | B44: IN | C44: Sakthi | D44: shinoy.thachapully@ae.mcd.com | E44: Food | F44: #154488423 | G44: 1. The sent us an agenda, for the topics to discuss on the demo as follows: Team Folders, Access control, Audit Trail, Version control, Smart search, Sync/mobile apps, file collection, Data templates, DLP, Workflows, client users. 2. The total storage they are looking for is 30TB of storage for 550 users initially. | H44: 1. They wanted to integrate WorkDrive with ZScaler for DLP. @Aravindhan N 2. They wanted to have UAE based PII predefined sensitive information types. We have also asked them for a list. In the meantime we have to work on this from our end to provide default UAE related sensitive information PII types. @Rishi @Saravanapandi S 3. They wanted to provide us with SSL certificate for custom domain, instead of us purchasing and maintaining the SSL certificate for them. @Saravanapandi S >> We have mentioned that due to the expiry of SSL, every time reaching out to MC Donald’s for SSL will be tedious and asked to confirm whether this is a mandatory requirement. 4. They are also evaluating Egnyte and wanted a comparison document of WD VS Egnyte. @Durai 5. They also asked for threat and anomaly detections like bulk download notifications, Bulk version deletion notification, bulk deletion notification and DLP download attempts, Malware detections and alerts. @Aravindhan N 6. They have requested for integration with Teams, Office 365, Sharepoint. >> Do we have any integration with Teams in our roadmap. For O365 we can suggest MS office extension. For Sharepoint, we have requested for more information. Aravindhan | K44: Sales follow up 3 | M44: From Sales End | N44: Already Engaged Px | O44: No | P44: Deal Lost | Q44: 550 | S44: Business | U44: MS Teams | W44: 1. UAE Sensitive information type:https://sprints.zoho.in/workspace/zdocs#P15/itemdetails/I7229 2. ZScalar integration: https://sprints.zoho.in/workspace/zdocs#P15/itemdetails/I7231
A45: 46065 | B45: US | C45: Jennifer | D45: keir@dbmp.com | E45: Individual | F45: #154962417 | G45: Looking to interact with his clients - so demoed on collect files and share feature. however collect files were not suitable to him, as he is just looking to share and maybe get few files - so explained on share feature where they can share folder with upload permission which creates a common ground between client and him | H45: None | I45: Local Drive | K45: Sales follow up 3 | L45: No PSE | M45: WorkDrive - Book a Demo (direct) | N45: New Prospect | O45: Yes | P45: Deal Won | Q45: 1 | R45: 30 | S45: Business | U45: No recording - connected via Zoho voice and shared screen through meeting
A46: 46066 | B46: IN | C46: Rohith | D46: iakashsharma68@gmail.com | E46: Marketing agency | F46: #155022165 | G46: They are looking to move their entire organization’s ecosystem from multiple tools into a single Zoho ecosystem. | I46: GoogleDrive | K46: Do not follow | L46: No PSE | M46: WorkDrive - Book a Demo (direct) | N46: New Prospect | O46: No | P46: Deal Lost | S46: Zoho One | T46: They are evaluating Zoho One and were intending to connect with the Zoho One team, but the session was booked with us by mistake. | U46: https://workdrive.zoho.in/file/9rfbo7b58a28a890f43559c2c62417c28e369
A47: 46066 | B47: EMEA | C47: Rohith | D47: rrangdal@agility.com | E47: logistics & warehousing | F47: #155023704 | G47: They are evaluating Zoho WorkDrive as a replacement for SharePoint Online for day-to-day document collaboration, while continuing to use SharePoint for intranet content and organizational announcements. | H47: They require data retention settings of up to five years from the admin console, in line with company policies Migration tool support for SharePoint. | I47: Sharepoint | J47: Less than 20TB | K47: Sales follow up 3 | L47: PSE555894 | M47: From Sales End | N47: New Prospect | O47: Suspended | P47: Deal Lost | Q47: 200 to 500 | S47: Business | U47: https://workdrive.zoho.in/file/b2sef14488879233543d2b37fe060981ada85 | V47: Couldn't reach the cx. Sent a follow up email. | W47: Sharepoint migration https://sprints.zoho.in/workspace/zdocs#P15/itemdetails/I7454
A48: 46069 | B48: IN | C48: Janani | D48: ravishmaniyar@gmail.com | E48: CA | F48: #150560748 | G48: Prospect is looking for OneDrive alternative due to challenges in brining in data to cloud from their clients. | H48: Collect file feature enhancement to be able to change destination folder after creating the link | I48: OneDrive | K48: Sales follow up 3 | M48: From Sales End | N48: New Prospect | O48: Yes | P48: Deal Lost | Q48: 3 | S48: Team | U48: https://workdrive.zoho.in/file/b3vi3d3a6e4167ded4eaea22c9b26ecea75e4
A49: 46069 | B49: IN | C49: Janani | D49: anil.kunda@charismight.com | E49: IT | F49: #155018697 | G49: Zoho Document Management System (DMS) to better understand its features, functionalities, and use cases. The session will help us evaluate how Zoho DMS can support our document organization, access control, version management, and overall operational efficiency | K49: Sales follow up 3 | M49: WorkDrive - Book a Demo (direct) | N49: New Prospect | O49: Yes | P49: Deal Lost | Q49: 20 | S49: Team | U49: https://workdrive.zoho.in/file/b3vi3894bee8af7194e62b3ecb831ee679525
A50: 46069 | B50: IN | C50: Rohith | D50: abhilash@mecpl.in | E50: Construction | F50: #155085591 | G50: The customer is exploring Zoho Workplace and requested a detailed session specifically on Zoho WorkDrive. They were looking for clarity around data security, access control, offline usage, migration from on-premise or local servers to the cloud, and the ability to continue working with existing Excel and Microsoft Office files. | H50: None | I50: Network Drive | K50: Sales follow up 1 | L50: PSE556004 | M50: From Sales End | N50: New Prospect | O50: Yes | P50: Deal Won | Q50: 380 | R50: ₹ 493,240 [418,000 + 75,240(Tax)] | S50: WP (Standard) | T50: Connect post | U50: https://workdrive.zoho.in/file/8boq9281db074b5bb4274a60c08ba4ee05f26
A51: 46069 | B51: US | C51: Rohith | D51: civani@sisgea.com | E51: Personal | F51: #155051299 | G51: Assisted on managing storage | H51: None | K51: Do not follow | M51: WorkDrive - Book a Demo (direct) | N51: Existing Paid Cx | O51: Existing user | P51: Existing customer | Q51: 2 | S51: WP (Standard) | U51: No recording
A52: 46069 | B52: US | C52: Rohith | D52: george@gcgtax.ca | E52: Tax | F52: #155083810 | G52: They are looking for a centralized document storage solution that enables real-time collaboration between two remote users working from different locations. The expectation is functionality similar to Google Docs, without using Google, mainly for collaborating on Excel and Word files, as well as data files generated by TaxCycle (Canadian tax software). Maintaining version consistency is critical, with no duplicate or conflicting files during collaboration. | H52: None | I52: Local Drive | K52: Sales follow up 2 | L52: PSE555931 | M52: WorkDrive - Book a Demo (direct) | N52: New Prospect | O52: Yes | P52: Deal Won | Q52: 2 | S52: Starter | U52: https://workdrive.zoho.in/file/b2sefe10c440522e74bd1be09069d7225ae7f
A53: 46069 | B53: IN | C53: Sakthi | D53: ITC | E53: Manufacturing | G53: They are looking for MS O365 replacement. | H53: 1. Though we have an option to enable or disable Zoho Editors to open and edit non-native files. However, they expect an option where a docx file need to be opened with Zoho Office editor without a copy and save in Office Suite format itself instead of Zoho Proprietary format. The severity of this feature can only be known in further engagements. >> As of now, though offline desktop apps has this an option to locally save the files in MS Office formats (as available in Zoho Writer desktop app), can we incorporate the same in the cloud as well, for saving docx files opened in Writer as docx, also for Sheet and Show in corresponding MS Office formats. >> We have also suggested downloading the file in corresponding MS Office formats in such cases, however, they want the actual file to retain the original format. | I53: MS Office 365 | K53: Do not follow | M53: Direct Mail to Presales | N53: New Prospect | O53: No | P53: In Progress | Q53: 8000 | S53: WP (Professional) | U53: Zoho Office visit | W53: Open and save in MS office format via Zoho Editors online https://sprints.zoho.in/workspace/zdocs#P15/itemdetails/I7480
A54: 46069 | B54: IN | C54: Sakthi | D54: ea@pasarigroup.com | E54: Real Estate | F54: #155075586 | G54: There are departments like Accounts, Purchase, Legal, Sales and Marketting. They are looking to use WD where some of them need to upload and share, some of them should only view and comment. | H54: None | K54: Sales follow up 3 | M54: WorkDrive - Book a Demo (direct) | N54: New Prospect | O54: No | P54: Deal Lost | Q54: 15 | S54: Business | U54: https://workdrive.zoho.in/file/bs2ila6b142c1f95145d0b999f87d14b9df00 | V54: Call went unanswered - dropped mail
A55: 46069 | B55: IN | C55: Sakthi | D55: ashok_gaikar@icicipruamc.com | E55: Banking | F55: #155133975 | G55: 1. Zscalar is being used and Edge is their secured browser. 2. Mail has integrated with ForcePoint for DLP but WorkDrive is yet to integrate with Forcepoint. | H55: 2. Mail has integrated with ForcePoint for DLP but WorkDrive is yet to integrate with Forcepoint. | I55: MS Office 365 | K55: Do not follow | M55: Direct Mail to Presales | N55: New Prospect | O55: No | P55: In Progress | Q55: 1000+ | S55: WP (Professional) | U55: Zoho Office visit | W55: Forcepoint integration with WorkDrive: https://sprints.zoho.in/workspace/zdocs#P15/itemdetails/I7467/details
A56: 46069 | B56: US | C56: Jennifer | D56: hospitalityfunding@yahoo.com | E56: Financial | F56: #155055933 | G56: Dropbox users looking to create a private link to have his clients upload files to prospect without have his clients create zoho accounts. | I56: Dropbox | K56: Sales follow up 3 | L56: No PSE | M56: WorkDrive - Book a Demo (direct) | N56: New Prospect | O56: Free User | P56: Deal Lost | Q56: 2 | U56: No recording - connected via Zoho voice and shared screen through meeting | V56: 3 FUP sent - asked to call on Monday
A57: 46070 | B57: IN | C57: Rohith | D57: ashok_gaikar@icicipruamc.com | E57: Banking | F57: #155133975 | G57: Test migration from OneDrive | H57: None | I57: OneDrive | K57: Sales follow up 2 | M57: From Sales End | N57: Already Engaged Px | O57: Yes | P57: In Progress | U57: No recording
A58: 46070 | B58: EMEA | C58: Rohith | D58: it.admin@petiolehub.com | E58: Foods | F58: #154948296 | G58: Followup session | K58: Sales follow up 2 | L58: PSE556152 | M58: From Sales End | N58: Already Engaged Px | O58: Yes | P58: Deal Won | Q58: 20 | S58: Business | T58: trial extended till 25th march 2026 | U58: https://workdrive.zoho.in/file/8boq990261e54827a44a3b222612466ac8cbe | V58: trial extended till 25th march 2026
A59: 46071 | B59: US | C59: Jennifer | D59: vivek@aihifusion.com | E59: Individual | F59: #154960613 | G59: She has been using Google Drive and MS Office but had challenges with collecting documents from her clients, where she does not want to rely on mail to get files from clients. | I59: Google Drive and Microsoft | K59: Sales follow up 3 | L59: No PSE | M59: Internally Looped | N59: New Prospect | O59: Suspended | P59: Deal Lost | Q59: 1 | S59: Team | U59: https://workdrive.zoho.in/file/bjqb6a5a65dc946bb4afd85c0deedce0908d6 | V59: spoke with px they are completely occupied and will get back by April 1st week
A60: 46071 | B60: US | C60: Jennifer | D60: pranil@spadesecurityservices.com | E60: Security | F60: #155165637 | G60: Prospect is new to Zoho and has signed up for Zoho One trial. Looking to know more about workdrive - especially his challenges on security over files upon member deletion and while being active. Plus the option to migrate the data from google drive to WD. | I60: Google Drive | K60: Z1 follow up | L60: No PSE | M60: WorkDrive - Book a Demo (direct) | N60: New Prospect | O60: Yes | P60: Deal Won | Q60: 1 | R60: 146 | S60: Zoho One | U60: https://workdrive.zoho.in/file/bjqb67e324ddb32c6450c9fc3ef2de28ebd9c
A61: 46071 | B61: IN | C61: Janani | D61: vivek@aihifusion.com | E61: IT services | F61: #155026814 | G61: Prospect is already using Zoho Mail and wanted Zoho WorkDrive to store, manage and secure platform their data | I61: Google Drive | J61: 1TB | K61: Sales follow up 3 | M61: From Sales End | N61: Already Engaged Px | O61: Yes | P61: Deal Lost | Q61: 3 | S61: WP (Standard) | U61: https://workdrive.zoho.in/file/8boq978974de924784820a365af44f89ce0c5 | V61: spoke with px they are completely occupied and will get back by April 1st week
A62: 46071 | B62: IN | C62: Rohith | D62: vigneshdev.nagarajan@ilink-systems.com | E62: Sales force | F62: #155153837 | G62: The customer is evaluating cloud-based document storage solutions and is currently comparing multiple services in the market. Their primary focus was to understand pricing, storage options, and overall suitability before moving away from local storage. | H62: None | I62: HardDrive | J62: Less than 5TB | K62: Sales follow up 3 | L62: PSE556061 | M62: From Sales End | N62: New Prospect | O62: No | P62: Deal Lost | Q62: 3 | S62: Business | U62: https://workdrive.zoho.in/file/8boq9012e828f5f3e4e55893074cb7b045df8 | V62: got me the reverted stating that it takes some time to get an update internally and get back to us ,
A63: 46071 | B63: IN | C63: Rohith | D63: gomathishivabalan@gmail.com | E63: Startup | F63: #155222210 | G63: They run a startup and are currently storing documents on local machines. They are looking for a straightforward cloud-based solution that supports collaboration, especially on Excel files. | H63: None | I63: Local Drive | K63: Sales follow up 3 | L63: No PSE | M63: WD support - Chat/Call/Mail | N63: New Prospect | O63: Yes | P63: Deal Lost | Q63: 5 to 10 | S63: Starter | U63: https://workdrive.zoho.in/file/fu5rw9d8c3ae3a74e4d6f98dec71e3b496818 | V63: Cx is not looking for standalone application as Zoho WorkDrive.
A64: 46071 | B64: EMEA | C64: Jennifer | D64: sethu@elvisec.com/ rajesh.s@elvisec.com | E64: IT | F64: #155064151 | G64: They are looking for a backup solution to sync automatically between their local storage to WorkDrive with the option to configure access levels at department levels. They had been having challenges with their servers, where because of system crashes the data loss happens. | I64: Local Drive | K64: Sales follow up 2 | L64: No PSE | M64: WD support - Chat/Call/Mail | N64: New Prospect | O64: Yes | P64: Deal Won | Q64: 10 | R64: 105.25 | S64: Starter | U64: https://workdrive.zoho.in/file/fu5rw34414ce31f274b40b079fb75cd5fcefc
A65: 46071 | B65: IN | C65: Jennifer | D65: caakashag9@gmail.com | E65: Marketing | F65: #154205905 | G65: Followup session | I65: Local Drive | K65: Do not follow | L65: PSE552267 | M65: WD support - Chat/Call/Mail | N65: Already Engaged Px | O65: Suspended | P65: Deal Lost | Q65: 3 | U65: No recording - Follow up session | V65: Call went unanswered
A66: 46071 | B66: IN | C66: Sakthi | D66: pradeep.thakur@canarahsbclife.in | E66: Insurance | F66: #155280636 | G66: Their are looking to replace MS Office 365 replacement only for their Sales team who are frontline workers. | H66: 1. Using Intune they can save email attachments directly to OneDrive for their entire org. They are looking for this MDM based settings or product level settings, where they can let the Email attachments save to WorkDrive for their entire org, instead of creating the filter manually at the user-level. >> Mentioned that we will check on this internally and circle back. 2. Currently there is a restriction in OneDrive while copying permalink “Anyone on the team” can be restricted and only email address based internal sharing with Default “View” only access can be allowed. >> Informed that as of now, only external sharing can be restricted and “Anyone on the team” links can be created and restriction of “Anyone on the team” based sharing at the org-level is currently not supported. >> As of now, though we support internal sharing with email address, he wants to restrict “Anyone on the team” based sharing as he does n to want files to be loosely shared as links, even internally. | I66: MS Office 365 | K66: Do not follow | M66: Direct Mail to Presales | N66: New Prospect | O66: Yes | P66: Deal Lost | Q66: 4500 | S66: WP flexi | U66: MS Teams | W66: Save email attachments to WorkDrive at org level https://sprints.zoho.in/workspace/zdocs#P15/itemdetails/I7478 Restrict anyone on the team share: https://sprints.zoho.in/workspace/zdocs#P15/itemdetails/I7479
A67: 46071 | B67: IN | C67: Sakthi | D67: rameshg@amrutanjan.com | E67: Healthcare | F67: #155281858 | G67: Gave a complete training to Amrutanjan team. 30+ Users joined the session. | K67: Do not follow | M67: Direct Mail to Presales | N67: Existing Paid Cx | O67: Existing user | P67: Existing customer | Q67: 619 | S67: WP flexi | U67: Training session.
A68: 46072 | B68: IN | C68: Janani | D68: finance@enviro-t.in | E68: Finance | F68: #155257553 | G68: We need Online Server for 15 people to store our company data and which can be accessed through cloud. | I68: System Drive | J68: 1-3TB | K68: Sales follow up 2 | M68: From Sales End | N68: Already Engaged Px | O68: Yes | P68: Deal Won | Q68: 10 | S68: Business | U68: https://workdrive.zoho.in/file/2yn4mb93a47d903b0461a82f3ea61548feeff
A69: 46072 | B69: IN | C69: Janani | D69: s.johnsonsamuel@gmail.com | E69: Consulting | F69: #155188147 | G69: Prospect is looking for difference between Workplace and standalone workdrive | I69: Google Drive | K69: Sales follow up 3 | M69: From Sales End | N69: New Prospect | O69: No | P69: Deal Lost | Q69: 3 | S69: Starter | U69: https://workdrive.zoho.in/file/2yn4mc8e68c21dbb041c2b7aba7b2cb54728f | V69: No response
A70: 46072 | B70: IN | C70: Sakthi | D70: agnes.buyser@priorityconsultants.com | E70: Consultancy | F70: #155029864 | G70: The user is looking to upload client related documents, like contracts with deadlines, policies, client reports. They will be asking Zia certain questions like based on the expiry, summary of a report and any key parameters of a report. | H70: 1. As of now, the user is looking to generate some outreach program document and client agreement document. As of now, the generated content cannot be directly saved to Zia hub, it can only be saved within My folder or Team folder. 2. The user is looking for a replacement of Chat GPT, within WorkDrive. So, if the user uploads a “Client agreement” template along with user details and expiry, and asks AI to generate a document tailored to this user and save it in Zia Hubs directly. This will be very helpful to ask questions later in Hub. 3. Also, the user is looking the kinds of questions that can be used for Zia hubs. If there is a list of questions or best practices for Zia hubs, it would be nice.Sivaprakasam S Aravindhan | K70: Do not follow | M70: WorkDrive - Book a Demo (direct) | N70: Existing Paid Cx | O70: Existing user | P70: Existing customer | Q70: 57 | S70: Zoho One | U70: Training session.
A71: 46072 | B71: IN | C71: Rohith | D71: accounts@fineinstruments.in | E71: Mechanical | F71: #155280740 | G71: Onboarding session | K71: Do not follow | L71: No PSE | M71: WD support - Chat/Call/Mail | N71: New Prospect | O71: Yes | P71: Deal Won | Q71: 5 | S71: Starter | U71: NO recording
A72: 46072 | B72: EMEA | C72: Rohith | D72: renjith.kalathil@sofonmaritime.com | E72: Maritime | F72: #155287517 | G72: They are looking to replace Microsoft OneDrive with a centralized cloud storage solution that supports folder-based collaboration, controlled access, the ability to download files, and local sync capabilities. | H72: None | I72: OneDrive | J72: less than 3TB | K72: Sales follow up 3 | L72: PSE557630 | M72: WorkDrive - Book a Demo (direct) | N72: New Prospect | O72: No | P72: Deal Lost | Q72: 5 | S72: Team | U72: https://workdrive.zoho.in/file/1x1sbd2d1b696ecb144cdb2302b36a6360990 | V72: March 6 - Cx asked me to follow up with him after a couple of weeks
A73: 46073 | B73: IN | C73: Janani | D73: darshana.t@olankatravels.com | E73: Travel | F73: #155293791 | G73: Our organization is looking for a secure cloud storage solution to manage highly sensitive internal documents and partner collaborations. We would like to request a demo specifically focused on the following requirements: | K73: Sales follow up 2 | M73: WorkDrive - Book a Demo (direct) | N73: New Prospect | O73: Yes | P73: Deal Won | Q73: 12 | S73: Starter | U73: https://workdrive.zoho.in/file/1x1sbd21f0648d2694dc08a93a19a9baa4a26
A74: 46073 | B74: IN | C74: Rohith | D74: it@raudratech.com | E74: Tech | F74: #155296677 | G74: They are currently managing documents using an inbuilt tool but are facing challenges due to the lack of a centralized repository. Finding the right documents has become difficult, and there is no clear structure across departments or projects. They are looking for a centralized, well-structured document management system that enables easy document discovery while providing controlled access based on departments or project needs. | H74: None | I74: Inbuilt | K74: Sales follow up 1 | L74: PSE557639 | M74: WorkDrive - Book a Demo (direct) | N74: New Prospect | O74: Yes | P74: Deal Won | Q74: 5 | S74: Business | U74: https://workdrive.zoho.in/file/nm45ybfa0a6bfe14443a0a4cca4a3f149adab
A75: 46076 | B75: EMEA | C75: Rohith | D75: it.admin@petiolehub.com | E75: Food | F75: #154948296 | G75: Followup session | H75: User wants document collaboration and approval workflows to be managed in Zoho WorkDrive and the finalized documents should be pushed to Box AI | I75: Local Drive | K75: Sales follow up 2 | L75: PSE557549 | M75: From Sales End | N75: Already Engaged Px | O75: Yes | P75: Deal Won | Q75: 20 | S75: Business | U75: No recording - issue with Zoho Meeting | V75: trial extended till 25th march 2026 | W75: Option available via API
A76: 46076 | B76: IN | C76: Rohith | D76: deepak.singh@fazethree.com | E76: Textile | F76: #150718624 | G76: The user is ready to proceed with Zoho WorkDrive and wanted to understand how to migrate data from their local drive to WorkDrive. They also requested a quick walkthrough of the product and its core features. | H76: None | I76: Local Drive | K76: Sales follow up 2 | L76: PSE557554 | M76: From Sales End | N76: Already Engaged Px | O76: Yes | P76: Deal Won | Q76: 3 | S76: Business | U76: No recording - issue with Zoho Meeting
A77: 46076 | B77: IN | C77: Rohith | D77: office@shanthibhavan.in | E77: NGO | F77: #155293424 | G77: The customer is currently using Dropbox along with a local drive for document storage and wants to consolidate everything into a single cloud-based storage solution. | H77: None | I77: Local Drive and Dropbox | J77: Less than 1TB | K77: Sales follow up 2 | L77: PSE557569 | M77: From Sales End | N77: New Prospect | O77: Yes | P77: Deal Won | Q77: 3 | R77: 55.44 | S77: Starter | U77: No recording - issue with Zoho Meeting | V77: March 18 Follow up email shared to cx.
A78: 46076 | B78: IN | C78: Monisha | D78: rahuljha@4basecare.com | G78: Hindi Demo - They are using Google WorkSpace and now want to switch to WorkDrive. They were interested in Collaboration features, custom folder , external share settings, Team Folders and granular access control. | K78: Sales follow up 3 | M78: WorkDrive - Book a Demo (direct) | N78: New Prospect | O78: Yes | P78: Deal Lost | V78: no answer, follow up email sent
A79: 46077 | B79: IN | C79: Janani | D79: atul2goyal@gmail.com | E79: Consulting | F79: #155437253 | G79: prospect is consulting firm looking for an detailed overview about Zoho WorkDrive in Workplace | H79: None | I79: GoogleDrive | J79: Below 500GB | K79: Sales follow up 3 | M79: WorkDrive - Book a Demo (direct) | N79: New Prospect | O79: No | P79: Deal Lost | Q79: 10 ( May increaase to 70) | S79: WP (Standard) | U79: https://workdrive.zoho.in/file/tz2iw5fdc0a5cc6b148a08a1dd7dbd667ddc9 | V79: Call went unanswered - dropped mail
A80: 46077 | B80: IN | C80: Janani | D80: puru.jain@urbanmoney.co.in | E80: Finance | F80: #154978856 | G80: Need to handle large amount of data on cloud to get an access easily from anywhere. | H80: None | I80: System HardDrive | J80: 2TB | K80: Sales follow up 3 | M80: From Sales End | N80: New Prospect | O80: Yes | P80: Deal Lost | Q80: 3 | S80: Business | U80: https://workdrive.zoho.in/file/xww67dcd144a57f3249ff919523ad423d2fb5 | V80: Purchased under a different account
A81: 46077 | B81: IN | C81: Rohith | D81: vinita.yadav@hawkinscookers.com | E81: Consumer goods | F81: #155182259 | G81: They are currently maintaining all documents in physical form and are looking to digitize them. However, due to internal company policy, they require the data to be hosted on their own in-house servers rather than on a public cloud platform. | H81: On-prem | I81: Physical documents | K81: Do not follow | L81: PSE558023 | M81: From Sales End | N81: New Prospect | O81: No | P81: No Scope for WD
A82: 46077 | B82: IN | C82: Rohith | D82: vedant.kasture@smartjoules.in | E82: Electrical | F82: #155286038 | G82: Centralized repository & structure, Version control & controlled documents,Approval workflows,Access control & external sharing,Search & retrieval,Compliance readiness,Integrations & automation | H82: None | K82: Sales follow up 3 | L82: PSE558412 | M82: From Sales End | N82: New Prospect | O82: Suspended | P82: Deal Lost | S82: Business | T82: Org size - 150, deal size is not confirmed | U82: Session not recorded | V82: Cx dropped mail stating they are not planning to opt in for now
A83: 46077 | B83: IN | C83: Rohith | D83: daminijain123@gmail.com | E83: Data management | F83: #155499791 | G83: They are looking for a cloud-based solution to store audit reports, checklists, inspection documents, and related files with controlled access for employees. The documents should be accessible from anywhere, as they are currently stored on local hard drives. | H83: None | I83: Local Drivel | J83: 500GB | K83: Sales follow up 3 | L83: PSE558434 | M83: WorkDrive - Book a Demo (direct) | N83: New Prospect | O83: Yes | P83: Deal Lost | Q83: 10 | S83: Starter | U83: https://workdrive.zoho.in/file/oaggobff5c726c66c46658e466cac5c3b7e23
A84: 46078 | B84: US | C84: Jennifer | D84: jmoore@escrow321.com | E84: Real Estate | F84: #155476923 | G84: They have been using GreenFolder (workflow and document management system for title, escrow, and real estate operations) as their file manipulation s/w and database, where they had challenges on simple tasks due to their recent update. Plus they are planning to move from onsite to a cloud based solution. | H84: 7-year data retention feasibility | I84: GreenFolders | K84: Sales follow up 3 | L84: No PSE | M84: WorkDrive - Book a Demo (direct) | N84: New Prospect | O84: No | P84: Deal Lost | Q84: Not confirmed | U84: https://workdrive.zoho.in/file/vt5o1a363a8fe54b34168948668789e8adff8 | V84: No response | W84: https://sprints.zoho.in/workspace/zdocs#P15/itemdetails/I6334/details
A85: 46078 | B85: IN | C85: Janani | D85: abhishek@bhagatassociates.in | E85: Law | F85: #155302796 | G85: Automation for folder creation and writer mail merge And auto document creation . | K85: Sales follow up 3 | M85: From Sales End | N85: Already Engaged Px | O85: Yes | P85: Deal Lost | V85: Cx dropped mail asking for call by sunday - reshared link yesterday will fup accordingly
A86: 46078 | B86: IN | C86: Janani | D86: p.byali@hima.com | E86: finance | F86: #155489858 | G86: Primary requirement include of - Organising data in cloud - Managing file activity and versions within application | K86: Sales follow up 3 | M86: From Sales End | N86: New Prospect | O86: No | P86: Deal Lost | V86: No response from the cx
A87: 46078 | B87: IN | C87: Janani | D87: development@greenrootsrenewable.in | E87: Manufacturing | F87: #155446405 | G87: Prospect is looking for a data managing tool | K87: Do not follow | M87: From Sales End | N87: New Prospect | O87: No | P87: No Scope for WD
A88: 46078 | B88: EMEA | C88: Rohith | D88: creditcontroller@dhofarglobal.com | E88: Household goos | F88: #155495307 | G88: They operate across four regions and are currently using Zoho CRM and Zoho Books. They are evaluating a document management system that can handle document expiry and renewal management, specifically for tracking trade licenses and contracts. Key expectations include automatic identification of expiry dates from documents, automated email notifications (for example, 30 days before expiry) to internal teams or customers, strong search and classification capabilities, and AI-based document intelligence. | H88: Expiry dates can be assigned to documents and automated follow-up emails are triggered at configurable intervals (such as 30, 60, or 90 days before expiry), on the expiry date itself, and with escalation if the document is not renewed. | K88: Do not follow | L88: PSE558481 | M88: WorkDrive - Book a Demo (direct) | N88: New Prospect | O88: Yes | P88: No Scope for WD | U88: https://workdrive.zoho.in/file/oaggofc11b79bca6440538048d24b4616510c | W88: https://sprints.zoho.in/workspace/zdocs#P15/itemdetails/I7455/details
A89: 46078 | B89: IN | C89: Rohith | D89: vinathreshview@gmail.com | E89: Design | F89: #155555191 | G89: They are a small design team working on posters and templates. Currently, all files are stored on local drives, which makes collaboration difficult and often leads to duplicate versions. They also share and collect files from clients through WhatsApp, resulting in unnecessary phone storage usage and a cluttered workflow. They are looking for a simpler, centralized way to collaborate, manage versions, and exchange files with clients. | H89: None | I89: Local drive | K89: Sales follow up 3 | L89: PSE558571 | M89: WD support - Chat/Call/Mail | N89: New Prospect | O89: Suspended | P89: Deal Lost | Q89: 3 | S89: Team | U89: https://workdrive.zoho.in/file/zav3se462839206ef46b5b4e7106b913c7752 | V89: No response from cx
A90: 46078 | B90: IN | C90: Sakthi | D90: jaiprakash.yadav@kotak.com | E90: Banking | F90: #150750654 | G90: 90% of their org is looking for offline desktop apps and 10% of their org (both online + offline). | H90: They mentioned that they use VLOOKUP a lot in Excel. >> In Online and Offline we have a limitation with VLOOKUP, where pulling data from different spreadsheets is not yet supported. >> In the offline Sheet app, do we have it in the roadmap to support VLOOKUP across different workbooks, as in Excel? | I90: MS Office 365 | K90: Follow up 3 | M90: From Sales End | N90: Already Engaged Px | O90: Yes | P90: Deal Lost | S90: Zoho Office Suite Desktop apps | U90: MS Teams | V90: No response, sent follow up mail to cx. | W90: Office editors
A91: 46078 | B91: IN | C91: Jennifer | D91: palakkhurana0000@gmail.com | E91: Manufacturing | F91: #155559576 | G91: They are planning to go for Zoho One, as they have requirements towards multiple apps. Concerning WD, they are looking for a centralised space to manage their files along with sharing them with their vendors. | H91: None | K91: Z1 follow up | L91: PSE558632 | M91: WorkDrive - Book a Demo (direct) | N91: New Prospect | O91: Yes | P91: Deal Won | Q91: 5 | R91: 50.16 | S91: Zoho One | U91: https://workdrive.zoho.in/file/zav3sce8f970aadf747f3a9313ae1fd40799f
A92: 46079 | B92: IN | C92: Janani | D92: mohit@cstarunakalra.com | E92: Finance | F92: #154799418 | G92: Prospect is looking to store their data in cloud and manage it online | H92: Need Device management in Starter Edition | J92: 200GB | K92: Sales follow up 3 | M92: From Sales End | N92: New Prospect | O92: Suspended | P92: Deal Lost | Q92: 7 | S92: Starter | U92: https://workdrive.zoho.in/file/ocdz17f16d42b8faf4fb0be435adfe70ee4b8 | V92: March 20 No response to the call yesterday | W92: Custom plan
A93: 46079 | B93: IN | C93: Janani | D93: sahilnparikh@gmail.com | E93: Consulting | F93: #155540839 | G93: Prospect is looking to switch from Google to Zoho WorkDrive due to pricing constrain | I93: GoogleDrive | J93: 1TB | K93: Sales follow up 3 | M93: WorkDrive - Book a Demo (direct) | N93: New Prospect | O93: No | P93: Deal Lost | Q93: 10 | S93: Starter | U93: https://workdrive.zoho.in/file/ocdz177cb6c5d85994386935d079d16554ecf
A94: 46079 | B94: IN | C94: Rohith | D94: sagar@healthylifeinnovation.com | E94: Healthcare | F94: #155573211 | G94: Query on WorkDrive | K94: Do not follow | M94: WorkDrive - Book a Demo (direct) | N94: Existing Paid Cx | O94: Existing user | P94: Existing customer | S94: WP (Professional) | U94: No recording
A95: 46079 | B95: IN | C95: Rohith | D95: bnpatel@mehsanaunion.coop | E95: Food production | F95: #155496215 | G95: They are looking for a document management system that enables easy sharing of documents with clients, supports review and approval workflows, and includes an option for digital signatures. | H95: None | K95: Sales follow up 3 | L95: PSE560465 | M95: WorkDrive - Book a Demo (direct) | N95: New Prospect | O95: Free User | P95: Deal Lost | Q95: 15 | S95: Starter | U95: https://workdrive.zoho.in/file/78y5lfc5f30f04dae4266af7a4488e3279496 | V95: MArch 17 Cx said he will schedule the meeting and share the confirmation.
A96: 46079 | B96: IN | C96: Rohith | D96: enquiry@vaultenergy.no | E96: Renewable energy | F96: #155613452 | G96: They are looking for a document management system that enables seamless internal team collaboration as well as secure collaboration with suppliers and clients. The solution should support configurable workflows with automated reminders, built-in document revisioning and version control, and a structured way to track supplier data updates and manage documents efficiently. | H96: None | K96: Sales follow up 3 | L96: PSE560479 | M96: WD support - Chat/Call/Mail | N96: New Prospect | O96: Suspended | P96: Deal Lost | S96: Business | U96: Cx doesn’t want it to be recorded
A97: 46080 | B97: US | C97: Jennifer | D97: parveen@pvrealtyadvisors.ca | E97: Real Estate | F97: #155642635 | G97: Most of their requirements where on the pricing. They basically want to upload files and review/download it. They are a team of 10, however they prefer to purchase for 3 licenses and rest should be able to only upload/view files for whom they dont prefer to not purchase license. | H97: none | I97: DropBox | J97: <1 TB | K97: Follow up 1 | L97: No PSE | M97: WorkDrive - Book a Demo (direct) | N97: New Prospect | O97: Yes | P97: Deal Won | Q97: 3 | R97: 108 | S97: Starter | T97: Collect files enabled in starter edition using custom plan | U97: https://workdrive.zoho.in/file/ocdz1ef819e3909ec426399f32e0f06f8e590
A98: 46080 | B98: IN | C98: Janani | D98: george@spectra.com.my | E98: Legal | F98: #154905556 | G98: wants to digitalise their storage, which is currently on hard drives / NAS, into a proper document management solution. | H98: None | I98: NAS Drive | J98: Hardcopies | K98: Sales follow up 3 | M98: From Sales End | N98: Already Engaged Px | O98: Yes | P98: Deal Lost | Q98: 3 | S98: Starter | U98: https://workdrive.zoho.in/file/us2t75b80c2eacf5044c08b507567d19e28ac
A99: 46080 | B99: IN | C99: Sakthi | D99: roshan.komaravolu@altinvest.ai | E99: Investment Management | F99: #155626072 | G99: . Centralized document management system to replace Google Drive, Dropbox, and scattered local storage. | H99: They are looking Activity tab alone in Starter edition. So, we may need to enable custom plan for this user, if he confirms he goes with Starter edition. | J99: Google Workspace, Dropbox | K99: Sales follow up 3 | M99: WorkDrive - Book a Demo (direct) | N99: New Prospect | O99: Suspended | P99: Deal Lost | Q99: 150 | S99: Starter | V99: No answer, follow up email sent | W99: Custom plan

Sheet March
A1: Date | B1: Region | C1: Handled by | D1: Email address | E1: Industry | F1: Ticket ID | G1: Purpose | H1: New requirements | I1: Current Platform | J1: Existing data size | K1: Follow up stages | L1: PSE Creation | M1: Source | N1: Engagement Type | O1: Trial sign up | P1: Status | Q1: Deal Size | R1: Revenue | S1: Suggested/purchased edition | T1: Notes | U1: Demo Recording | V1: Sales Notes from CRM | W1: Sprint link
A2: 46083 | B2: IN | C2: Sakthi | D2: enquiry@vaultenergy.no | E2: Energy | F2: #155613452 | G2: While initiating manual workflow for a file, the email address of an external user (non-zoho) is being added. The external user receives an email with the link and an OTP gets triggered, but the same email address does not receive an OTP despite retrying several times. “ sunil.shenoy@outlook.com ” is the external user’s email address, who is not receiving OTP to his inbox | H2: 1.The user wants to reassign email address in the middle of the manual workflow, to some other external user. If a person does not approve the file, the initiator needs to assign to a different external user. Pradeepkumar C Kabilkumar C 2. The prospect requested for exporting workflow activity as a report. | K2: Sales follow up 3 | M2: WorkDrive - Book a Demo (direct) | N2: Already Engaged Px | O2: Yes | P2: Deal Lost | Q2: 10 | S2: Starter | U2: The user did not want the session to be recorded. | V2: Mail addressed by support for a follow-up. | W2: Reassign external user in Workflow https://sprints.zoho.in/workspace/zdocs#P15/itemdetails/I7674
A3: 46083 | B3: EU | C3: Rohith | D3: ori@crowdmaster.co.uk | E3: Software | F3: #155703133 | G3: They are currently using Zoho Mail and Microsoft OneDrive for document management. They are considering a move to Zoho WorkDrive to keep everything within a single ecosystem. In addition, they need a way to send quizzes or forms to large groups (100–400 participants) and collect responses efficiently. | H3: None | I3: OneDrive | K3: Follow up 1 | L3: NO PSE | M3: WorkDrive - Book a Demo (direct) | N3: New Prospect | O3: Yes | P3: Deal Won | Q3: 4 | S3: Starter | U3: https://workdrive.zoho.in/file/gnb8b797ff3212b19463c8172b1d1117f963b
A4: 46084 | B4: APAC | C4: Janani | D4: nurul.apriani@acc.co.id | E4: Consulting | F4: #155277269 | G4: Prospect is looking for an overview about Zoho Sheet and collaborative tool in Zoho WorkDrive roles and permissions , security and compliance also added more on collaborating data | H4: Testing maximum row and column limits (creating and loading 4 million data entries), and Show Set Up Configuration - Zoho Sheet | I4: Excel | K4: Sales follow up 3 | M4: WorkDrive - Book a Demo (direct) | N4: New Prospect | O4: No | P4: Deal Lost | Q4: Not confirmed | S4: Business | U4: https://workdrive.zoho.in/file/kkv2z048eee0cf13a43f9b94797db906a1eae | V4: Regarding the current engagement, I would like to inform you that we are putting the process on hold for the time being. This is due to some internal feature adjustments and architectural alignment that we need to finalize on our end.
A5: 46084 | B5: IN | C5: Sakthi | D5: dhiraj@playo.co | E5: Financial service | F5: #155713681 | G5: Zoho One requirement. The prospect changed his mind and started looking at Zoho One License. | K5: Do not follow | M5: WorkDrive - Book a Demo (direct) | N5: New Prospect | O5: No | P5: No Scope for WD | Q5: 20 | S5: Zoho One | U5: Zoho One
A6: 46084 | B6: IN | C6: Rohith | D6: recruitment@meridiangbl.com | E6: HR solution | F6: #155619049 | G6: They are currently using Google Workspace and find it expensive. They are exploring a more affordable alternative and evaluating Zoho Workplace as a replacement. | H6: None | I6: Google Workspace | J6: 500GB | K6: Follow up 1 | L6: NO PSE | M6: WD support - Chat/Call/Mail | N6: New Prospect | O6: Yes | P6: Deal Won | Q6: 8 | S6: Starter | U6: https://workdrive.zoho.in/file/3p8iefef86f8b99dd464abca54b22146772dd
A7: 46085 | B7: IN | C7: Janani | D7: admin.team@neemargroup.com | E7: IT services | F7: #155857905 | G7: Prospect is looking for an cloud storage platform to store their data and manage in cloud | H7: None | K7: Sales follow up 3 | M7: WorkDrive - Book a Demo (direct) | N7: New Prospect | O7: Yes | P7: Deal Lost | Q7: 6 | S7: Starter | U7: https://workdrive.zoho.in/file/6j1r6dea4b57fc9404337b3d55a2de35fa86c | V7: Connected on the call, the free plan is sufficient.
A8: 46085 | B8: IN | C8: Janani | D8: abbabu@lorveninsurance.com | E8: Consulting | F8: #155617914 | G8: Paid Zoho Workplace Standard user User did not join the session, tried reaching on call he joined the session | H8: None | K8: Do not follow | M8: WorkDrive - Book a Demo (direct) | N8: Existing Paid Cx | O8: Existing user | P8: Existing customer | Q8: 3 | S8: WP (Professional) | U8: https://workdrive.zoho.in/file/6j1r604f45a2f569e483dbaee29f0bf7d6ecd
A9: 46086 | B9: IN | C9: Janani | D9: deepak.joshi@insecticidesindia.com | E9: Agrochemicals | F9: #155667623 | G9: 2 TB of cloud storage for files and folders. - User Management: Ability to create users with file upload and download permissions. - Desktop Integration: Ability to map the drive directly to local computers. - Backup: A comprehensive backup solution. - Security: Robust security features. | H9: None | J9: 2TB | K9: Sales follow up 2 | M9: WorkDrive - Book a Demo (direct) | N9: New Prospect | O9: Yes | P9: Deal Won | Q9: 10 | S9: Team | U9: https://workdrive.zoho.in/file/j753996ece80acf1442b5b41edc62cf53b48b | V9: Cx had purchased today
A10: 46086 | B10: US | C10: Rohith | D10: kaldavi350@gmail.com | E10: Personal | F10: #155857330 | G10: I want to be able to control my production process through a digital system and have the information at hand. | H10: None | K10: Follow up 1 | M10: WorkDrive - Book a Demo (direct) | N10: New Prospect | O10: Suspended | P10: Deal Lost | T10: user would like to know more about Zoho WorkDrive and prefers to continue the conversation in Spanish, looped LATAM team
A11: 46086 | B11: IN | C11: Praba | D11: giordanivarenkha@gmail.com | E11: Induvidual | F11: #155860272 | G11: User is interested in the Zoho Workplace bundle and requested a demo focused on Zoho WorkDrive. | I11: None | J11: - | K11: Sales follow up 2 | L11: NO PSE | M11: WorkDrive - Book a Demo (direct) | N11: New Prospect | O11: Yes | P11: Deal Won | Q11: 2 | S11: WP (Standard)
A12: 46086 | B12: EU | C12: Rohith | D12: lucie@ateliergaia.cz | E12: IT services | F12: #2329436 | G12: Queries on WD | H12: None | K12: Do not follow | L12: PSE/Concierge 59501 | M12: From Sales End | N12: New Prospect | O12: Yes | P12: Deal Won | Q12: 3 | S12: Starter | U12: No recording
A13: 46086 | B13: IN | C13: Rohith | D13: jijil@gsoftcomm.net | E13: Partner | F13: #154461063 | G13: Their teams operate from Mumbai and Kerala, with documents currently stored on local drives and external hard drives. Files are primarily shared via email, which has led to multiple versions of the same document and confusion over the latest copy. They are looking to move to a centralized cloud-based solution to streamline collaboration and eliminate duplication. | H13: None | I13: Local Drive | J13: 15 to 20TB | K13: Sales follow up 3 | L13: NO PSE | M13: From Sales End | N13: Partners | O13: Yes | P13: Deal Won | Q13: 25 | S13: WP (Standard) | V13: March 23 No response from the customer. Partner will let us know once the customer responds.
A14: 46084 | B14: IN | C14: Sakthi | D14: prashant.saxena@charismight.com | E14: Maritime Charter | F14: #155018697 | G14: >> Existing MS Office 365 user. Initially looking for a DMS that integrates with their Charismight application, which is an in-house application built in PHP and hosted in cloud. | H14: 1. The charter documents are usually 200 to 250 pages. They want to have charter templates created and documents created using templates. He will be saving charter template documents as org templates. >> The charter document will have lots of check lists, based on the check-lists filled, a score will be auto-calculated in the document, which will be in a table within the document. >> Based on the score generated in the document, a dashboard showcasing the analytics like the histograms will be created separately. For this dashboard, they are using an in-house application created using PHP. The painpoint is the complexity involved in quick updation of the parameters of the document checklists. >> He wants a solution that caters to this particular requirement, for which creator can also be suggested if Writer provides such data to create dashboards based on the parameters and scores generated in the document. | I14: MS Office 365 | K14: Sales follow up 2 | M14: WorkDrive - Book a Demo (direct) | N14: New Prospect | O14: No | P14: Deal Lost | Q14: 25 | S14: Business | U14: https://workdrive.zoho.in/file/6j1r6acd85030cfc1480e81fd8a2789478238 | V14: Connected to cx Anushka 00917775860594 POC said she will check and update creator team is also working on their requirements | W14: Writer related Requirement
A15: 46086 | B15: IN | C15: Sakthi | D15: alcantro@wellbeingnutrition.com | E15: Supplement manufacturing | F15: #155674385 | G15: Existing MS O365 E1 users. They currently have 14 TB of data in Sharepoint. | H15: They are looking for a Sharepoint migration tool as migrating 14TB of data manually would be a tedious task. | I15: MS Office 365 | J15: 14TB | K15: Sales follow up 3 | M15: WorkDrive - Book a Demo (direct) | N15: New Prospect | O15: Yes | P15: Deal Won | Q15: 30 | R15: 20400 | S15: Business | U15: No recording | V15: Spoke with cx, they wanted to go with the monthly billing. Shared mail to cx. Licenses will be procured under implementations@wellbeingnutrition.com | W15: Sharepoint migration https://sprints.zoho.in/workspace/zdocs#P15/itemdetails/I7689
A16: 46086 | B16: IN | C16: Sakthi | D16: idham.zulkifli@binary-nexus.com | E16: IT services | F16: #155778053 | G16: They are currently using 8000 MS O 365 licenses and aprox 6000 Google Workspace licenses. | H16: 1. They want interoperability with OneDrive and Google Workspace. >> As of now, interoperability with OneDrive is possible, however adding all MS O365 user as unlicensed users in Google Workspace is not supported. 2. They want files created in OneDrive or Google Drive to be saved in WorkDrive too. >> Have mentioned that have files created in one cloud platform and saving the same file in WorkDrive will only create copies and would not be the right approach. >> We have mentioned that we only support migration tool and not cross platform syncing kind of solution. 3. They have requested for “Save to WorkDrive” MS Office add-on for Google editors too. They want files created using Google Docs, Sheet and Slides to be saved to WorkDrive, like it is available for MS Office. >> Informed them that WorkDrive add-on is only available for MS Office desktop app and not online. As Google editors are online editors, we do not support extensions to “save to WorkDrive”. | I16: MS Office 365 & Google Workspace | K16: Follow up 3 | M16: WorkDrive - Book a Demo (direct) | N16: New Prospect | O16: Yes | P16: Deal Won | Q16: 20 | S16: Business | T16: Interoperability between Google and WorkDrive was requested. | U16: MS Teams Meeting
A17: 46087 | B17: US | C17: Logaraj | D17: jmoore@escrow321.com | E17: Real Estate | F17: #155476923 | G17: - Annotation feature, adding electronical signature, working on PDF, Workflow - assigning to groups. - Wants to store their Email. | K17: Sales follow up 3 | L17: NO PSE | M17: From Sales End | N17: New Prospect | O17: No | P17: Deal Lost | U17: https://workdrive.zoho.in/file/j7539cd3c15f539c14db0a2215b56650da51a | V17: No response
A18: 46087 | B18: ANZ | C18: Janani | D18: jerome.bruno@tejmerjerendeavours.com | E18: Consulting | F18: #155884284 | G18: Storage and document management | H18: None | K18: Follow up 3 | M18: WorkDrive - Book a Demo (direct) | N18: New Prospect | O18: Yes | P18: Deal Lost | Q18: 4 | S18: Starter | T18: No response | U18: https://workdrive.zoho.in/file/j7539fd154448438940859346b61a70310d26
A19: 46087 | B19: IN | C19: Janani | D19: sahilnparikh@gmail.com | E19: Personal | F19: #155540839 | G19: Prospect is looking to switch from Google to Zoho WorkDrive due to pricing constrain | H19: None | I19: Google | K19: Sales follow up 3 | M19: WorkDrive - Book a Demo (direct) | N19: New Prospect | O19: Yes | P19: Deal Lost | Q19: 10 | S19: Starter | U19: https://workdrive.zoho.in/file/j7539149f37b0835c4ca1860b66922baa51ed | V19: Tried reaching no response
A20: 46090 | B20: IN | C20: Rohith | D20: padmanabh_k@hotmail.com | E20: Personal | F20: #154886776 | G20: Zoho office desktop app | K20: Do not follow | L20: NO PSE | M20: Internally Looped | N20: Free Users | O20: Free User | P20: Free user | U20: No recording
A21: 46090 | B21: US | C21: Rohith | D21: jim@jimpeake.com | E21: Consultancy | F21: #101418190 | G21: Onboarding session | H21: None | K21: Do not follow | L21: NO PSE | M21: From Sales End | N21: Existing Paid Cx | O21: Existing user | P21: Existing customer | Q21: 3 | S21: Team
A22: 46090 | B22: US | C22: Rohith | D22: jayachandran.karumathil@intlreg.org | E22: Shipping | F22: #148896893 | G22: They are currently using a private cloud solution provided by a local IT company in Miami that offers hardware support, a VOIP phone system, and IT support services. They are looking for a cloud storage solution with folder hierarchy, user access control, personal folders for individual users, and department-based folder setup. | H22: None | I22: Inhouse server | J22: 1TB | K22: Sales follow up 1 | L22: PSE563085 | M22: From Sales End | N22: New Prospect | O22: Yes | P22: Deal Won | Q22: 10 | S22: Business | T22: Added 5 more license in trial account with custom plan | U22: https://workdrive.zoho.in/file/z1hra53740e3081b1473a957b654820096096
A23: 46090 | B23: IN | C23: Sakthi | D23: head.it@sithltd.com | E23: Food | F23: #155995585 | G23: 1. They were looking for a repository for their HR and Finance teams. | H23: Support for Workflow on mobile apps for iOS and Android | I23: Power Doc | K23: Sales follow up 3 | M23: WorkDrive - Book a Demo (direct) | N23: New Prospect | O23: Yes | P23: In Progress | Q23: 10 | S23: Business | U23: https://workdrive.zoho.in/file/uhqn7c0b45a41b1f84806bef8b9e3d9a6e480 | W23: Support Workflow on mobile app (Android) https://sprints.zoho.in/workspace/zdocs#P15/itemdetails/I7693 Support Workflow on mobile app (iOS) https://sprints.zoho.in/workspace/zdocs#P15/itemdetails/I7692
A24: 46090 | B24: IN | C24: Sakthi | D24: pragneshdhage@zohomail.in | E24: Information Services | F24: #153102371 | G24: Gave a complete demo to Pragnesh, there were no special requirements. prospect is looking to purchase 5Starter licenses. | K24: Sales follow up 3 | M24: WorkDrive - Book a Demo (direct) | N24: New Prospect | O24: Yes | P24: Deal Lost | Q24: 5 | S24: Starter | U24: https://workdrive.zoho.in/file/uhqn77ccc817b375d49f580c6198f936eab87 | V24: No response over mails/ calls
A25: 46090 | B25: IN | C25: Janani | D25: caredont473@gmail.com | E25: Consulting | F25: #155825611 | G25: Store company data securely. Share selected files/folders with clients. | H25: None | K25: Sales follow up 1 | M25: WorkDrive - Book a Demo (direct) | N25: New Prospect | O25: No | P25: Deal Lost | Q25: 46146 | S25: Starter
A26: 46090 | B26: IN | C26: Janani | D26: tanmay.th@gmail.com | E26: Small Tech Project | F26: #150273609 | G26: Prospect is looking for switch from System server to cloud, as there are 2 people in the CA firm and accessing data if a person is not available has been a challenge | H26: None | I26: System server | K26: Follow up 3 | M26: WorkDrive - Book a Demo (direct) | N26: New Prospect | O26: Yes | P26: Deal Won | Q26: 4 | S26: Starter | U26: https://workdrive.zoho.in/file/j753962559477364341238cfc09e30ab36c04
A27: 46090 | B27: EU | C27: Janani | D27: admin@bramhall1840.co.uk | E27: Manufacturing | F27: #155301639 | G27: Customer joined the session using a mobile device due to laptop issues. Customer had already explored the free trial earlier. Primary requirement is to upload data, organize files, and give team access. Data is currently stored on a local hard drive. | H27: None | K27: Follow up 3 | M27: From Sales End | N27: Already Engaged Px | O27: Yes | P27: Free user | Q27: 4 | S27: Starter | U27: https://workdrive.zoho.in/file/j7539bdd595fddc7a4adeabd366b4038064c5
A28: 46090 | B28: IN | C28: Janani | D28: jayaprakash.h@spagofoods.com | E28: Food Retail | F28: #155893242 | G28: The customer is looking to digitize physical documents and implement a digital approval workflow to eliminate paper-based approvals and manual document handling. | H28: None | K28: Sales follow up 3 | M28: WD support - Chat/Call/Mail | N28: New Prospect | O28: Extended | P28: Deal Lost | Q28: 15 | S28: Team | T28: Connect customer with Zoho Concierge Team for solution consultation. Arrange follow-up discussions for: Zoho Desk Zoho Projects Zoho Creator integrations | U28: https://workdrive.zoho.in/file/j753910a15b5d141e46638b3c5aeb5be9f141 | V28: No response
A29: 46091 | B29: APAC | C29: Sakthi | D29: shayne.higino@devtac.com | E29: Partner | F29: #155942873 | G29: Gave a training to partner DEVTAC. 20+ Team members from Partner org joined the session to focus on how WorkDrive can be pitched. | I29: Google Workspace | K29: Do not follow | M29: From Sales End | N29: Partners | O29: Partner | P29: Partner | T29: Partner training session. | U29: https://workdrive.zoho.in/file/z1hracdfadd9dc69f4fc587b00fd885f037c2
A30: 46091 | B30: EU | C30: Rohith | D30: admin@bramhall1840.co.uk | E30: IT services | F30: #2221931 | G30: Queries on WD | H30: None | I30: Local Drive | K30: Follow up 3 | M30: From Sales End | N30: Already Engaged Px | O30: Yes | P30: Free user | Q30: 5 | S30: Starter | U30: Not recorded
A31: 46091 | B31: IN | C31: Rohith | D31: yogesh@vara.co | E31: Accounting | F31: #156144235 | G31: They are looking for a compliance tracker solution that can automatically send monthly reminders to upload compliance documents and provide a tracking system to ensure files are uploaded regularly. Once documents are uploaded, the system should notify or report to the hierarchy or higher management. They are looking for something more advanced than simple cloud storage, unlike their current setup with OneDrive | H31: compliance tracking + reminders + document repository solution | I31: OneDrive | K31: Follow up 3 | L31: NO PSE | M31: WorkDrive - Book a Demo (direct) | N31: New Prospect | O31: Yes | P31: Free user | S31: Business | U31: https://workdrive.zoho.in/file/j75397a625a94bb9841459110c92fb9786316 | W31: Documents expiry - https://sprints.zoho.in/workspace/zdocs#P15/itemdetails/I7456/details
A32: 46091 | B32: IN | C32: Rohith | D32: manivelca@gmail.com | E32: Accounting | F32: #156105917 | G32: They are currently using OneDrive for document management but are facing several issues, especially with after-sales support. As a result, they are exploring Zoho as an alternative—not only for document management but also for other Zoho solutions such as invoicing, payment gateway, campaigns, CRM, and more. | H32: None | I32: OneDrive | K32: Sales follow up 3 | L32: PSE562759 | M32: From Sales End | N32: New Prospect | O32: Yes | P32: Deal Won | Q32: 20 | S32: Business | U32: https://workdrive.zoho.in/file/j7539bbd99514d7a042eba5a30594ad2ca679 | V32: They are interested in Zoho One bundle solution they will be evaluating it accordingly
A33: 46091 | B33: IN | C33: Janani | D33: bhavik181931@gmail.com | E33: Personal | F33: #156092071 | G33: Prospect was looking for family storage option, explained and differentiated | J33: 1TB | K33: Do not follow | M33: WorkDrive - Book a Demo (direct) | N33: New Prospect | O33: No | P33: No Scope for WD | Q33: 4 | S33: Zillum | U33: https://workdrive.zoho.in/file/j75395e530457887840518ded021fcc290f28
A34: 46091 | B34: IN | C34: Janani | D34: salesinfoelecom@gmail.com | E34: Telecommunications | F34: #150301978 | G34: They are currently storing documents on individual users’ machines and want to move everything to the cloud. They had already explored Zoho WorkDrive and, before proceeding with the purchase, wanted a complete walkthrough of the product. | H34: None | J34: 2TB | K34: Sales follow up 3 | M34: From Sales End | N34: Already Engaged Px | O34: Yes | P34: Free user | Q34: 7 | S34: Team | U34: https://workdrive.zoho.in/file/j7539f5e1afc021954a8e9d1c427d63ffc986
A35: 46092 | B35: US | C35: Rohith | D35: chris@nwids.com | E35: Design | F35: #155981652 | G35: manage expenses, invoices, inventory, mileage, and equipment purchases | K35: Do not follow | L35: NO PSE | M35: WorkDrive - Book a Demo (direct) | N35: New Prospect | O35: No | P35: No Scope for WD | Q35: 2 | T35: Suggested Zoho Inventory & books | U35: https://workdrive.zoho.in/file/j75391ae6f914b67846c09456657fcc8a68e6
A36: 46092 | B36: APAC | C36: Rohith | D36: stu.hunter@rbbs.com.au | E36: Internet | F36: #155891419 | G36: The customer is looking for a secure FTP-based file transfer solution where their customers can upload sensitive documents safely instead of sending them through email. The files should be uploaded to a secure server, remain available for about 72 hours, and then automatically delete. The solution should also support large file uploads (up to ~25 GB) and provide timestamping or traceability for the transfers. They currently use Microsoft OneDrive for storage and host their systems on Microsoft Azure, but are exploring more cost-effective alternatives since Azure’s FTP feature is relatively expensive. | I36: OneDrive | K36: Do not follow | L36: PSE562761 | M36: From Sales End | N36: New Prospect | O36: Yes | P36: No Scope for WD | T36: They are not interested to move from OneDrive to WorkDrive, just looking for FTP solution | U36: https://workdrive.zoho.in/file/j75393864b76e15544396bff0a9dab75cfd54
A37: 46092 | B37: APAC | C37: Rohith | D37: itsupport@linesandframesprojects.com | E37: IT services | F37: #156166565 | G37: user wanted to know the available storage add-on options in the Workplace bundle. | H37: None | K37: Do not follow | L37: NO PSE | M37: WorkDrive - Book a Demo (direct) | N37: Existing Paid Cx | O37: Existing user | P37: Existing customer | Q37: 13 | S37: WP (Standard) | U37: https://workdrive.zoho.in/file/j753926d5e2aa340848d48a31908e7f981bab
A38: 46092 | B38: IN | C38: Janani | D38: sales@piinacle.com.sg | E38: Manufacturing | F38: #155432463 | G38: provided an overview of Zia AI capabilities within Zoho WorkDrive for existing Zoho Workplace users and to address queries related to AI features and user management. | H38: ZIA Hubs in WP | K38: Do not follow | M38: WorkDrive - Book a Demo (direct) | N38: Existing Paid Cx | O38: Existing user | P38: Existing customer | Q38: 3 | S38: WP (Standard)
A39: 46092 | B39: IN | C39: Sakthi | D39: shaheer@shintech.co.uk | E39: Manufacturing | F39: #156129679 | G39: 1. Existing users of Zoho Books. The customer is currently using Synology for local storage and wants a cloud-based backup and collaboration solution. | K39: Sales follow up 3 | M39: WorkDrive - Book a Demo (direct) | N39: New Prospect | O39: Yes | P39: Deal Lost | Q39: 40 | S39: Team | U39: https://workdrive.zoho.in/file/bwvtoaf5a513edcb34da185495b4665d29d9a
A40: 46092 | B40: IN | C40: Sakthi | D40: ashok_gaikar@icicipruamc.com | E40: Banking | F40: #122669811 | G40: Discussed on Zoho Office Suite. They have requested for packages to download writer, sheet and Show in one go. | H40: Download Writer, Sheet and Show offline apps in one package. | K40: Do not follow | M40: Direct Mail to Presales | N40: Already Engaged Px | O40: POC | P40: In Progress | Q40: 3000 | S40: WP flexi | U40: MS Teams Meeting | W40: Related to Office Suite
A41: 46092 | B41: US | C41: Rohith | D41: p.riesel@massbbo.org | E41: Law practice | F41: #155963064 | G41: They have recently purchased Zoho Desk for their ticketing system and are currently using ShareFile for document storage. Since ShareFile does not integrate with Zoho Desk, they are unable to attach files from their document storage while replying to tickets. Hence, they are considering moving to Zoho WorkDrive so they can easily pick and attach files from WorkDrive while responding in Zoho Desk. No other special requirements were mentioned. | H41: None | I41: ShareFile | K41: Sales follow up 3 | L41: NO PSE | M41: WorkDrive - Book a Demo (direct) | N41: New Prospect | O41: Yes | P41: Deal Lost | Q41: 12 | U41: https://workdrive.zoho.in/file/iyyxxc3b64be9b6a04845a99d956eeeb3df01 | V41: Tried reaching the prospect through phone but it was a common line hence sent an email to the prospect.
A42: 46092 | B42: IN | C42: Rohith | D42: arunav.uppal@gmail.com | E42: Startup | F42: #156105271 | G42: The customer wanted to understand key aspects of Zoho WorkDrive, including storage limits and scalability for their team, admin controls and user permission management, integration capabilities with tools such as Microsoft 365 and Gmail, as well as details on data security, compliance, privacy, and pricing flexibility including any enterprise or volume discounts. | H42: They were also particularly interested in the AI aspect and asked whether Claude AI by Anthropic can integrate with WorkDrive through a plugin, extension, marketplace integration, or APIs. | I42: Google Drive | K42: Sales follow up 3 | L42: NO PSE | M42: From Sales End | N42: New Prospect | O42: Yes | P42: Deal Lost | Q42: 30 - 40 | S42: Business | U42: https://workdrive.zoho.in/file/iyyxxb6ce4fa2352d495a87794f56e70112af | V42: Mach 18 No response | W42: WorkDrive + Claude AI integration https://sprints.zoho.in/workspace/zdocs#P15/itemdetails/I7737
A43: 46093 | B43: IN | C43: Janani | D43: rmishra@hngil.com | E43: Manufacturing | F43: #156099020 | G43: The main objective discussed was to digitize and organize all physical and digital records into a structured document management system. | K43: Do not follow | M43: WorkDrive - Book a Demo (direct) | N43: New Prospect | O43: No | P43: No Scope for WD | Q43: 6 | S43: Zoho One
A44: 46093 | B44: IN | C44: Janani | D44: docsupport@choiceorg.com | E44: Manufacturing | F44: #156154216 | G44: How documentation and folders can be managed in the system, How restricted access can be provided to specific users How the owner or admin can control permissions for accessing folders and documents How workflows for document review and approval can be implemented | H44: None | K44: Follow up 3 | M44: WorkDrive - Book a Demo (direct) | N44: New Prospect | O44: Yes | P44: Deal Lost | Q44: 10 | S44: Team | V44: No response
A45: 46093 | B45: EU | C45: Sakthi | D45: christine.sielemann@luxaviation.com | E45: Aviation | F45: #154334623 | G45: The prospect is evaluating for 3 user licenses. | H45: Need to check on your requirement to have a template document created as theme in Zoho Show, so that you can change the theme to the slides created from Analytics dashboard | K45: Follow up 3 | M45: WorkDrive - Book a Demo (direct) | N45: New Prospect | O45: Yes | P45: Deal Lost | Q45: 3 | S45: Starter | T45: Zoho Show has to provide an upload or create theme and set it up as default theme.\ | U45: https://workdrive.zoho.in/file/77r61dc36760c40f64012ac4fadb56000e227 | W45: Zoho Show related.
A46: 46093 | B46: IN | C46: Sakthi | D46: ajked@ajkcas.com | E46: Educational institution | F46: #152777802 | G46: 1. Existing prospect came for a complete demo on Workflow with their team. 2. He wanted to integrate Zoho Sign at the end of the Workflow. Showed him how to meet this requirement using cu | K46: Sales follow up 3 | M46: WorkDrive - Book a Demo (direct) | N46: Already Engaged Px | O46: Yes | P46: Deal Lost | Q46: 70 | S46: Business | U46: https://workdrive.zoho.in/file/77r6157747334e0874574a33c38d5de5a468b | V46: Cx is asked to follow up later
A47: 46093 | B47: IN | C47: Rohith | D47: kvrvenkat.ca@outlook.com | E47: Marketing | F47: #156203899 | G47: They are currently using multiple Zoho products, but for document management they use Google Drive in their Chennai office and OneDrive in their Bangalore office. They are planning to move to Zoho WorkDrive so that all document management can be handled on a single unified platform. | H47: None | I47: Google Drive & OneDrive | K47: Sales follow up 3 | L47: NO PSE | M47: WD support - Chat/Call/Mail | N47: New Prospect | O47: Yes | P47: Deal Lost | Q47: 20 | U47: https://workdrive.zoho.in/file/77r612966ee480df54a099360e1e983d4bcd3 | V47: 23/3/2026 No answer , follow up email sent
A48: 46094 | B48: IN | C48: Janani | D48: ben.thomas@absatellite.com | E48: Telecommunications | F48: #156096705 | G48: - We need team folder management with group-based access controls so we can assign users to specific folders by department or project | H48: None | K48: Sales follow up 3 | M48: WorkDrive - Book a Demo (direct) | N48: New Prospect | O48: No | P48: Deal Lost | Q48: 10 | S48: Starter | U48: https://workdrive.zoho.in/file/ggxqxa2b3b1c1cb0c4b65b51569925fd399c2 | V48: spoke with the px he said he is going the existing subcription - share point
A49: 46094 | B49: IN | C49: Janani | D49: thoratshivraj@gmail.com | E49: Personal | F49: #155249896 | G49: Personal use | H49: Selective Sync - Need to choose Subfolders from a team folder Sync | K49: Follow up 2 | M49: From Sales End | N49: New Prospect | O49: Yes | P49: Deal Won | Q49: 3 | S49: Starter | U49: https://workdrive.zoho.in/file/ggxqxe17d54ecc3714df58faa299a743b6d9e
A50: 46094 | B50: IN | C50: Janani | D50: charan.kumar@tattvasol.com | E50: Digital Marketing | F50: #149786709 | G50: Need to explore for documents storing, and sharing with customer . Working online, joning the meeting | H50: None | K50: Sales follow up 3 | M50: WorkDrive - Book a Demo (direct) | N50: New Prospect | O50: Yes | P50: Deal Won | Q50: 5 | S50: Starter | U50: https://workdrive.zoho.in/file/ggxqx628403b290d04b5cbc4ad820366c5426 | V50: wanted to get price quote shared him official price quote follow up email sent
A51: 46094 | B51: IN | C51: Rohith | D51: infoteranovaspace026@gmail.com | E51: Design | F51: #156146347 | G51: They are facing challenges in sharing large files both internally and with external clients. Their typical file size is around 20GB per file, and clients need to download files via shared links. | H51: None | J51: 500GB | K51: Sales follow up 3 | L51: PSE566674 | M51: WorkDrive - Book a Demo (direct) | N51: New Prospect | O51: Yes | P51: Deal Lost | Q51: 3 | S51: Starter | U51: https://workdrive.zoho.in/file/hcuw68b00812983db471aa94d1722504d40ab | V51: March 25 No answer, follow up email sent
A52: 46094 | B52: IN | C52: Sakthi | D52: deepak.joshi@insecticidesindia.com | E52: Manufacturing | F52: #155667623 | G52: Need to store large files such as videos, images, and scanned documents instead of storing them locally on laptops | H52: None | K52: Sales follow up 3 | M52: WorkDrive - Book a Demo (direct) | N52: New Prospect | O52: Yes | P52: Deal Won | Q52: 18 | S52: Team | U52: https://workdrive.zoho.in/file/h18q4cf49afb79d1f446a819e361e4a30827f
A53: 46094 | B53: IN | C53: Sakthi | D53: info@kcomforttravels.com | E53: Travels | F53: #156202152 | G53: They are exploring various Zoho apps like WorkDrive, CRM, Books and mail. | K53: Do not follow | M53: WorkDrive - Book a Demo (direct) | N53: New Prospect | O53: No | P53: Deal Lost | Q53: 7 | S53: Zoho One | U53: No recording
A54: 46097 | B54: US | C54: Jennifer | D54: bria@brightlittlepages.com | E54: Individual | F54: #156135761 | G54: She is an author who is looking for centralised storage between herself and her friend with whom she will be sharing documents, initially she was using mail but found it difficult to keep track. | H54: None | I54: Mail | K54: Sales follow up 2 | L54: PSE564062 | M54: From Sales End | N54: New Prospect | O54: Yes | P54: Deal Won | Q54: 3 | R54: 9 | S54: Starter | U54: https://workdrive.zoho.in/file/h8u2hde72b07ea9ca4cfab2dc288f0edae7a3 | V54: Deal won
A55: 46097 | B55: IN | C55: Jennifer | D55: dinagaran@bvrpc.com | E55: Consultancy | F55: #155569446 | G55: Cx and team (existing paid team) joined the session and mentioned they are a consulting firm with 10-15 members using large data of resumes. Currently they are managing files from their local drives, where its difficult to process them so looking for ways to efficiently manage them. | H55: None | I55: Local Drive | K55: Do not follow | L55: NO PSE | M55: WorkDrive - Book a Demo (direct) | N55: Existing Paid Cx | O55: Existing user | P55: Existing customer
A56: 46095 | B56: IN | C56: Sakthi | D56: bharathkumar.k@cityunionbank.in | E56: Banking | F56: #156377104 | G56: 1. They are evaluating Offline Desktop apps of Writer, Sheet and Show for 8700 users. 2. There are 3700+ Linux (SUSE) machines and 4000+ Windows machines. | H56: Special Requirement: 1. They are looking for Zoho Sheet and Zoho Show for Linux (SUSE) as .RMP. >> They wanted to be notified once beta for Linux SUSE for Sheet and Show is available. >> As 3700 users are using Linux machines and the number is going to grow in the future as they want to curb Windows machine and increase Linux machines in their organisation. @Vaseekaran Baskaran @Tikeshwar Sahu @Kumar Vinay Shree Shiv Shankar Prasad Saw @Kirubhakaran Mohan @Ramasubiah Mohanasundaram @John Victor D 2. Currently Writer for Linux is available as .DEB, but they are looking to have as .RMP format installer file. @Ganeshprabhu Rajendran @Madhankumar Ramamoorthy 3. Macros support for Zoho Sheet Offline desktop app. @Kumar Vinay Shree Shiv Shankar Prasad Saw @Ganesh Ramsakthi Mohan 4. Offline installation (without internet) for Writer, Sheet and Show, is crucial for them as they do not want to provide internet access to their users. 5. They want to push the installation of Office Suite and app updates through ME Endpoint Central. They are currently using Endpoint Central to install other applications and they want native Zoho application to be the same way. >> Please add your insights for #4 and #5, @Shyamala Ramesh @Ramesh Sripathy @Karthikeyan Jambulingam | K56: Do not follow | M56: From Sales End | N56: Existing Paid Cx | O56: Yes | P56: In Progress | Q56: 8700 | S56: Zoho Office Suite Desktop apps | U56: MS Teams Meeting | W56: Zoho Office Suite related.
A57: 46097 | B57: IN | C57: Janani | D57: ssbglobal07@gmail.com | E57: Consutling | F57: #156350015 | G57: UL - 10 Connected with Suresh and provided an overview and demo of Zoho WorkDrive. | H57: None | K57: Sales follow up 3 | M57: WorkDrive - Book a Demo (direct) | N57: New Prospect | O57: Yes | P57: Deal Lost | Q57: 10 | S57: Starter | U57: https://workdrive.zoho.in/file/100ge76ffc86606524f71875e40b8ac4b3b17 | V57: no answer, follow up emnail sent
A58: 46097 | B58: US | C58: Janani | D58: design@iscaffdesigns.co.uk | E58: Architect | F58: #156375211 | G58: Connected with the customer and discussed their requirement to share folders with remote employees to upload and download files without giving full platform access. | H58: None | K58: Follow up 3 | M58: WorkDrive - Book a Demo (direct) | N58: New Prospect | O58: No | P58: Deal Won | Q58: 1 | S58: Team
A59: 46097 | B59: IN | C59: Sakthi | D59: akashvince.h@usam.in | E59: Partner | F59: #155932660 | G59: 1. They are using Auto CAD to preview and edit their design files. 2. WorkDrive is yet to support Auto CAD. They say that in order to preview the file, it has to be downloaded. 3. As of now suggested WorkDrive TrueSync and Genie to preview and edit CAD files. . | H59: 1. We need to provide preview support for CAD files in WorkDrive | K59: Do not follow | M59: WorkDrive - Book a Demo (direct) | N59: Partners | O59: Partner | P59: Partner | T59: It was a user education session for Partner for a client's requirement. | U59: No recording | W59: Auto CAD preview supporthttps://sprints.zoho.in/workspace/zdocs#P15/itemdetails/I7462/details
A60: 46097 | B60: IN | C60: Rohith | D60: xemploy09@gmail.com | E60: Electronics | F60: #156394602 | G60: i need a full crm, inventory management or dealer Portal. so can you give me a demo about this system? | K60: Do not follow | L60: NO PSE | M60: WorkDrive - Book a Demo (direct) | N60: Free Users | O60: No | P60: No Scope for WD | T60: Cx is looking for CRM & Inventory
A61: 46097 | B61: LATAM | C61: Rohith | D61: hima.haridas@whitehatvirtual.com | E61: IT services | F61: #156348331 | G61: The customer initially mentioned a requirement for data management, but during the discussion it became clear that their needs were primarily related to Zoho Vault. | H61: None | K61: Do not follow | L61: NO PSE | M61: From Sales End | N61: Free Users | O61: No | P61: No Scope for WD | U61: Zoom meeting
A62: 46097 | B62: IN | C62: Rohith | D62: sudharsan0124@gmail.com | E62: Photography | F62: #156265729 | G62: The customer is a photographer currently storing raw files on external hard disks. Due to increasing storage costs, they are exploring cloud storage as a secondary backup solution for raw photography files. | H62: None | I62: Hard Disk | J62: 2TB | K62: Sales follow up 3 | L62: PSE565504 | M62: WorkDrive - Book a Demo (direct) | N62: New Prospect | O62: Yes | P62: Deal Lost | Q62: 3 | S62: Business | U62: https://workdrive.zoho.in/file/pzjvw6e8f055db870443bacb31579e495ed6e | V62: March 23 No answer, follow up email sent
A63: 46098 | B63: IN | C63: Janani | D63: archita.s.parikh@gmail.com | E63: Marketing | F63: #156406214 | G63: Customer is evaluating migration from Google Workspace to Zoho within 24 hours | K63: Do not follow | M63: From Sales End | N63: New Prospect | O63: Yes | P63: Deal Lost | Q63: 18 | S63: WP (Professional) | T63: WP Team has sent email | U63: https://workdrive.zoho.in/file/100gef4ccd26f92b44bfcb68c569065a5a3e8
A64: 46098 | B64: IN | C64: Jennifer | D64: enquiry@ssmasc.edu.in | E64: Educational institution | F64: #156261467 | G64: They are currently using their local drive and mail to host and share files within them, and now looking to moved to a cloud based DMS. | I64: Local Drive | K64: Sales follow up 3 | L64: PSE564517 | M64: WD support - Chat/Call/Mail | N64: New Prospect | O64: Yes | P64: Deal Lost | Q64: Not confirmed | U64: https://workdrive.zoho.in/file/dixwue73221d9aeb24d708f809a6d8ce9b682 | V64: Follow up email sent asking for updates
A65: 46098 | B65: APAC | C65: Jennifer | D65: director@indokrisna.com | E65: Partners | F65: #156480110 | G65: They are looking to understand how Zoho WorkDrive can be positioned as a standalone DMS solution for their clients. | H65: Client's requirement: AI-based auto-classification of files into folders based on content | K65: Do not follow | L65: NO PSE | M65: From Sales End | N65: Partners | O65: Partner | P65: Partner | U65: https://workdrive.zoho.in/file/du5hqf274dc4db26c4d439e1a5bb5113512af | W65: https://sprints.zoho.in/workspace/zdocs#P15/itemdetails/I7425
A66: 46098 | B66: IN | C66: Rohith | D66: vishal.s@senseselec.com | E66: Electronics | F66: #156422427 | G66: They are currently using Google services to store and share training materials such as videos, PPTX, DOCX, XLSX, and audio files. They have also created a self-training website using Google Sites where team members log in to access content stored in Google Drive. | H66: None | I66: Google drive | K66: Sales follow up 3 | L66: PSE564809 | M66: WorkDrive - Book a Demo (direct) | N66: New Prospect | O66: Yes | P66: Deal Lost | Q66: 10 + few client user license | S66: Team | U66: https://workdrive.zoho.in/file/pzjvw973ec7ee532a40249fe16d81c405b513 | V66: April 6 Tried reaching the px but they ignored my call
A67: 46098 | B67: IN | C67: Sakthi | D67: vir.singh@teri.res.in | E67: Non-profit | F67: #155224008 | G67: Each project has a defined approval hierarchy (Purchase department-> PI → Director → Department Director → Purchase Admin Director → DG based on value less than or More than 10L). | K67: Sales follow up 2 | M67: WorkDrive - Book a Demo (direct) | N67: Already Engaged Px | O67: Yes | P67: Deal Lost | Q67: 70 | S67: Zoho One | U67: https://workdrive.zoho.in/file/du5hqaa1ce780c7684be88414cdcbb28ae88e | V67: Tried reaching the px no response, sent email
A68: 46098 | B68: IN | C68: Sakthi | D68: jaineel.shah@npcpl.in | E68: Consultancy | F68: #156340712 | G68: Looking for a cloud storage solution similar to Dropbox/Google Drive but more cost-effective. | I68: Google Drive / Dropbox | K68: Sales follow up 3 | M68: WorkDrive - Book a Demo (direct) | N68: New Prospect | O68: Yes | P68: Deal Lost | Q68: 5 | S68: Starter | U68: https://workdrive.zoho.in/file/du5hq608203f3ffbe4194b9be1db4d19c16b4 | V68: Cx had dropped mail Dear Monica, I tried zoho workdrive and I found useful. However we have to use office 365 for other users for their day to day tasks. So it is not making sense for me tonpay at both ends. But in future I will definitely consider this as sure replacement of onedrive.
A69: 46063 | B69: IN | C69: Jennifer | D69: sumeet.sodhani@gmail.com | E69: CA | F69: #154821218 | G69: Follow up QnA session | H69: None | I69: on-premise | K69: Sales follow up 3 | L69: PSE553553 | M69: From Sales End | N69: New Prospect | O69: Yes | P69: Deal Won | Q69: 3 | V69: px done with demo tried reaching the px no response sent email - Tried reaching no response sent commercials, px done with demo
A70: 46099 | B70: IN | C70: Janani | D70: rvasane@amherst.com | E70: Manufacturing | F70: #156472880 | G70: Customer manages ~10K+ invoices/month using Excel with formulas. | K70: Do not follow | M70: WorkDrive - Book a Demo (direct) | N70: New Prospect | O70: No | P70: No Scope for WD | Q70: Not confirmed | S70: Free Individual | U70: https://workdrive.zoho.in/file/100ged37e3681e54d434c85e40ad8be672f01
A71: 46099 | B71: IN | C71: Rohith | D71: jitesh.jadhav@tyger.in | E71: Financial service | F71: #156208786 | G71: OneDrive for test migration | H71: None | I71: OneDrive | K71: Do not follow | M71: Internally Looped | N71: Already Engaged Px | O71: Yes | P71: In Progress | S71: Business | U71: No recording
A72: 46099 | B72: IN | C72: Rohith | D72: rizwan@alainfinance.ae | E72: Financial service | F72: #155474896 | G72: Requirement discussion | K72: Sales follow up 2 | L72: PSE568758 | M72: WD support - Chat/Call/Mail | N72: New Prospect | O72: Yes | P72: Deal Lost | Q72: 5 | S72: Business | U72: https://workdrive.zoho.in/file/100ge9cd034004ccf43cdbfe14909a3c0ece5
A73: 46099 | B73: IN | C73: Janani | D73: rvasane@amherst.com | E73: Real Estate Investment | F73: #156472880 | G73: The prospect currently uses Excel with multiple sheets and formulas to record utility service bill details before uploading them to their accounting application. The file often hangs when making enhancements. He is looking for an alternative solution where the same formulas can be applied, and multiple team members can access and work on the file simultaneously. | H73: Excel is slow and unstable with large data (~3+ lakh rows). Manual consolidation and GL coding. | K73: Do not follow | M73: WorkDrive - Book a Demo (direct) | N73: New Prospect | O73: Yes | P73: No Scope for WD | Q73: 10 | U73: https://workdrive.zoho.in/file/100ge0c5230ccb6bc4bfd9a9da1930684d91b
A74: 46100 | B74: IN | C74: Janani | D74: ayushdas11@gmail.com | E74: Consulting | F74: #156495380 | G74: Conducted a product demo of Zoho WorkDrive for ~5–10 users looking for a cloud-based solution primarily for data storage and backup. Clarified that WorkDrive is a cloud storage and collaboration platform (similar to Google Drive/Dropbox) and does not support automatic system backup—files need to be uploaded manually or via TrueSync. | H74: None | K74: Sales follow up 3 | M74: From Sales End | N74: New Prospect | O74: Yes | P74: Deal Lost | Q74: 46300 | S74: Team | U74: https://workdrive.zoho.in/file/100ge4dd7f17f2dbe4e1f88b30205ac249860 | V74: Tried reaching the px no response.
A75: 46100 | B75: ANZ | C75: Janani | D75: mehdi.alinejad@yhuterminal.com | E75: Logistics | F75: #156559493 | G75: Prospect joined the session, due to some audio challenges prospect wanted to share the details about the feature and then he will reach back to us | H75: None | K75: Sales follow up 3 | M75: WorkDrive - Book a Demo (direct) | N75: New Prospect | O75: No | P75: Deal Lost | Q75: 200 | S75: Business | V75: Thank you for your quotation and support. After careful review, we have decided to proceed with another option and will not be moving forward with your proposal at this time. We appreciate your time .
A76: 46100 | B76: EU | C76: Rohith | D76: schmittef@gemm.ms.de | E76: Primary school | F76: #2371902 | G76: They are currently using IServ, a platform designed for schools, but are facing limitations with storage (only 1 TB available). They also highlighted issues such as files being accidentally deleted by students and difficulty accessing files across multiple devices. | H76: They are looking for SSO integration with the IServ platform | I76: IServ, a platform designed for schools | J76: 1TB | K76: Sales follow up 2 | L76: PSE/Concierge 59998 | M76: From Sales End | N76: New Prospect | O76: No | P76: In Progress | Q76: 150 user licenses and 1000 client user licenses | S76: Starter | T76: They plan to start evaluating the product after April 13 (post school vacation), with a potential full rollout by August this year. Connect post | U76: https://workdrive.zoho.in/file/tcoml783644bce4eb45d48a27f35fb7240bc3 | W76: Accounts team related
A77: 46100 | B77: EU | C77: Rohith | D77: slouis@ohs.uk | E77: Construction | F77: #2375234 | G77: They are looking to manage invoices for construction projects. Currently, invoices are received via Gmail and approved manually, which is inefficient. They want a centralized portal to upload all invoices, set up approval workflows, and then move approved files to the appropriate folders. | H77: None | I77: None | K77: Sales follow up 3 | L77: PSE/Concierge 60049 | M77: From Sales End | N77: New Prospect | O77: Yes | P77: Deal Won | Q77: 3 | S77: Business | U77: https://workdrive.zoho.in/file/tcomla0e7767734304ba08c306d78fa19b4e5 | V77: no response, sending an email follow up
A78: 46101 | B78: IN | C78: Janani | D78: crandell@myedusolutions.com | E78: Education | F78: #156678022 | G78: ustomer is using multiple Zoho One organizations across different businesses and is looking for a consistent UI/experience across all. | H78: None | K78: Do not follow | M78: WorkDrive - Book a Demo (direct) | N78: Existing Paid Cx | O78: Existing user | P78: Existing customer | Q78: 6 | S78: Zoho One
A79: 46101 | B79: IN | C79: Janani | D79: adpradhan5101@gmail.com | E79: Consulting | F79: #156581004 | G79: I want to explore all the possible features that we can use on zoho to optimise our workflow and also want to know in detail regarding the workflow option in zoho workdrive | H79: None | K79: Do not follow | M79: WorkDrive - Book a Demo (direct) | N79: Existing Paid Cx | O79: Existing user | P79: Existing customer | Q79: 80 | S79: Business
A80: 46101 | B80: IN | C80: Jennifer | D80: siddharthbest@gmail.com | E80: Interior Design | F80: #156619048 | G80: They are currently going e-commerce/digital where they are trying to create ad and would like their external users to directly access around 50 number of files for view or download purposes. | H80: None | K80: Sales follow up 2 | L80: NO PSE | M80: WorkDrive - Book a Demo (direct) | N80: New Prospect | O80: No | P80: In Progress | Q80: 46115 | S80: Starter | U80: No recording - connected in Zvoice for audio and Zmeeting for share screen | V80: April 21 Spoke with cx and they had queries in external share link. Email shared to cx
A81: 46101 | B81: IN | C81: Jennifer | D81: shivaraj@yantralive.com | E81: Automobile | F81: #156480655 | G81: They are into the heavy equipment (attachments & spare parts) business and are looking to use WorkDrive as a centralized DMS to manage their operations. | H81: Zoho Books + WorkDrive Integration and Automation to track missing documents when users miss to upload few files (e.g., if only partial files uploaded, system should notify). | I81: Notion, Google Drive | K81: Sales follow up 3 | L81: PSE565778 | M81: WD support - Chat/Call/Mail | N81: New Prospect | O81: Free User | P81: Deal Won | Q81: 6 | S81: Starter | U81: https://workdrive.zoho.in/file/6fmw0d74daf6691904fbbbff084c16cca8089 | V81: Spoke with the cx, the demo has been completed , and they need some time for product evalaution asked me to call on tuesday | W81: Books + WD - https://sprints.zoho.in/workspace/zdocs#P15/itemdetails/I7563 Automation to track missing - https://sprints.zoho.in/workspace/zdocs#P15/itemdetails/I7564
A82: 46101 | B82: IN | C82: Sakthi | D82: ashfaquedawre@bdo.in | E82: Financial service | F82: #156639884 | G82: The prospect was looking for interoperability between MS O 365 and Zoho WorkDrive. | K82: Do not follow | M82: Direct Mail to Presales | N82: New Prospect | O82: POC | P82: In Progress | Q82: 6000 | S82: WP flexi | U82: MS Teams Meeting
